Workbook
Name ListaContratos: '2027'!$E$8:$E$107

Sheet Instruções
A1: COMO PREENCHER — Superintendência Municipal de Distritos - SMD
A2: Guia rápido para quem alimenta os dados • Fluxo: aba 2027 → Ficha do contrato → Base de Dados → Dashboard
B4: ANTES DE COMEÇAR — ENTENDA AS CORES DAS CÉLULAS
B6: BRANCO | C6: Digitação manual — é aqui que você digita os dados.
B7: BEGE | C7: Lista suspensa — clique na célula e ESCOLHA uma opção (digitar livremente é rejeitado).
B8: AZUL CLARO | C8: Automático — preenche sozinho a partir de outra aba. Bloqueado para digitação.
B9: VERDE CLARO | C9: Calculado / alerta — resultado automático de fórmula. Bloqueado para digitação.
B11: PASSO 1 — CADASTRE O CONTRATO NA ABA «2027»
B13: • Use a primeira linha em branco da tabela (começa na linha 8). Uma linha por contrato, sem pular linhas.
B14: • Digite nas células brancas: processo SEI, contratada, CPF/CNPJ, nº do contrato/ano, objeto,
B15: datas de vigência (dd/mm/aaaa), valor mensal (apenas números, sem “R$”), meses vigentes e valor empenhado.
B16: • Escolha nas listas bege: Tipo de Objeto, Modalidade de Licitação, Regime de Execução e Tipo de Empenho.
B17: • As colunas azuis calculam sozinhas — ex.: Valor Total no Exercício = Valor Mensal × Meses Vigentes;
B18: Saldo a Empenhar = Valor Total − Valor Empenhado. A linha TOTAL, fixa no topo, soma tudo.
B20: ABA «PRETENSÕES 2027» — PLANEJAMENTO DE CONTRATAÇÕES FUTURAS
B22: • Registre as contratações que a unidade PRETENDE realizar em 2027 — uma linha por objeto pretendido.
B23: • Digite nas células brancas: objeto, quantidade, unidade de medida, valor estimado (apenas números), justificativa e observações.
B24: • Escolha nas listas bege: Tipo de Objeto, Trimestre Previsto, Grau de Prioridade e Fonte de Recursos.
B25: • A linha TOTAL, no topo, soma o valor estimado automaticamente.
... B62: EXEMPLO — competência de Julho/2027 paga por duas fontes:
B63: Período Ref. | C63: Nº Empenho | D63: Valor Pago (R$) | E63: Fonte de Recurso | F63: Observações
B64: Julho/2027 | C64: 2027NE0045 | D64: 30.000,00 | E64: Recurso Livre | F64: Parcela mensal – parte 1/2
B65: Julho/2027 | C65: 2027NE0051 | D65: 20.000,00 | E65: Convênio | F65: Parcela mensal – parte 2/2
B66: Resultado: o KPI 2.1 soma R$ 30.000 em Recurso Livre e R$ 20.000 em Convênio; o total do mês (R$ 50.000) fica correto automaticamente.
B69: GUIA RÁPIDO DAS LISTAS SUSPENSAS
B71: TIPO DE OBJETO — lista completa (selecionável nas abas 2027 e Pretensões 2027):
B72: Contratos Tradicionais de Compras e Serviços (Lei 14.133/2021)
B73: Contrato de Obras | C73: Construção, reforma ou ampliação de prédios públicos, escolas, postos de saúde e pontes.
B74: Contrato de Serviços de Engenharia | C74: Manutenção preventiva, reformas parciais, reparos asfálticos e sinalização viária.
B75: Contrato de Prestação de Serviços Contínuos | C75: Serviços essenciais do dia a dia: limpeza urbana, segurança patrimonial e TI.
B76: Contrato de Prestação de Serviços Técnicos Especializados | C76: Consultorias, auditorias externas, estudos de viabilidade ou projetos arquitetônicos.
B77: Contrato de Fornecimento Integral (Compras) | C77: Aquisição imediata ou parcelada de bens móveis (medicamentos, merenda, fardamentos, veículos).
B78: Contrato de Locação de Imóveis | C78: Aluguel de imóveis privados para abrigar secretarias, creches ou almoxarifados municipais.
B79: Contrato de Alienação | C79: Venda de bens públicos móveis inservíveis (carros velhos, sucata) ou imóveis autorizados por lei.
B81: Contratos de Concessão e Delegação de Serviços
B82: Concessão Comum de Serviço Público | C82: Serviço ao setor privado com remuneração via tarifa paga pelo usuário (ex.: transporte coletivo).
B83: Parceria Público-Privada (PPP) Administrativa | C83: Concessão em que o município é o usuário e paga integralmente (ex.: iluminação pública, hospital).
B84: Parceria Público-Privada (PPP) Patrocinada | C84: Tarifa paga pelo cidadão + complemento pago pela prefeitura (ex.: saneamento, água e esgoto).
B85: Permissão de Uso de Bem Público | C85: Uso precário de espaços públicos por particulares (ex.: quiosques, bancas, boxes de mercados).
B87: Parcerias com o Terceiro Setor (MROSC — Lei 13.019/2014)
B88: Termo de Colaboração | C88: Repasse de recursos para projetos propostos pelo município (ex.: vagas em creches comunitárias).
B89: Termo de Fomento * | C89: Repasse para projetos propostos pelas próprias OSCs. * Não está na lista suspensa — registrar em Observações.
B90: Acordo de Cooperação | C90: Parceria sem repasse de verba (ex.: ONG que assume a revitalização de um parque municipal).
B92: Instrumentos de Cooperação Intergovernamental
B93: Contrato de Consórcio Público | C93: União formal entre municípios para ratear custos e gerir demandas comuns (ex.: aterro regional).
B94: Convênio Administrativo | C94: Cooperação com o Estado ou a União para receber verbas de emendas ou programas específicos.
B96: REGIME DE EXECUÇÃO:
B97: Contrato Continuado | C97: Serviço essencial e permanente; a interrupção causa prejuízo (ex.: vigilância).
B98: Contrato não continuado | C98: Serviço esporádico ou temporário (ex.: uma reforma pontual).
B99: Contrato por Escopo | C99: Serviço/obra com objeto definido; termina quando o objeto é concluído e entregue (ex.: uma obra específica).
B101: TIPO DE EMPENHO:
B102: Ordinário | C102: Preço fixo + pagamento único.
B103: Global | C103: Preço fixo + pagamento parcelado.
B104: Estimativo | C104: Preço variável + pagamento conforme o consumo.
B106: FONTE DE RECURSO (na ficha — seção 5, uma por pagamento):
B107: Recurso Livre | C107: Recursos próprios sem destinação vinculada; uso livre pela Administração.
B108: Recurso Vinculado | C108: Recursos com destinação legal específica (ex.: educação, saúde).
B109: Convênio | C109: Recursos repassados por convênio/acordo com outro ente ou órgão.
B110: Operação de Crédito | C110: Recursos de empréstimo ou financiamento contratado pela Administração.
B111: Emendas Parlamentares | C111: Recursos indicados por emenda parlamentar.
B112: ⚠ IMPORTANTE — a Fonte de Recurso aparece em DOIS lugares, com finalidades diferentes:
B113: • Seção 1 (Identificação): mostra automaticamente a fonte PREDOMINANTE (a de maior valor pago) — vai para o dashboard. • Seção 5 (Pagamentos): informe a fonte de CADA pagamento — é o que alimenta o "Pago por Fonte" (KPI 2.1), a fonte predominante e o dashboard.
B114: Confira na Base de Dados a coluna "Verificação — Pago vs. Fonte": mostra "OK" quando tudo bate, ou avisa se houver pagamento sem fonte.
B116: DÚVIDAS RÁPIDAS
B118: A lista suspensa não aparece? → Clique na própria célula: a seta surge no canto direito dela.
B119: Erro ao tentar digitar? → A célula só aceita opções da lista (bege) ou é automática/bloqueada (azul ou verde).
B120: Coluna automática mostra “-” ou 0? → Falta algum dado usado na fórmula (ex.: valor mensal ou meses vigentes).
B121: Nº do contrato aparece em vermelho / “DUPLICADO”? → Esse Nº/Ano já foi usado em outra linha. Verifique e corrija — cada contrato deve ser único.
B125: Dúvidas não resolvidas? Procure a coordenação do Projeto SIGO — SEMEC / PMPV.

Sheet 2027
A1: UNIDADE: Superintendência Municipal de Distritos - SMD
A3: CONTROLE DE CONTRATOS VIGENTES — 2027
A5: TOTAL | M5: =SUM(M8:M107) -> 93551.81 | O5: =SUM(O8:O107) -> 1101021.7 | Q5: =SUM(Q8:Q107) -> 1085331.8 | R5: =SUM(R8:R107) -> 15689.96 | T5: =SUM(T8:T107) -> 5462.32 | U5: =SUM(U8:U107) -> 18220.68
A7: Nº | B7: Nº do Processo SEI | C7: Contratada (Nome/Razão Social) | D7: CPF/CNPJ da Contratada | E7: Nº do Contrato/Ano | F7: Tipo de Objeto | G7: Modalidade de Licitação | H7: Objeto do Contrato | I7: Regime de Execução | J7: Tipo de Empenho | K7: Início da Vigência | L7: Término da Vigência | M7: Valor Mensal do Contrato | N7: Meses Vigentes no Exercício | O7: Valor Total no Exercício 2027 | P7: Meses Empenhados | Q7: Valor Empenhado no Exercício | R7: Saldo a Empenhar | S7: % Empenhado no Exercício | T7: Saldo Orçamentário da Unidade | U7: Valor a Suplementar | V7: Observações | W7: Nº Duplicado?
A8: 1 | B8: 024.000147/2025-98 | C8: RECHE GALDEANO & CIA LTDA | D8: 08.713.403/0001-90 | E8: 66/2024 | F8: Contrato de Prestação de Serviços Contínuos | G8: Carona (ARP Externa) | H8: Locação de 11 veículos utilitários leves, sem condutor, para atendimento da sede e dos distritos. | I8: Contrato continuado | J8: Global | K8: 9/26/2024 | L8: 9/26/2027 | M8: 42393.45 | N8: 12 | O8: =IFERROR(M8*N8,0) -> 508721.4 | P8: =IFERROR(ROUNDDOWN(Q8/M8,0),0) -> 12 | Q8: 508721.4 | R8: =IFERROR(O8-Q8,0) -> 0 | S8: =IFERROR(Q8/O8,0) -> 1 | T8: 19.3 | U8: =IFERROR(R8-T8,0) -> -19.3 | V8: Projeção anual para 2027. Referência de 2026: R$ 508.721,40 empenhados. O saldo de R$ 19,30 do elemento 3.3.90.33, compartilhado com o Contrato nº 64/2025, foi registrado somente nesta linha para evitar duplicidade. | W8: =IF($E8="","",IF(COUNTIF($E$8:$E$107,$E8)>1,"DUPLICADO","OK")) -> OK
A9: 2 | B9: 024.000144/2025-54 | C9: ISAIAS RODRIGUES DOS ANJOS | D9: 768.916.742-04 | E9: 39/2022 | F9: Contrato de Locação de Imóveis | G9: Dispensa | H9: Locação do imóvel onde funciona a sede administrativa do Distrito de Extrema. | I9: Contrato continuado | J9: Global | K9: 7/23/2022 | L9: 7/22/2027 | M9: 4117 | N9: 12 | O9: =IFERROR(M9*N9,0) -> 49404 | P9: =IFERROR(ROUNDDOWN(Q9/M9,0),0) -> 12 | Q9: 49721 | R9: =IFERROR(O9-Q9,0) -> -317 | S9: =IFERROR(Q9/O9,0) -> 1.0064165 | T9: 1959.02 | U9: =IFERROR(R9-T9,0) -> -2276.02 | V9: Projeção anual para 2027. Referência de 2026: R$ 49.721,00 empenhados, considerando o processo principal e o processo apartado nº 024.000319/2026-12. O saldo de R$ 1.959,02 do elemento 3.3.90.36, compartilhado com as demais locações de pessoa física, foi registrado somente nesta linha. | W9: =IF($E9="","",IF(COUNTIF($E$8:$E$107,$E9)>1,"DUPLICADO","OK")) -> OK
A10: 3 | B10: 024.000200/2025-51 | C10: HELENA VASCONCELOS DE ALENCAR | D10: 161.816.892-49 | E10: 20/2023 | F10: Contrato de Locação de Imóveis | G10: Dispensa | H10: Locação do imóvel onde funciona a sede administrativa do Distrito de Nazaré. | I10: Contrato continuado | J10: Global | K10: 4/14/2023 | L10: 4/13/2027 | M10: 1095.11 | N10: 12 | O10: =IFERROR(M10*N10,0) -> 13141.32 | P10: =IFERROR(ROUNDDOWN(Q10/M10,0),0) -> 12 | Q10: 13443.69 | R10: =IFERROR(O10-Q10,0) -> -302.37 | S10: =IFERROR(Q10/O10,0) -> 1.0230091 | T10: - | U10: =IFERROR(R10-T10,0) -> 0 | V10: Projeção anual para 2027. Referência de 2026: R$ 13.443,69 empenhados. O saldo compartilhado do elemento 3.3.90.36 foi registrado na linha do Contrato nº 39/2022 para não ser somado em duplicidade. | W10: =IF($E10="","",IF(COUNTIF($E$8:$E$107,$E10)>1,"DUPLICADO","OK")) -> OK
A11: 4 | B11: 024.000150/2025-10 | C11: FUNDO PENITENCIARIO DO ESTADO DE RONDONIA - FUPEN | D11: 15.837.081/0001-56 | E11: 92/2023 | F11: Convênio Administrativo | H11: Cooperação para disponibilização de 1 reeducando em regime aberto, em atividade de serviços gerais na SMD. | I11: Contrato continuado | J11: Estimativo | K11: 45234 | L11: 46664 | M11: 2526.25 | N11: 12 | O11: =IFERROR(M11*N11,0) -> 30315 | P11: =IFERROR(ROUNDDOWN(Q11/M11,0),0) -> 12 | Q11: 31365.67 | R11: =IFERROR(O11-Q11,0) -> -1050.67 | S11: =IFERROR(Q11/O11,0) -> 1.0346584 | T11: - | U11: =IFERROR(R11-T11,0) -> 0 | V11: Projeção anual para 2027. Referência de 2026: R$ 31.365,67 empenhados líquidos, incluída a despesa de exercício anterior vinculada ao instrumento. Não foi identificado saldo livre específico no elemento para registro nesta linha. | W11: =IF($E11="","",IF(COUNTIF($E$8:$E$107,$E11)>1,"DUPLICADO","OK")) -> OK
A12: 5 | B12: 024.000145/2025-07 | C12: IMOBILIÁRIA ATRIUM LTDA | D12: 21.309.241/0001-97 | E12: 16/2023 | F12: Contrato de Locação de Imóveis | G12: Dispensa | H12: Locação do imóvel onde funciona a sede administrativa da SMD. | I12: Contrato continuado | J12: Global | K12: 3/16/2023 | L12: 9/14/2027 | M12: 13000 | N12: 12 | O12: =IFERROR(M12*N12,0) -> 156000 | P12: =IFERROR(ROUNDDOWN(Q12/M12,0),0) -> 12 | Q12: 156000 | R12: =IFERROR(O12-Q12,0) -> 0 | S12: =IFERROR(Q12/O12,0) -> 1 | T12: 3484 | U12: =IFERROR(R12-T12,0) -> -3484 | V12: Terceiro termo aditivo: vigência por 24 meses a partir de 15/09/2025 e aluguel mensal de R$ 13.000,00. Projeção anual para 2027. Referência de 2026: R$ 156.000,00 empenhados; saldo informado no elemento 3.3.90.39: R$ 3.484,00. | W12: =IF($E12="","",IF(COUNTIF($E$8:$E$107,$E12)>1,"DUPLICADO","OK")) -> OK
A13: 6 | B13: 024.000146/2025-43 | C13: LUCAS GOMES PATRICIO | D13: 019.472.152-30 | E13: 28/2018 | F13: Contrato de Locação de Imóveis | G13: Dispensa | H13: Locação do imóvel onde funciona a sede administrativa do Distrito de União Bandeirantes. | I13: Contrato continuado | J13: Global | K13: 4/17/2018 | L13: 10/15/2026 | M13: 1200 | N13: 4 | O13: =IFERROR(M13*N13,0) -> 4800 | P13: =IFERROR(ROUNDDOWN(Q13/M13,0),0) -> 9 | Q13: 11440 | R13: =IFERROR(O13-Q13,0) -> -6640 | S13: =IFERROR(Q13/O13,0) -> 2.3833333 | T13: - | U13: =IFERROR(R13-T13,0) -> 0 | V13: Oitavo termo aditivo vigente por seis meses a partir de 16/04/2026. A necessidade foi projetada para os 12 meses de 2027, mediante nova locação ou instrumento cabível. Referência de 2026: R$ 11.440,00 empenhados. O saldo compartilhado do elemento 3.3.90.36 foi registrado na linha de Extrema. | W13: =IF($E13="","",IF(COUNTIF($E$8:$E$107,$E13)>1,"DUPLICADO","OK")) -> OK
A14: 7 | B14: 024.000050/2025-85 | C14: KAELE LTDA | D14: 04.819.323/0001-62 | E14: 64/2025 | F14: Contrato de Prestação de Serviços Contínuos | G14: Carona (ARP Externa) | H14: Locação de 2 caminhonetes 4x4, sem condutor, para deslocamentos em ramais e localidades de difícil acesso. | I14: Contrato continuado | J14: Global | K14: 45728 | L14: 46065 | M14: 26220 | N14: 12 | O14: =IFERROR(M14*N14,0) -> 314640 | P14: =IFERROR(ROUNDDOWN(Q14/M14,0),0) -> 12 | Q14: 314640 | R14: =IFERROR(O14-Q14,0) -> 0 | S14: =IFERROR(Q14/O14,0) -> 1 | T14: - | U14: =IFERROR(R14-T14,0) -> 0 | V14: Contrato com prazo de 12 meses contado da assinatura em 03/12/2025. A continuidade foi projetada para todo o exercício de 2027. Referência de 2026: R$ 314.640,00 empenhados. O saldo compartilhado do elemento 3.3.90.33 foi registrado na linha do Contrato nº 66/2024. | W14: =IF($E14="","",IF(COUNTIF($E$8:$E$107,$E14)>1,"DUPLICADO","OK")) -> OK
A15: 8 | C15: LOCAÇÃO NOVO IMOVEL SEDE SMD EM UNIÃO BANDEIRANTES. | H15: Locação do imóvel onde funciona a sede administrativa do Distrito de União Bandeirantes. | M15: 3000 | N15: 8 | O15: =IFERROR(M15*N15,0) -> 24000 | P15: =IFERROR(ROUNDDOWN(Q15/M15,0),0) -> 0 | R15: =IFERROR(O15-Q15,0) -> 24000 | S15: =IFERROR(Q15/O15,0) -> 0 | U15: =IFERROR(R15-T15,0) -> 24000 | V15: Previsão para locação de novo imóvel destinado à sede administrativa do Distrito de União Bandeirantes, em substituição ao imóvel atualmente utilizado, cuja estrutura não oferece condições adequadas para o atendimento à população, o desenvolvimento das atividades administrativas e a guarda dos equipamentos da SMD. Prevê-se a prorrogação temporária da locação atual, de outubro de 2026 até abril de 2027, para assegurar a continuidade do atendimento, com início da instrução do novo processo em janeiro de 2027. A seleção observará a adequação do imóvel, a avaliação mercadológica, a regularidade documental e a busca pelo menor valor compatível com as necessidades da unidade, em atenção à economicidade e ao interesse público. | W15: =IF($E15="","",IF(COUNTIF($E$8:$E$107,$E15)>1,"DUPLICADO","OK"))
A16: 9 | O16: =IFERROR(M16*N16,0) -> 0 | P16: =IFERROR(ROUNDDOWN(Q16/M16,0),0) -> 0 | R16: =IFERROR(O16-Q16,0) -> 0 | S16: =IFERROR(Q16/O16,0) -> 0 | U16: =IFERROR(R16-T16,0) -> 0 | W16: =IF($E16="","",IF(COUNTIF($E$8:$E$107,$E16)>1,"DUPLICADO","OK"))
A17: 10 | O17: =IFERROR(M17*N17,0) -> 0 | P17: =IFERROR(ROUNDDOWN(Q17/M17,0),0) -> 0 | R17: =IFERROR(O17-Q17,0) -> 0 | S17: =IFERROR(Q17/O17,0) -> 0 | U17: =IFERROR(R17-T17,0) -> 0 | W17: =IF($E17="","",IF(COUNTIF($E$8:$E$107,$E17)>1,"DUPLICADO","OK"))
A18: 11 | O18: =IFERROR(M18*N18,0) -> 0 | P18: =IFERROR(ROUNDDOWN(Q18/M18,0),0) -> 0 | R18: =IFERROR(O18-Q18,0) -> 0 | S18: =IFERROR(Q18/O18,0) -> 0 | U18: =IFERROR(R18-T18,0) -> 0 | W18: =IF($E18="","",IF(COUNTIF($E$8:$E$107,$E18)>1,"DUPLICADO","OK"))
A19: 12 | O19: =IFERROR(M19*N19,0) -> 0 | P19: =IFERROR(ROUNDDOWN(Q19/M19,0),0) -> 0 | R19: =IFERROR(O19-Q19,0) -> 0 | S19: =IFERROR(Q19/O19,0) -> 0 | U19: =IFERROR(R19-T19,0) -> 0 | W19: =IF($E19="","",IF(COUNTIF($E$8:$E$107,$E19)>1,"DUPLICADO","OK"))
A20: 13 | O20: =IFERROR(M20*N20,0) -> 0 | P20: =IFERROR(ROUNDDOWN(Q20/M20,0),0) -> 0 | R20: =IFERROR(O20-Q20,0) -> 0 | S20: =IFERROR(Q20/O20,0) -> 0 | U20: =IFERROR(R20-T20,0) -> 0 | W20: =IF($E20="","",IF(COUNTIF($E$8:$E$107,$E20)>1,"DUPLICADO","OK"))
A21: 14 | O21: =IFERROR(M21*N21,0) -> 0 | P21: =IFERROR(ROUNDDOWN(Q21/M21,0),0) -> 0 | R21: =IFERROR(O21-Q21,0) -> 0 | S21: =IFERROR(Q21/O21,0) -> 0 | U21: =IFERROR(R21-T21,0) -> 0 | W21: =IF($E21="","",IF(COUNTIF($E$8:$E$107,$E21)>1,"DUPLICADO","OK"))
A22: 15 | O22: =IFERROR(M22*N22,0) -> 0 | P22: =IFERROR(ROUNDDOWN(Q22/M22,0),0) -> 0 | R22: =IFERROR(O22-Q22,0) -> 0 | S22: =IFERROR(Q22/O22,0) -> 0 | U22: =IFERROR(R22-T22,0) -> 0 | W22: =IF($E22="","",IF(COUNTIF($E$8:$E$107,$E22)>1,"DUPLICADO","OK"))
A23: 16 | O23: =IFERROR(M23*N23,0) -> 0 | P23: =IFERROR(ROUNDDOWN(Q23/M23,0),0) -> 0 | R23: =IFERROR(O23-Q23,0) -> 0 | S23: =IFERROR(Q23/O23,0) -> 0 | U23: =IFERROR(R23-T23,0) -> 0 | W23: =IF($E23="","",IF(COUNTIF($E$8:$E$107,$E23)>1,"DUPLICADO","OK"))
A24: 17 | O24: =IFERROR(M24*N24,0) -> 0 | P24: =IFERROR(ROUNDDOWN(Q24/M24,0),0) -> 0 | R24: =IFERROR(O24-Q24,0) -> 0 | S24: =IFERROR(Q24/O24,0) -> 0 | U24: =IFERROR(R24-T24,0) -> 0 | W24: =IF($E24="","",IF(COUNTIF($E$8:$E$107,$E24)>1,"DUPLICADO","OK"))
A25: 18 | O25: =IFERROR(M25*N25,0) -> 0 | P25: =IFERROR(ROUNDDOWN(Q25/M25,0),0) -> 0 | R25: =IFERROR(O25-Q25,0) -> 0 | S25: =IFERROR(Q25/O25,0) -> 0 | U25: =IFERROR(R25-T25,0) -> 0 | W25: =IF($E25="","",IF(COUNTIF($E$8:$E$107,$E25)>1,"DUPLICADO","OK"))
A26: 19 | O26: =IFERROR(M26*N26,0) -> 0 | P26: =IFERROR(ROUNDDOWN(Q26/M26,0),0) -> 0 | R26: =IFERROR(O26-Q26,0) -> 0 | S26: =IFERROR(Q26/O26,0) -> 0 | U26: =IFERROR(R26-T26,0) -> 0 | W26: =IF($E26="","",IF(COUNTIF($E$8:$E$107,$E26)>1,"DUPLICADO","OK"))
A27: 20 | O27: =IFERROR(M27*N27,0) -> 0 | P27: =IFERROR(ROUNDDOWN(Q27/M27,0),0) -> 0 | R27: =IFERROR(O27-Q27,0) -> 0 | S27: =IFERROR(Q27/O27,0) -> 0 | U27: =IFERROR(R27-T27,0) -> 0 | W27: =IF($E27="","",IF(COUNTIF($E$8:$E$107,$E27)>1,"DUPLICADO","OK"))
... A107: 100 | O107: =IFERROR(M107*N107,0) -> 0 | P107: =IFERROR(ROUNDDOWN(Q107/M107,0),0) -> 0 | R107: =IFERROR(O107-Q107,0) -> 0 | S107: =IFERROR(Q107/O107,0) -> 0 | U107: =IFERROR(R107-T107,0) -> 0 | W107: =IF($E107="","",IF(COUNTIF($E$8:$E$107,$E107)>1,"DUPLICADO","OK"))

Sheet Pretensões 2027
A1: UNIDADE: Superintendência Municipal de Distritos - SMD
A3: PLANEJAMENTO DE CONTRATAÇÕES — PRETENSÕES FUTURAS 2027
A5: TOTAL | F5: =SUM(F8:F107) -> 1409000
A7: Nº | B7: Objeto Pretendido | C7: Tipo de Objeto | D7: Quantidade Estimada | E7: Unidade de Medida | F7: Valor Estimado (R$) | G7: Trimestre Previsto para Contratação | H7: Grau de Prioridade | I7: Fonte de Recursos | J7: Justificativa da Necessidade | K7: Observações
A8: 1 | B8: Manutenção preventiva e corretiva da frota, com aquisição de peças, componentes, pneus e contratação dos serviços necessários | C8: Contrato de Prestação de Serviços Contínuos | D8: 1 | E8: Lote anual | F8: 175000 | G8: 1º Trimestre | H8: Alta | I8: Recursos Livres | J8: Assegurar a disponibilidade, a segurança e a continuidade operacional da frota utilizada no atendimento da sede e dos distritos, mediante manutenção preventiva e corretiva e fornecimento dos insumos necessários, reduzindo o risco de indisponibilidade dos veículos e de prejuízo às atividades administrativas e de campo. | K8: Planejamento anual consolidado no valor de R$ 175.000,00, abrangendo peças, componentes, pneus, materiais e serviços de manutenção. A modelagem da contratação, a eventual divisão em itens ou lotes, os quantitativos, as especificações e os preços de referência serão definidos no DFD e nos estudos técnicos, com base na identificação da frota, no histórico de manutenção e em pesquisa de preços.
A9: 2 | B9: Aquisição de água mineral para a sede e as 13 unidades distritais | C9: Contrato de Fornecimento Integral (Compras) | D9: 1 | E9: Lote anual | F9: 25000 | G9: 1º Trimestre | H9: Alta | I9: Recursos Livres | J9: Assegurar o fornecimento contínuo de água potável aos servidores e usuários da sede e das 13 unidades distritais durante o exercício. | K9: Estimativa anual sujeita ao detalhamento dos quantitativos no DFD, considerando o consumo projetado, o estoque disponível e os preços vigentes na data da contratação.
A10: 3 | B10: Aquisição de materiais de limpeza e higienização | C10: Contrato de Fornecimento Integral (Compras) | D10: 1 | E10: Lote anual | F10: 25000 | G10: 1º Trimestre | H10: Alta | I10: Recursos Livres | J10: Manter condições adequadas de limpeza, higienização, salubridade e conservação nos ambientes da sede e das 13 unidades distritais, prevenindo o desabastecimento de insumos necessários ao funcionamento regular das unidades. | K10: Estimativa anual para atendimento contínuo da sede e dos 13 distritos. Os quantitativos serão detalhados no DFD com base no consumo, no estoque e na pesquisa de preços. Papel higiênico, papel-toalha e guardanapos permanecem em item separado para evitar duplicidade.
A11: 4 | B11: Aquisição de copos descartáveis para água e café | C11: Contrato de Fornecimento Integral (Compras) | D11: 121 | E11: Caixas | F11: 15000 | G11: 1º Trimestre | H11: Alta | I11: Recursos Livres | J11: Atender ao consumo necessário para disponibilização de água e café na sede administrativa e nas 13 unidades distritais durante o exercício. | K11: Estimativa anual a ser detalhada no DFD, com definição dos tipos, capacidades e quantitativos conforme a demanda efetiva das unidades e a pesquisa de preços.
A12: 5 | B12: Aquisição de materiais de expediente para a sede e unidades distritais | C12: Contrato de Fornecimento Integral (Compras) | D12: 1 | E12: Lote anual | F12: 25000 | G12: 1º Trimestre | H12: Alta | I12: Recursos Livres | J12: Assegurar a continuidade da instrução processual, dos registros administrativos, do arquivamento e do atendimento realizado pela sede da SMD e pelas unidades distritais, evitando desabastecimento de insumos indispensáveis às rotinas de trabalho. | K12: Estimativa anual para atendimento da sede e dos 13 distritos. Os quantitativos e as especificações serão consolidados no DFD com base no consumo histórico, no estoque disponível e na pesquisa de preços, priorizando aquisição compatível com a demanda efetiva.
A13: 6 | B13: Aquisição de papel toalha, papel higiênico e guardanapos | C13: Contrato de Fornecimento Integral (Compras) | D13: 1560 | E13: Pacotes | F13: 20000 | G13: 1º Trimestre | H13: Alta | I13: Recursos Livres | J13: Assegurar o abastecimento contínuo de insumos de higiene e uso sanitário na sede e nas 13 unidades distritais, necessários à manutenção das condições de salubridade e ao atendimento regular de servidores e usuários. | K13: Estimativa anual para os 12 meses de 2027. Os quantitativos serão consolidados no DFD conforme consumo histórico, estoque disponível e pesquisa de preços, mantendo-se este objeto separado dos demais materiais de limpeza para controle e prevenção de duplicidade.
A14: 7 | B14: Aquisição de café, açúcar e recarga de gás de cozinha | C14: Contrato de Fornecimento Integral (Compras) | D14: 1 | E14: Lote anual | F14: 20000 | G14: 1º Trimestre | H14: Alta | I14: Recursos Livres | J14: Atender à rotina de copa da sede administrativa e das unidades distritais durante o exercício, com fornecimento regular dos insumos de consumo previstos. | K14: Estimativa anual para os 12 meses de 2027. Os quantitativos serão definidos no DFD conforme consumo projetado, estoque disponível e pesquisa de preços.
A15: 8 | B15: Diárias civis para deslocamentos institucionais e operacionais | D15: 1 | E15: Estimativa anual | F15: 120000 | G15: 1º Trimestre | H15: Alta | I15: Recursos Livres | J15: Custear deslocamentos de servidores para atendimento das atividades da sede, dos distritos e de localidades do Município. | K15: Previsão anual definida pela SMD. Despesa orçamentária não contratual, mantida nesta aba para demonstrar a necessidade integral de 2027.
A16: 9 | B16: Diárias indenizatórias para deslocamentos no território municipal | D16: 1 | E16: Estimativa anual | F16: 70000 | G16: 1º Trimestre | H16: Alta | I16: Recursos Livres | J16: Custear as indenizações de deslocamento necessárias às atividades de campo e ao atendimento dos distritos. | K16: Previsão anual definida pela SMD. Despesa orçamentária não contratual, mantida nesta aba para demonstrar a necessidade integral de 2027.
A17: 10 | B17: Suprimento de fundos para despesas com materiais de consumo e serviços de terceiros na sede e nos 13 distritos | D17: 1 | E17: Estimativa anual | F17: 140000 | G17: 1º Trimestre | H17: Alta | I17: Recursos Livres | J17: Viabilizar o atendimento de despesas excepcionais, urgentes, de pequeno vulto e de pronto pagamento, nas hipóteses admitidas pela regulamentação aplicável, abrangendo a aquisição de materiais de consumo e a contratação de serviços de terceiros necessários ao funcionamento da sede e das unidades distritais. | K17: Previsão anual unificada no valor de R$ 140.000,00, reunindo as necessidades anteriormente apresentadas em itens distintos para material de consumo e serviços de terceiros, sem duplicidade de recursos. A unificação possui finalidade de planejamento; na execução orçamentária, as despesas deverão ser classificadas, empenhadas e prestadas contas nos elementos correspondentes à sua natureza e de acordo com cada concessão.
A18: 11 | B18: Aquisição de cartuchos de toner para as impressoras da SMD | C18: Contrato de Fornecimento Integral (Compras) | D18: 50 | E18: Unidades | F18: 20000 | G18: 1º Trimestre | H18: Alta | I18: Recursos Livres | J18: Assegurar a continuidade da impressão de documentos necessários à instrução processual, às comunicações administrativas e ao atendimento das unidades que utilizam equipamentos próprios. | K18: Estimativa preliminar para atendimento durante os 12 meses de 2027. Os modelos, os quantitativos e a compatibilidade dos cartuchos serão definidos após o inventário das impressoras, a verificação do estoque e a consolidação do DFD, com posterior pesquisa de preços.
A19: 12 | B19: Aquisição de equipamentos de informática para a sede e unidades distritais | C19: Contrato de Fornecimento Integral (Compras) | D19: 1 | E19: Lote | F19: 50000 | G19: 2º Trimestre | H19: Alta | I19: Recursos Livres | J19: Substituir equipamentos defasados e estruturar os postos de trabalho da sede e dos distritos. | K19: Previsão inicial para aquisição gradual dos equipamentos de informática mais urgentes. O levantamento preliminar era superior, mas a dotação foi reduzida para reforçar os contratos continuados anualizados.
A20: 13 | B20: Aquisição de roçadeiras profissionais, motopodas telescópicas e kits de ferramentas | C20: Contrato de Fornecimento Integral (Compras) | D20: 40 | E20: Equipamentos e kits | F20: 80000 | G20: 1º Trimestre | H20: Alta | I20: Recursos Livres | J20: Atender os serviços de roçagem, poda e manutenção das áreas públicas nos 13 distritos. | K20: Previsão anual reforçada para aquisição de roçadeiras profissionais, motopodas telescópicas e kits de ferramentas destinados às atividades operacionais nos distritos. Os quantitativos e as especificações definitivas dependerão do levantamento técnico e da pesquisa de preços.
A21: 14 | B21: Aquisição de acessórios, peças e lubrificantes para roçadeiras e motopodas | C21: Contrato de Fornecimento Integral (Compras) | D21: 1 | E21: Lote anual | F21: 25000 | G21: 1º Trimestre | H21: Alta | I21: Recursos Livres | J21: Garantir o funcionamento e a manutenção dos equipamentos durante os 12 meses do exercício. | K21: Estimativa anual para acessórios, peças e lubrificantes necessários ao funcionamento das roçadeiras e motopodas. A relação definitiva será ajustada aos modelos dos equipamentos adquiridos.
A22: 15 | B22: Aquisição de equipamentos de proteção individual para operadores de roçadeiras e motopodas | C22: Contrato de Fornecimento Integral (Compras) | D22: 15 | E22: Kits | F22: 25000 | G22: 1º Trimestre | H22: Alta | I22: Recursos Livres | J22: Proteger os operadores durante os serviços de roçagem e poda nos distritos. | K22: Estimativa anual para equipamentos de proteção individual dos operadores. O valor foi dimensionado dentro da proposta global e será revisto após a definição das especificações e dos preços unitários.
A23: 16 | B23: Contratação de serviço de agenciamento de passagens aéreas | C23: Contrato de Prestação de Serviços Contínuos | D23: 20 | E23: Viagens completas | F23: 40000 | G23: 1º Trimestre | H23: Média | I23: Recursos Livres | J23: Atender viagens institucionais para capacitação, aperfeiçoamento e representação da SMD. | K23: Estimativa anual priorizada para agenciamento de passagens. O quantitativo será compatibilizado com o valor disponível, sem incluir diárias ou deslocamentos terrestres.
A24: 17 | B24: Reforma da sede administrativa do Distrito de Abunã | C24: Contrato de Serviços de Engenharia | D24: 1 | E24: Prédio | F24: 50000 | G24: 1º Trimestre | H24: Alta | I24: Recursos Livres | J24: Recuperar as condições de segurança, conservação e funcionamento da sede administrativa do Distrito de Abunã, mediante avaliação das necessidades de execução de muro, adequação do padrão e do poste de energia elétrica e serviços de pintura. As intervenções são necessárias à preservação do imóvel público e à continuidade do atendimento administrativo à população. | K24: Estimativa preliminar extraída do Relatório de Necessidade de Reparos de Sedes Próprias, sujeita à vistoria e ao estudo de viabilidade por equipe técnica de engenharia. A definição do escopo, dos quantitativos, das soluções construtivas, do cronograma e do orçamento de referência deverá preceder a contratação, com pesquisa de preços e seleção da alternativa tecnicamente adequada e economicamente mais vantajosa para a Administração.
A25: 18 | B25: Reforma e avaliação da adequação da sede administrativa do Distrito de Calama | C25: Contrato de Serviços de Engenharia | D25: 1 | E25: Prédio | F25: 200000 | G25: 1º Trimestre | H25: Alta | I25: Recursos Livres | J25: Restabelecer condições adequadas de uso da sede administrativa do Distrito de Calama, considerando a necessidade indicada de reparos nas instalações hidráulicas, recuperação do telhado e avaliação técnica da solução para ampliação, substituição ou construção de estrutura compatível com as atividades da unidade. A medida busca assegurar segurança, salubridade e continuidade dos serviços públicos no distrito. | K25: Estimativa preliminar extraída do Relatório de Necessidade de Reparos de Sedes Próprias, sujeita à vistoria e ao estudo de viabilidade por equipe técnica de engenharia. A definição do escopo, dos quantitativos, das soluções construtivas, do cronograma e do orçamento de referência deverá preceder a contratação, com pesquisa de preços e seleção da alternativa tecnicamente adequada e economicamente mais vantajosa para a Administração.
A26: 19 | B26: Reforma da sede administrativa do Distrito de Demarcação | C26: Contrato de Serviços de Engenharia | D26: 1 | E26: Prédio | F26: 15000 | G26: 1º Trimestre | H26: Alta | I26: Recursos Livres | J26: Adequar as condições de abastecimento de água e conservação da sede administrativa do Distrito de Demarcação, mediante avaliação para instalação de reservatório de água com capacidade estimada de 1.000 litros e execução de pintura, de modo a garantir condições mínimas de funcionamento e atendimento à população. | K26: Estimativa preliminar extraída do Relatório de Necessidade de Reparos de Sedes Próprias, sujeita à vistoria e ao estudo de viabilidade por equipe técnica de engenharia. A definição do escopo, dos quantitativos, das soluções construtivas, do cronograma e do orçamento de referência deverá preceder a contratação, com pesquisa de preços e seleção da alternativa tecnicamente adequada e economicamente mais vantajosa para a Administração.
A27: 20 | B27: Adequação das instalações elétricas da sede administrativa do Distrito de Fortaleza do Abunã | C27: Contrato de Serviços de Engenharia | D27: 1 | E27: Prédio | F27: 20000 | G27: 1º Trimestre | H27: Alta | I27: Recursos Livres | J27: Corrigir e adequar as instalações elétricas da sede administrativa do Distrito de Fortaleza do Abunã, reduzindo riscos à segurança de servidores, usuários, equipamentos e ao patrimônio público e assegurando condições regulares para a continuidade das atividades administrativas. | K27: Estimativa preliminar extraída do Relatório de Necessidade de Reparos de Sedes Próprias, sujeita à vistoria e ao estudo de viabilidade por equipe técnica de engenharia. A definição do escopo, dos quantitativos, das soluções construtivas, do cronograma e do orçamento de referência deverá preceder a contratação, com pesquisa de preços e seleção da alternativa tecnicamente adequada e economicamente mais vantajosa para a Administração.
A28: 21 | B28: Complementação da reforma da sede administrativa do Distrito de Jaci-Paraná | C28: Contrato de Serviços de Engenharia | D28: 1 | E28: Prédio | F28: 20000 | G28: 1º Trimestre | H28: Alta | I28: Recursos Livres | J28: Prever recursos para serviços complementares necessários à conclusão ou adequação da reforma em andamento na sede administrativa do Distrito de Jaci-Paraná, conforme apuração técnica do estágio da obra e das intervenções remanescentes, com o objetivo de restabelecer plenamente as condições de uso do imóvel. | K28: Estimativa preliminar extraída do Relatório de Necessidade de Reparos de Sedes Próprias, sujeita à vistoria e ao estudo de viabilidade por equipe técnica de engenharia. A definição do escopo, dos quantitativos, das soluções construtivas, do cronograma e do orçamento de referência deverá preceder a contratação, com pesquisa de preços e seleção da alternativa tecnicamente adequada e economicamente mais vantajosa para a Administração.
A29: 22 | B29: Reforma do pátio da sede administrativa do Distrito de Nova Califórnia | C29: Contrato de Serviços de Engenharia | D29: 1 | E29: Prédio | F29: 80000 | G29: 1º Trimestre | H29: Alta | I29: Recursos Livres | J29: Recuperar e adequar o pátio da sede administrativa do Distrito de Nova Califórnia, garantindo melhores condições de acesso, circulação, segurança e conservação do imóvel utilizado na prestação dos serviços públicos distritais. | K29: Estimativa preliminar extraída do Relatório de Necessidade de Reparos de Sedes Próprias, sujeita à vistoria e ao estudo de viabilidade por equipe técnica de engenharia. A definição do escopo, dos quantitativos, das soluções construtivas, do cronograma e do orçamento de referência deverá preceder a contratação, com pesquisa de preços e seleção da alternativa tecnicamente adequada e economicamente mais vantajosa para a Administração.
... A33: 26 | B33: Locação de imóvel para implantação da sede administrativa do Distrito de Rio Pardo | C33: Contrato de Locação de Imóveis | D33: 12 | E33: Mês | F33: 24000 | G33: 1º Trimestre | H33: Alta | I33: Recursos Livres | J33: Implantar estrutura física adequada para o funcionamento da administração distrital de Rio Pardo, que atualmente não dispõe de sede própria, assegurando local apropriado para o atendimento à população, o desenvolvimento das rotinas administrativas e a continuidade dos serviços públicos no distrito. | K33: Estimativa preliminar de até R$ 2.000,00 mensais, totalizando R$ 24.000,00 para 12 meses. A locação dependerá de estudo de viabilidade, definição das necessidades da unidade, pesquisa de mercado, avaliação do imóvel, regularidade documental e demonstração de compatibilidade do preço, buscando-se o menor valor possível entre as alternativas que atendam ao interesse público e aos requisitos técnicos.
A34: 27
A35: 28
A36: 29
A37: 30
A38: 31
A39: 32
A40: 33
A41: 34
A42: 35
A43: 36
A44: 37
A45: 38
... A107: 100

Sheet Base de Dados
A1: BASE DE DADOS — DESDOBRAMENTO INDIVIDUALIZADO POR CONTRATO | L1: =TRIM(MID('2027'!$A$1,FIND(":",'2027'!$A$1)+2,200)) -> Superintendência Municipal de Distritos - SMD
A2: 1. CADASTRO DO CONTRATO | AC2: 2. GESTÃO FINANCEIRA | AT2: 3. CONTROLE DA EXECUÇÃO | BA2: 4. ALTERAÇÕES CONTRATUAIS | BG2: 5. ALERTAS AUTOMÁTICOS | BN2: 6. PAGO POR FONTE DE RECURSO
A3: Nº do Contrato/Ano | B3: Ficha (nome da aba) | C3: Nº do Processo SEI | D3: Contratada (Nome/Razão Social) | E3: CPF/CNPJ da Contratada | F3: Nº do Contrato/Ano | G3: Tipo de Objeto | H3: Objeto do Contrato | J3: Regime de Execução | K3: Código da Ação | L3: Tipo de Empenho | M3: Início da Vigência | N3: Término da Vigência | O3: Unidade Gestora | Q3: Programa | R3: Natureza da Despesa | S3: Elemento de Despesa | T3: Fonte de Recurso | U3: Categoria Econômica | V3: Modalidade de Licitação | X3: Fiscal do Contrato | Y3: Gestor do Contrato | Z3: Valor Original do Contrato | AA3: Data de Assinatura | AB3: Situação | AC3: Exercício Financeiro | AD3: Valor Mensal do Contrato | AE3: Meses Vigentes no Exercício | AF3: Valor Total no Exercício | AG3: Dotação Inicial | AH3: Dotação Atualizada | AI3: Valor Empenhado no Exercício | AJ3: Valor Liquidado | AK3: Valor Pago | AL3: Saldo a Empenhar | AM3: Saldo a Liquidar | AN3: Saldo a Pagar | AO3: % Empenhado no Exercício | AP3: % Executado (Pago/Total) | AQ3: Restos a Pagar | AR3: Saldo Orçamentário da Unidade | AS3: Valor a Suplementar | AT3: Valor Executado no Mês | AV3: % Físico Executado | AW3: Última Medição | AX3: Próxima Medição | AY3: Último Pagamento | AZ3: Próximo Pagamento Previsto | BA3: Qtde de Aditivos | BB3: Valor Acrescido (Aditivos) | BC3: Valor Suprimido (Aditivos) | BD3: Novo Valor do Contrato | BE3: Nova Vigência (após aditivo) | BF3: Última Justificativa | BG3: Dias para Vencer | BH3: Vence em até 90 dias | BI3: Contrato Vencido | BJ3: Saldo a Empenhar < 20% | BK3: Execução acima de 90% | BL3: Sem pagamento há +60 dias | BM3: Observações | BN3: Pago — Recurso Livre | BO3: Pago — Recurso Vinculado | BP3: Pago — Convênio | BQ3: Pago — Operação de Crédito | BR3: Pago — Emendas Parlamentares | BS3: Verificação — Pago vs. Fonte
A4: =IF('2027'!$E$8="","",'2027'!$E$8) -> 66/2024 | B4: C01 | C4: =IF('2027'!$B$8="","",'2027'!$B$8) -> 024.000147/2025-98 | D4: =IF('2027'!$C$8="","",'2027'!$C$8) -> RECHE GALDEANO & CIA LTDA | E4: =IF('2027'!$D$8="","",'2027'!$D$8) -> 08.713.403/0001-90 | F4: =IF('2027'!$E$8="","",'2027'!$E$8) -> 66/2024 | G4: =IF('2027'!$F$8="","",'2027'!$F$8) -> Contrato de Prestação de Serviços Contínuos | H4: =IF('2027'!$H$8="","",'2027'!$H$8) -> Locação de 11 veículos utilitários leves, sem condutor, para atendimento da sede e dos distritos. | J4: =IF('2027'!$I$8="","",'2027'!$I$8) -> Contrato continuado | K4: =IF($B4="","",IFERROR(IF(INDIRECT("'"&$B4&"'!$B$10")="","",INDIRECT("'"&$B4&"'!$B$10")),"")) | L4: =IF('2027'!$J$8="","",'2027'!$J$8) -> Global | M4: =IF('2027'!$K$8="","",'2027'!$K$8) -> 9/26/2024 | N4: =IF('2027'!$L$8="","",'2027'!$L$8) -> 9/26/2027 | O4: =IF($B4="","","SMD") -> SMD | Q4: =IF($B4="","",IFERROR(IF(INDIRECT("'"&$B4&"'!$B$11")="","",INDIRECT("'"&$B4&"'!$B$11")),"")) | R4: =IF($B4="","",IFERROR(IF(INDIRECT("'"&$B4&"'!$F$11")="","",INDIRECT("'"&$B4&"'!$F$11")),"")) | S4: =IF($B4="","",IFERROR(IF(INDIRECT("'"&$B4&"'!$J$11")="","",INDIRECT("'"&$B4&"'!$J$11")),"")) | T4: =IF($B4="","",IFERROR(IF(INDIRECT("'"&$B4&"'!$J$10")="","",INDIRECT("'"&$B4&"'!$J$10")),"")) | U4: =IF($B4="","",IFERROR(IF(INDIRECT("'"&$B4&"'!$F$10")="","",INDIRECT("'"&$B4&"'!$F$10")),"")) | V4: =IF('2027'!$G$8="","",'2027'!$G$8) -> Carona (ARP Externa) | X4: =IF($B4="","",IFERROR(IF(INDIRECT("'"&$B4&"'!$F$12")="","",INDIRECT("'"&$B4&"'!$F$12")),"")) | Y4: =IF($B4="","",IFERROR(IF(INDIRECT("'"&$B4&"'!$B$12")="","",INDIRECT("'"&$B4&"'!$B$12")),"")) | Z4: =IF($B4="","",IFERROR(IF(INDIRECT("'"&$B4&"'!$J$13")="","",INDIRECT("'"&$B4&"'!$J$13")),"")) | AB4: =IF($B4="","",IFERROR(IF(INDIRECT("'"&$B4&"'!$J$4")="","",INDIRECT("'"&$B4&"'!$J$4")),"")) | AC4: =IF($B4="","",2026) -> 2026 | AD4: =IF('2027'!$M$8="","",'2027'!$M$8) -> 42393.45 | AE4: =IF('2027'!$N$8="","",'2027'!$N$8) -> 12 | AF4: =IF('2027'!$O$8="","",'2027'!$O$8) -> 508721.4 | AI4: =IF('2027'!$Q$8="","",'2027'!$Q$8) -> 508721.4 | AJ4: =IF($B4="","",IFERROR(IF(INDIRECT("'"&$B4&"'!$D$21")="","",INDIRECT("'"&$B4&"'!$D$21")),"")) -> 0 | AK4: =IF($B4="","",IFERROR(IF(INDIRECT("'"&$B4&"'!$E$21")="","",INDIRECT("'"&$B4&"'!$E$21")),"")) -> 0 | AL4: =IF('2027'!$R$8="","",'2027'!$R$8) -> 0 | AM4: =IFERROR(AI4-AJ4,0) -> 508721.4 | AN4: =IFERROR(AJ4-AK4,0) -> 0 | AO4: =IF('2027'!$S$8="","",'2027'!$S$8) -> 1 | AP4: =IFERROR(AK4/AF4,0) -> 0 | AQ4: =IF($B4="","",IFERROR(IF(INDIRECT("'"&$B4&"'!$K$21")="","",INDIRECT("'"&$B4&"'!$K$21")),"")) -> 0 | AR4: =IF('2027'!$T$8="","",'2027'!$T$8) -> 19.3 | AS4: =IF('2027'!$U$8="","",'2027'!$U$8) -> -19.3 | AT4: =IF($B4="","",IFERROR(IF(INDIRECT("'"&$B4&"'!$B$15")="","",INDIRECT("'"&$B4&"'!$B$15")),"")) -> 0 | AV4: =IF($B4="","",IFERROR(IF(INDIRECT("'"&$B4&"'!$B$14")="","",INDIRECT("'"&$B4&"'!$B$14")),"")) | AW4: =IF($B4="","",AY4) | AX4: =IF($B4="","",IFERROR(IF(INDIRECT("'"&$B4&"'!$F$14")="","",INDIRECT("'"&$B4&"'!$F$14")),"")) | AY4: =IF($B4="","",IFERROR(IF(INDIRECT("'"&$B4&"'!$D$35")="","",INDIRECT("'"&$B4&"'!$D$35")),"")) | AZ4: =IF($B4="","",IFERROR(IF(INDIRECT("'"&$B4&"'!$J$14")="","",INDIRECT("'"&$B4&"'!$J$14")),"")) | BA4: =IF($B4="","",IFERROR(IF(INDIRECT("'"&$B4&"'!$I$21")="","",INDIRECT("'"&$B4&"'!$I$21")),"")) -> 0 | BB4: =IF($B4="","",IFERROR(IF(INDIRECT("'"&$B4&"'!$C$67")="","",INDIRECT("'"&$B4&"'!$C$67")),"")) -> 0 | BC4: =IF($B4="","",IFERROR(IF(INDIRECT("'"&$B4&"'!$D$68")="","",INDIRECT("'"&$B4&"'!$D$68")),"")) -> 0 | BD4: =IFERROR(Z4+BB4-BC4,0) -> 0 | BE4: =IF($B4="","",IFERROR(IF(INDIRECT("'"&$B4&"'!$J$21")="","",INDIRECT("'"&$B4&"'!$J$21")),"")) | BF4: =IF($B4="","",IFERROR(IF(INDIRECT("'"&$B4&"'!$F$15")="","",INDIRECT("'"&$B4&"'!$F$15")),"")) | BG4: =IFERROR(N4-TODAY(),"") | BH4: =IF(N4="","",IF(AND(N4-TODAY()>=0,N4-TODAY()<=90),"Sim","Não")) -> #VALUE! | BI4: =IF(N4="","",IF(N4<TODAY(),"Sim","Não")) -> Não | BJ4: =IF(AF4=0,"",IF(IFERROR(AL4/AF4,0)<0.2,"Sim","Não")) -> Sim | BK4: =IF(AF4=0,"",IF(IFERROR(AK4/AF4,0)>0.9,"Sim","Não")) -> Não | BL4: =IF(AY4="","",IF(TODAY()-AY4>60,"Sim","Não")) | BM4: =IF('2027'!$V$8="","",'2027'!$V$8) -> Projeção anual para 2027. Referência de 2026: R$ 508.721,40 empenhados. O saldo de R$ 19,30 do elemento 3.3.90.33, compartilhado com o Contrato nº 64/2025, foi registrado somente nesta linha para evitar duplicidade. | BN4: =IF($B4="","",IFERROR(IF(INDIRECT("'"&$B4&"'!$B$24")="","",INDIRECT("'"&$B4&"'!$B$24")),"")) -> 0 | BO4: =IF($B4="","",IFERROR(IF(INDIRECT("'"&$B4&"'!$B$25")="","",INDIRECT("'"&$B4&"'!$B$25")),"")) -> 0 | BP4: =IF($B4="","",IFERROR(IF(INDIRECT("'"&$B4&"'!$B$26")="","",INDIRECT("'"&$B4&"'!$B$26")),"")) -> 0 | BQ4: =IF($B4="","",IFERROR(IF(INDIRECT("'"&$B4&"'!$B$27")="","",INDIRECT("'"&$B4&"'!$B$27")),"")) -> 0 | BR4: =IF($B4="","",IFERROR(IF(INDIRECT("'"&$B4&"'!$B$28")="","",INDIRECT("'"&$B4&"'!$B$28")),"")) -> 0 | BS4: =IF($B4="","",IF(AK4="","",IF(ROUND(AK4-SUM(BN4:BR4),2)>0,"Verificar — pagamento sem fonte",IF(ROUND(AK4-SUM(BN4:BR4),2)<0,"Verificar — fonte > pago","OK")))) -> OK
A5: =IF('2027'!$E$9="","",'2027'!$E$9) -> 39/2022 | C5: =IF('2027'!$B$9="","",'2027'!$B$9) -> 024.000144/2025-54 | D5: =IF('2027'!$C$9="","",'2027'!$C$9) -> ISAIAS RODRIGUES DOS ANJOS | E5: =IF('2027'!$D$9="","",'2027'!$D$9) -> 768.916.742-04 | F5: =IF('2027'!$E$9="","",'2027'!$E$9) -> 39/2022 | G5: =IF('2027'!$F$9="","",'2027'!$F$9) -> Contrato de Locação de Imóveis | H5: =IF('2027'!$H$9="","",'2027'!$H$9) -> Locação do imóvel onde funciona a sede administrativa do Distrito de Extrema. | J5: =IF('2027'!$I$9="","",'2027'!$I$9) -> Contrato continuado | K5: =IF($B5="","",IFERROR(IF(INDIRECT("'"&$B5&"'!$B$10")="","",INDIRECT("'"&$B5&"'!$B$10")),"")) | L5: =IF('2027'!$J$9="","",'2027'!$J$9) -> Global | M5: =IF('2027'!$K$9="","",'2027'!$K$9) -> 7/23/2022 | N5: =IF('2027'!$L$9="","",'2027'!$L$9) -> 7/22/2027 | O5: =IF($B5="","","SMD") | Q5: =IF($B5="","",IFERROR(IF(INDIRECT("'"&$B5&"'!$B$11")="","",INDIRECT("'"&$B5&"'!$B$11")),"")) | R5: =IF($B5="","",IFERROR(IF(INDIRECT("'"&$B5&"'!$F$11")="","",INDIRECT("'"&$B5&"'!$F$11")),"")) | S5: =IF($B5="","",IFERROR(IF(INDIRECT("'"&$B5&"'!$J$11")="","",INDIRECT("'"&$B5&"'!$J$11")),"")) | T5: =IF($B5="","",IFERROR(IF(INDIRECT("'"&$B5&"'!$J$10")="","",INDIRECT("'"&$B5&"'!$J$10")),"")) | U5: =IF($B5="","",IFERROR(IF(INDIRECT("'"&$B5&"'!$F$10")="","",INDIRECT("'"&$B5&"'!$F$10")),"")) | V5: =IF('2027'!$G$9="","",'2027'!$G$9) -> Dispensa | X5: =IF($B5="","",IFERROR(IF(INDIRECT("'"&$B5&"'!$F$12")="","",INDIRECT("'"&$B5&"'!$F$12")),"")) | Y5: =IF($B5="","",IFERROR(IF(INDIRECT("'"&$B5&"'!$B$12")="","",INDIRECT("'"&$B5&"'!$B$12")),"")) | Z5: =IF($B5="","",IFERROR(IF(INDIRECT("'"&$B5&"'!$J$13")="","",INDIRECT("'"&$B5&"'!$J$13")),"")) | AB5: =IF($B5="","",IFERROR(IF(INDIRECT("'"&$B5&"'!$J$4")="","",INDIRECT("'"&$B5&"'!$J$4")),"")) | AC5: =IF($B5="","",2026) | AD5: =IF('2027'!$M$9="","",'2027'!$M$9) -> 4117 | AE5: =IF('2027'!$N$9="","",'2027'!$N$9) -> 12 | AF5: =IF('2027'!$O$9="","",'2027'!$O$9) -> 49404 | AI5: =IF('2027'!$Q$9="","",'2027'!$Q$9) -> 49721 | AJ5: =IF($B5="","",IFERROR(IF(INDIRECT("'"&$B5&"'!$D$21")="","",INDIRECT("'"&$B5&"'!$D$21")),"")) | AK5: =IF($B5="","",IFERROR(IF(INDIRECT("'"&$B5&"'!$E$21")="","",INDIRECT("'"&$B5&"'!$E$21")),"")) | AL5: =IF('2027'!$R$9="","",'2027'!$R$9) -> -317 | AM5: =IFERROR(AI5-AJ5,0) -> 49721 | AN5: =IFERROR(AJ5-AK5,0) -> 0 | AO5: =IF('2027'!$S$9="","",'2027'!$S$9) -> 1.0064165 | AP5: =IFERROR(AK5/AF5,0) -> 0 | AQ5: =IF($B5="","",IFERROR(IF(INDIRECT("'"&$B5&"'!$K$21")="","",INDIRECT("'"&$B5&"'!$K$21")),"")) | AR5: =IF('2027'!$T$9="","",'2027'!$T$9) -> 1959.02 | AS5: =IF('2027'!$U$9="","",'2027'!$U$9) -> -2276.02 | AT5: =IF($B5="","",IFERROR(IF(INDIRECT("'"&$B5&"'!$B$15")="","",INDIRECT("'"&$B5&"'!$B$15")),"")) | AV5: =IF($B5="","",IFERROR(IF(INDIRECT("'"&$B5&"'!$B$14")="","",INDIRECT("'"&$B5&"'!$B$14")),"")) | AW5: =IF($B5="","",AY5) | AX5: =IF($B5="","",IFERROR(IF(INDIRECT("'"&$B5&"'!$F$14")="","",INDIRECT("'"&$B5&"'!$F$14")),"")) | AY5: =IF($B5="","",IFERROR(IF(INDIRECT("'"&$B5&"'!$D$35")="","",INDIRECT("'"&$B5&"'!$D$35")),"")) | AZ5: =IF($B5="","",IFERROR(IF(INDIRECT("'"&$B5&"'!$J$14")="","",INDIRECT("'"&$B5&"'!$J$14")),"")) | BA5: =IF($B5="","",IFERROR(IF(INDIRECT("'"&$B5&"'!$I$21")="","",INDIRECT("'"&$B5&"'!$I$21")),"")) | BB5: =IF($B5="","",IFERROR(IF(INDIRECT("'"&$B5&"'!$C$67")="","",INDIRECT("'"&$B5&"'!$C$67")),"")) | BC5: =IF($B5="","",IFERROR(IF(INDIRECT("'"&$B5&"'!$D$68")="","",INDIRECT("'"&$B5&"'!$D$68")),"")) | BD5: =IFERROR(Z5+BB5-BC5,0) -> 0 | BE5: =IF($B5="","",IFERROR(IF(INDIRECT("'"&$B5&"'!$J$21")="","",INDIRECT("'"&$B5&"'!$J$21")),"")) | BF5: =IF($B5="","",IFERROR(IF(INDIRECT("'"&$B5&"'!$F$15")="","",INDIRECT("'"&$B5&"'!$F$15")),"")) | BG5: =IFERROR(N5-TODAY(),"") | BH5: =IF(N5="","",IF(AND(N5-TODAY()>=0,N5-TODAY()<=90),"Sim","Não")) -> #VALUE! | BI5: =IF(N5="","",IF(N5<TODAY(),"Sim","Não")) -> Não | BJ5: =IF(AF5=0,"",IF(IFERROR(AL5/AF5,0)<0.2,"Sim","Não")) -> Sim | BK5: =IF(AF5=0,"",IF(IFERROR(AK5/AF5,0)>0.9,"Sim","Não")) -> Não | BL5: =IF(AY5="","",IF(TODAY()-AY5>60,"Sim","Não")) | BM5: =IF('2027'!$V$9="","",'2027'!$V$9) -> Projeção anual para 2027. Referência de 2026: R$ 49.721,00 empenhados, considerando o processo principal e o processo apartado nº 024.000319/2026-12. O saldo de R$ 1.959,02 do elemento 3.3.90.36, compartilhado com as demais locações de pessoa física, foi registrado somente nesta linha. | BN5: =IF($B5="","",IFERROR(IF(INDIRECT("'"&$B5&"'!$B$24")="","",INDIRECT("'"&$B5&"'!$B$24")),"")) | BO5: =IF($B5="","",IFERROR(IF(INDIRECT("'"&$B5&"'!$B$25")="","",INDIRECT("'"&$B5&"'!$B$25")),"")) | BP5: =IF($B5="","",IFERROR(IF(INDIRECT("'"&$B5&"'!$B$26")="","",INDIRECT("'"&$B5&"'!$B$26")),"")) | BQ5: =IF($B5="","",IFERROR(IF(INDIRECT("'"&$B5&"'!$B$27")="","",INDIRECT("'"&$B5&"'!$B$27")),"")) | BR5: =IF($B5="","",IFERROR(IF(INDIRECT("'"&$B5&"'!$B$28")="","",INDIRECT("'"&$B5&"'!$B$28")),"")) | BS5: =IF($B5="","",IF(AK5="","",IF(ROUND(AK5-SUM(BN5:BR5),2)>0,"Verificar — pagamento sem fonte",IF(ROUND(AK5-SUM(BN5:BR5),2)<0,"Verificar — fonte > pago","OK"))))
A6: =IF('2027'!$E$10="","",'2027'!$E$10) -> 20/2023 | C6: =IF('2027'!$B$10="","",'2027'!$B$10) -> 024.000200/2025-51 | D6: =IF('2027'!$C$10="","",'2027'!$C$10) -> HELENA VASCONCELOS DE ALENCAR | E6: =IF('2027'!$D$10="","",'2027'!$D$10) -> 161.816.892-49 | F6: =IF('2027'!$E$10="","",'2027'!$E$10) -> 20/2023 | G6: =IF('2027'!$F$10="","",'2027'!$F$10) -> Contrato de Locação de Imóveis | H6: =IF('2027'!$H$10="","",'2027'!$H$10) -> Locação do imóvel onde funciona a sede administrativa do Distrito de Nazaré. | J6: =IF('2027'!$I$10="","",'2027'!$I$10) -> Contrato continuado | K6: =IF($B6="","",IFERROR(IF(INDIRECT("'"&$B6&"'!$B$10")="","",INDIRECT("'"&$B6&"'!$B$10")),"")) | L6: =IF('2027'!$J$10="","",'2027'!$J$10) -> Global | M6: =IF('2027'!$K$10="","",'2027'!$K$10) -> 4/14/2023 | N6: =IF('2027'!$L$10="","",'2027'!$L$10) -> 4/13/2027 | O6: =IF($B6="","","SMD") | Q6: =IF($B6="","",IFERROR(IF(INDIRECT("'"&$B6&"'!$B$11")="","",INDIRECT("'"&$B6&"'!$B$11")),"")) | R6: =IF($B6="","",IFERROR(IF(INDIRECT("'"&$B6&"'!$F$11")="","",INDIRECT("'"&$B6&"'!$F$11")),"")) | S6: =IF($B6="","",IFERROR(IF(INDIRECT("'"&$B6&"'!$J$11")="","",INDIRECT("'"&$B6&"'!$J$11")),"")) | T6: =IF($B6="","",IFERROR(IF(INDIRECT("'"&$B6&"'!$J$10")="","",INDIRECT("'"&$B6&"'!$J$10")),"")) | U6: =IF($B6="","",IFERROR(IF(INDIRECT("'"&$B6&"'!$F$10")="","",INDIRECT("'"&$B6&"'!$F$10")),"")) | V6: =IF('2027'!$G$10="","",'2027'!$G$10) -> Dispensa | X6: =IF($B6="","",IFERROR(IF(INDIRECT("'"&$B6&"'!$F$12")="","",INDIRECT("'"&$B6&"'!$F$12")),"")) | Y6: =IF($B6="","",IFERROR(IF(INDIRECT("'"&$B6&"'!$B$12")="","",INDIRECT("'"&$B6&"'!$B$12")),"")) | Z6: =IF($B6="","",IFERROR(IF(INDIRECT("'"&$B6&"'!$J$13")="","",INDIRECT("'"&$B6&"'!$J$13")),"")) | AB6: =IF($B6="","",IFERROR(IF(INDIRECT("'"&$B6&"'!$J$4")="","",INDIRECT("'"&$B6&"'!$J$4")),"")) | AC6: =IF($B6="","",2026) | AD6: =IF('2027'!$M$10="","",'2027'!$M$10) -> 1095.11 | AE6: =IF('2027'!$N$10="","",'2027'!$N$10) -> 12 | AF6: =IF('2027'!$O$10="","",'2027'!$O$10) -> 13141.32 | AI6: =IF('2027'!$Q$10="","",'2027'!$Q$10) -> 13443.69 | AJ6: =IF($B6="","",IFERROR(IF(INDIRECT("'"&$B6&"'!$D$21")="","",INDIRECT("'"&$B6&"'!$D$21")),"")) | AK6: =IF($B6="","",IFERROR(IF(INDIRECT("'"&$B6&"'!$E$21")="","",INDIRECT("'"&$B6&"'!$E$21")),"")) | AL6: =IF('2027'!$R$10="","",'2027'!$R$10) -> -302.37 | AM6: =IFERROR(AI6-AJ6,0) -> 13443.69 | AN6: =IFERROR(AJ6-AK6,0) -> 0 | AO6: =IF('2027'!$S$10="","",'2027'!$S$10) -> 1.0230091 | AP6: =IFERROR(AK6/AF6,0) -> 0 | AQ6: =IF($B6="","",IFERROR(IF(INDIRECT("'"&$B6&"'!$K$21")="","",INDIRECT("'"&$B6&"'!$K$21")),"")) | AR6: =IF('2027'!$T$10="","",'2027'!$T$10) -> - | AS6: =IF('2027'!$U$10="","",'2027'!$U$10) -> 0 | AT6: =IF($B6="","",IFERROR(IF(INDIRECT("'"&$B6&"'!$B$15")="","",INDIRECT("'"&$B6&"'!$B$15")),"")) | AV6: =IF($B6="","",IFERROR(IF(INDIRECT("'"&$B6&"'!$B$14")="","",INDIRECT("'"&$B6&"'!$B$14")),"")) | AW6: =IF($B6="","",AY6) | AX6: =IF($B6="","",IFERROR(IF(INDIRECT("'"&$B6&"'!$F$14")="","",INDIRECT("'"&$B6&"'!$F$14")),"")) | AY6: =IF($B6="","",IFERROR(IF(INDIRECT("'"&$B6&"'!$D$35")="","",INDIRECT("'"&$B6&"'!$D$35")),"")) | AZ6: =IF($B6="","",IFERROR(IF(INDIRECT("'"&$B6&"'!$J$14")="","",INDIRECT("'"&$B6&"'!$J$14")),"")) | BA6: =IF($B6="","",IFERROR(IF(INDIRECT("'"&$B6&"'!$I$21")="","",INDIRECT("'"&$B6&"'!$I$21")),"")) | BB6: =IF($B6="","",IFERROR(IF(INDIRECT("'"&$B6&"'!$C$67")="","",INDIRECT("'"&$B6&"'!$C$67")),"")) | BC6: =IF($B6="","",IFERROR(IF(INDIRECT("'"&$B6&"'!$D$68")="","",INDIRECT("'"&$B6&"'!$D$68")),"")) | BD6: =IFERROR(Z6+BB6-BC6,0) -> 0 | BE6: =IF($B6="","",IFERROR(IF(INDIRECT("'"&$B6&"'!$J$21")="","",INDIRECT("'"&$B6&"'!$J$21")),"")) | BF6: =IF($B6="","",IFERROR(IF(INDIRECT("'"&$B6&"'!$F$15")="","",INDIRECT("'"&$B6&"'!$F$15")),"")) | BG6: =IFERROR(N6-TODAY(),"") | BH6: =IF(N6="","",IF(AND(N6-TODAY()>=0,N6-TODAY()<=90),"Sim","Não")) -> #VALUE! | BI6: =IF(N6="","",IF(N6<TODAY(),"Sim","Não")) -> Não | BJ6: =IF(AF6=0,"",IF(IFERROR(AL6/AF6,0)<0.2,"Sim","Não")) -> Sim | BK6: =IF(AF6=0,"",IF(IFERROR(AK6/AF6,0)>0.9,"Sim","Não")) -> Não | BL6: =IF(AY6="","",IF(TODAY()-AY6>60,"Sim","Não")) | BM6: =IF('2027'!$V$10="","",'2027'!$V$10) -> Projeção anual para 2027. Referência de 2026: R$ 13.443,69 empenhados. O saldo compartilhado do elemento 3.3.90.36 foi registrado na linha do Contrato nº 39/2022 para não ser somado em duplicidade. | BN6: =IF($B6="","",IFERROR(IF(INDIRECT("'"&$B6&"'!$B$24")="","",INDIRECT("'"&$B6&"'!$B$24")),"")) | BO6: =IF($B6="","",IFERROR(IF(INDIRECT("'"&$B6&"'!$B$25")="","",INDIRECT("'"&$B6&"'!$B$25")),"")) | BP6: =IF($B6="","",IFERROR(IF(INDIRECT("'"&$B6&"'!$B$26")="","",INDIRECT("'"&$B6&"'!$B$26")),"")) | BQ6: =IF($B6="","",IFERROR(IF(INDIRECT("'"&$B6&"'!$B$27")="","",INDIRECT("'"&$B6&"'!$B$27")),"")) | BR6: =IF($B6="","",IFERROR(IF(INDIRECT("'"&$B6&"'!$B$28")="","",INDIRECT("'"&$B6&"'!$B$28")),"")) | BS6: =IF($B6="","",IF(AK6="","",IF(ROUND(AK6-SUM(BN6:BR6),2)>0,"Verificar — pagamento sem fonte",IF(ROUND(AK6-SUM(BN6:BR6),2)<0,"Verificar — fonte > pago","OK"))))
A7: =IF('2027'!$E$11="","",'2027'!$E$11) -> 92/2023 | C7: =IF('2027'!$B$11="","",'2027'!$B$11) -> 024.000150/2025-10 | D7: =IF('2027'!$C$11="","",'2027'!$C$11) -> FUNDO PENITENCIARIO DO ESTADO DE RONDONIA - FUPEN | E7: =IF('2027'!$D$11="","",'2027'!$D$11) -> 15.837.081/0001-56 | F7: =IF('2027'!$E$11="","",'2027'!$E$11) -> 92/2023 | G7: =IF('2027'!$F$11="","",'2027'!$F$11) -> Convênio Administrativo | H7: =IF('2027'!$H$11="","",'2027'!$H$11) -> Cooperação para disponibilização de 1 reeducando em regime aberto, em atividade de serviços gerais na SMD. | J7: =IF('2027'!$I$11="","",'2027'!$I$11) -> Contrato continuado | K7: =IF($B7="","",IFERROR(IF(INDIRECT("'"&$B7&"'!$B$10")="","",INDIRECT("'"&$B7&"'!$B$10")),"")) | L7: =IF('2027'!$J$11="","",'2027'!$J$11) -> Estimativo | M7: =IF('2027'!$K$11="","",'2027'!$K$11) -> 45234 | N7: =IF('2027'!$L$11="","",'2027'!$L$11) -> 46664 | O7: =IF($B7="","","SMD") | Q7: =IF($B7="","",IFERROR(IF(INDIRECT("'"&$B7&"'!$B$11")="","",INDIRECT("'"&$B7&"'!$B$11")),"")) | R7: =IF($B7="","",IFERROR(IF(INDIRECT("'"&$B7&"'!$F$11")="","",INDIRECT("'"&$B7&"'!$F$11")),"")) | S7: =IF($B7="","",IFERROR(IF(INDIRECT("'"&$B7&"'!$J$11")="","",INDIRECT("'"&$B7&"'!$J$11")),"")) | T7: =IF($B7="","",IFERROR(IF(INDIRECT("'"&$B7&"'!$J$10")="","",INDIRECT("'"&$B7&"'!$J$10")),"")) | U7: =IF($B7="","",IFERROR(IF(INDIRECT("'"&$B7&"'!$F$10")="","",INDIRECT("'"&$B7&"'!$F$10")),"")) | V7: =IF('2027'!$G$11="","",'2027'!$G$11) | X7: =IF($B7="","",IFERROR(IF(INDIRECT("'"&$B7&"'!$F$12")="","",INDIRECT("'"&$B7&"'!$F$12")),"")) | Y7: =IF($B7="","",IFERROR(IF(INDIRECT("'"&$B7&"'!$B$12")="","",INDIRECT("'"&$B7&"'!$B$12")),"")) | Z7: =IF($B7="","",IFERROR(IF(INDIRECT("'"&$B7&"'!$J$13")="","",INDIRECT("'"&$B7&"'!$J$13")),"")) | AB7: =IF($B7="","",IFERROR(IF(INDIRECT("'"&$B7&"'!$J$4")="","",INDIRECT("'"&$B7&"'!$J$4")),"")) | AC7: =IF($B7="","",2026) | AD7: =IF('2027'!$M$11="","",'2027'!$M$11) -> 2526.25 | AE7: =IF('2027'!$N$11="","",'2027'!$N$11) -> 12 | AF7: =IF('2027'!$O$11="","",'2027'!$O$11) -> 30315 | AI7: =IF('2027'!$Q$11="","",'2027'!$Q$11) -> 31365.67 | AJ7: =IF($B7="","",IFERROR(IF(INDIRECT("'"&$B7&"'!$D$21")="","",INDIRECT("'"&$B7&"'!$D$21")),"")) | AK7: =IF($B7="","",IFERROR(IF(INDIRECT("'"&$B7&"'!$E$21")="","",INDIRECT("'"&$B7&"'!$E$21")),"")) | AL7: =IF('2027'!$R$11="","",'2027'!$R$11) -> -1050.67 | AM7: =IFERROR(AI7-AJ7,0) -> 31365.67 | AN7: =IFERROR(AJ7-AK7,0) -> 0 | AO7: =IF('2027'!$S$11="","",'2027'!$S$11) -> 1.0346584 | AP7: =IFERROR(AK7/AF7,0) -> 0 | AQ7: =IF($B7="","",IFERROR(IF(INDIRECT("'"&$B7&"'!$K$21")="","",INDIRECT("'"&$B7&"'!$K$21")),"")) | AR7: =IF('2027'!$T$11="","",'2027'!$T$11) -> - | AS7: =IF('2027'!$U$11="","",'2027'!$U$11) -> 0 | AT7: =IF($B7="","",IFERROR(IF(INDIRECT("'"&$B7&"'!$B$15")="","",INDIRECT("'"&$B7&"'!$B$15")),"")) | AV7: =IF($B7="","",IFERROR(IF(INDIRECT("'"&$B7&"'!$B$14")="","",INDIRECT("'"&$B7&"'!$B$14")),"")) | AW7: =IF($B7="","",AY7) | AX7: =IF($B7="","",IFERROR(IF(INDIRECT("'"&$B7&"'!$F$14")="","",INDIRECT("'"&$B7&"'!$F$14")),"")) | AY7: =IF($B7="","",IFERROR(IF(INDIRECT("'"&$B7&"'!$D$35")="","",INDIRECT("'"&$B7&"'!$D$35")),"")) | AZ7: =IF($B7="","",IFERROR(IF(INDIRECT("'"&$B7&"'!$J$14")="","",INDIRECT("'"&$B7&"'!$J$14")),"")) | BA7: =IF($B7="","",IFERROR(IF(INDIRECT("'"&$B7&"'!$I$21")="","",INDIRECT("'"&$B7&"'!$I$21")),"")) | BB7: =IF($B7="","",IFERROR(IF(INDIRECT("'"&$B7&"'!$C$67")="","",INDIRECT("'"&$B7&"'!$C$67")),"")) | BC7: =IF($B7="","",IFERROR(IF(INDIRECT("'"&$B7&"'!$D$68")="","",INDIRECT("'"&$B7&"'!$D$68")),"")) | BD7: =IFERROR(Z7+BB7-BC7,0) -> 0 | BE7: =IF($B7="","",IFERROR(IF(INDIRECT("'"&$B7&"'!$J$21")="","",INDIRECT("'"&$B7&"'!$J$21")),"")) | BF7: =IF($B7="","",IFERROR(IF(INDIRECT("'"&$B7&"'!$F$15")="","",INDIRECT("'"&$B7&"'!$F$15")),"")) | BG7: =IFERROR(N7-TODAY(),"") -> 406 | BH7: =IF(N7="","",IF(AND(N7-TODAY()>=0,N7-TODAY()<=90),"Sim","Não")) -> Não | BI7: =IF(N7="","",IF(N7<TODAY(),"Sim","Não")) -> Não | BJ7: =IF(AF7=0,"",IF(IFERROR(AL7/AF7,0)<0.2,"Sim","Não")) -> Sim | BK7: =IF(AF7=0,"",IF(IFERROR(AK7/AF7,0)>0.9,"Sim","Não")) -> Não | BL7: =IF(AY7="","",IF(TODAY()-AY7>60,"Sim","Não")) | BM7: =IF('2027'!$V$11="","",'2027'!$V$11) -> Projeção anual para 2027. Referência de 2026: R$ 31.365,67 empenhados líquidos, incluída a despesa de exercício anterior vinculada ao instrumento. Não foi identificado saldo livre específico no elemento para registro nesta linha. | BN7: =IF($B7="","",IFERROR(IF(INDIRECT("'"&$B7&"'!$B$24")="","",INDIRECT("'"&$B7&"'!$B$24")),"")) | BO7: =IF($B7="","",IFERROR(IF(INDIRECT("'"&$B7&"'!$B$25")="","",INDIRECT("'"&$B7&"'!$B$25")),"")) | BP7: =IF($B7="","",IFERROR(IF(INDIRECT("'"&$B7&"'!$B$26")="","",INDIRECT("'"&$B7&"'!$B$26")),"")) | BQ7: =IF($B7="","",IFERROR(IF(INDIRECT("'"&$B7&"'!$B$27")="","",INDIRECT("'"&$B7&"'!$B$27")),"")) | BR7: =IF($B7="","",IFERROR(IF(INDIRECT("'"&$B7&"'!$B$28")="","",INDIRECT("'"&$B7&"'!$B$28")),"")) | BS7: =IF($B7="","",IF(AK7="","",IF(ROUND(AK7-SUM(BN7:BR7),2)>0,"Verificar — pagamento sem fonte",IF(ROUND(AK7-SUM(BN7:BR7),2)<0,"Verificar — fonte > pago","OK"))))
A8: =IF('2027'!$E$12="","",'2027'!$E$12) -> 16/2023 | C8: =IF('2027'!$B$12="","",'2027'!$B$12) -> 024.000145/2025-07 | D8: =IF('2027'!$C$12="","",'2027'!$C$12) -> IMOBILIÁRIA ATRIUM LTDA | E8: =IF('2027'!$D$12="","",'2027'!$D$12) -> 21.309.241/0001-97 | F8: =IF('2027'!$E$12="","",'2027'!$E$12) -> 16/2023 | G8: =IF('2027'!$F$12="","",'2027'!$F$12) -> Contrato de Locação de Imóveis | H8: =IF('2027'!$H$12="","",'2027'!$H$12) -> Locação do imóvel onde funciona a sede administrativa da SMD. | J8: =IF('2027'!$I$12="","",'2027'!$I$12) -> Contrato continuado | K8: =IF($B8="","",IFERROR(IF(INDIRECT("'"&$B8&"'!$B$10")="","",INDIRECT("'"&$B8&"'!$B$10")),"")) | L8: =IF('2027'!$J$12="","",'2027'!$J$12) -> Global | M8: =IF('2027'!$K$12="","",'2027'!$K$12) -> 3/16/2023 | N8: =IF('2027'!$L$12="","",'2027'!$L$12) -> 9/14/2027 | O8: =IF($B8="","","SMD") | Q8: =IF($B8="","",IFERROR(IF(INDIRECT("'"&$B8&"'!$B$11")="","",INDIRECT("'"&$B8&"'!$B$11")),"")) | R8: =IF($B8="","",IFERROR(IF(INDIRECT("'"&$B8&"'!$F$11")="","",INDIRECT("'"&$B8&"'!$F$11")),"")) | S8: =IF($B8="","",IFERROR(IF(INDIRECT("'"&$B8&"'!$J$11")="","",INDIRECT("'"&$B8&"'!$J$11")),"")) | T8: =IF($B8="","",IFERROR(IF(INDIRECT("'"&$B8&"'!$J$10")="","",INDIRECT("'"&$B8&"'!$J$10")),"")) | U8: =IF($B8="","",IFERROR(IF(INDIRECT("'"&$B8&"'!$F$10")="","",INDIRECT("'"&$B8&"'!$F$10")),"")) | V8: =IF('2027'!$G$12="","",'2027'!$G$12) -> Dispensa | X8: =IF($B8="","",IFERROR(IF(INDIRECT("'"&$B8&"'!$F$12")="","",INDIRECT("'"&$B8&"'!$F$12")),"")) | Y8: =IF($B8="","",IFERROR(IF(INDIRECT("'"&$B8&"'!$B$12")="","",INDIRECT("'"&$B8&"'!$B$12")),"")) | Z8: =IF($B8="","",IFERROR(IF(INDIRECT("'"&$B8&"'!$J$13")="","",INDIRECT("'"&$B8&"'!$J$13")),"")) | AB8: =IF($B8="","",IFERROR(IF(INDIRECT("'"&$B8&"'!$J$4")="","",INDIRECT("'"&$B8&"'!$J$4")),"")) | AC8: =IF($B8="","",2026) | AD8: =IF('2027'!$M$12="","",'2027'!$M$12) -> 13000 | AE8: =IF('2027'!$N$12="","",'2027'!$N$12) -> 12 | AF8: =IF('2027'!$O$12="","",'2027'!$O$12) -> 156000 | AI8: =IF('2027'!$Q$12="","",'2027'!$Q$12) -> 156000 | AJ8: =IF($B8="","",IFERROR(IF(INDIRECT("'"&$B8&"'!$D$21")="","",INDIRECT("'"&$B8&"'!$D$21")),"")) | AK8: =IF($B8="","",IFERROR(IF(INDIRECT("'"&$B8&"'!$E$21")="","",INDIRECT("'"&$B8&"'!$E$21")),"")) | AL8: =IF('2027'!$R$12="","",'2027'!$R$12) -> 0 | AM8: =IFERROR(AI8-AJ8,0) -> 156000 | AN8: =IFERROR(AJ8-AK8,0) -> 0 | AO8: =IF('2027'!$S$12="","",'2027'!$S$12) -> 1 | AP8: =IFERROR(AK8/AF8,0) -> 0 | AQ8: =IF($B8="","",IFERROR(IF(INDIRECT("'"&$B8&"'!$K$21")="","",INDIRECT("'"&$B8&"'!$K$21")),"")) | AR8: =IF('2027'!$T$12="","",'2027'!$T$12) -> 3484 | AS8: =IF('2027'!$U$12="","",'2027'!$U$12) -> -3484 | AT8: =IF($B8="","",IFERROR(IF(INDIRECT("'"&$B8&"'!$B$15")="","",INDIRECT("'"&$B8&"'!$B$15")),"")) | AV8: =IF($B8="","",IFERROR(IF(INDIRECT("'"&$B8&"'!$B$14")="","",INDIRECT("'"&$B8&"'!$B$14")),"")) | AW8: =IF($B8="","",AY8) | AX8: =IF($B8="","",IFERROR(IF(INDIRECT("'"&$B8&"'!$F$14")="","",INDIRECT("'"&$B8&"'!$F$14")),"")) | AY8: =IF($B8="","",IFERROR(IF(INDIRECT("'"&$B8&"'!$D$35")="","",INDIRECT("'"&$B8&"'!$D$35")),"")) | AZ8: =IF($B8="","",IFERROR(IF(INDIRECT("'"&$B8&"'!$J$14")="","",INDIRECT("'"&$B8&"'!$J$14")),"")) | BA8: =IF($B8="","",IFERROR(IF(INDIRECT("'"&$B8&"'!$I$21")="","",INDIRECT("'"&$B8&"'!$I$21")),"")) | BB8: =IF($B8="","",IFERROR(IF(INDIRECT("'"&$B8&"'!$C$67")="","",INDIRECT("'"&$B8&"'!$C$67")),"")) | BC8: =IF($B8="","",IFERROR(IF(INDIRECT("'"&$B8&"'!$D$68")="","",INDIRECT("'"&$B8&"'!$D$68")),"")) | BD8: =IFERROR(Z8+BB8-BC8,0) -> 0 | BE8: =IF($B8="","",IFERROR(IF(INDIRECT("'"&$B8&"'!$J$21")="","",INDIRECT("'"&$B8&"'!$J$21")),"")) | BF8: =IF($B8="","",IFERROR(IF(INDIRECT("'"&$B8&"'!$F$15")="","",INDIRECT("'"&$B8&"'!$F$15")),"")) | BG8: =IFERROR(N8-TODAY(),"") | BH8: =IF(N8="","",IF(AND(N8-TODAY()>=0,N8-TODAY()<=90),"Sim","Não")) -> #VALUE! | BI8: =IF(N8="","",IF(N8<TODAY(),"Sim","Não")) -> Não | BJ8: =IF(AF8=0,"",IF(IFERROR(AL8/AF8,0)<0.2,"Sim","Não")) -> Sim | BK8: =IF(AF8=0,"",IF(IFERROR(AK8/AF8,0)>0.9,"Sim","Não")) -> Não | BL8: =IF(AY8="","",IF(TODAY()-AY8>60,"Sim","Não")) | BM8: =IF('2027'!$V$12="","",'2027'!$V$12) -> Terceiro termo aditivo: vigência por 24 meses a partir de 15/09/2025 e aluguel mensal de R$ 13.000,00. Projeção anual para 2027. Referência de 2026: R$ 156.000,00 empenhados; saldo informado no elemento 3.3.90.39: R$ 3.484,00. | BN8: =IF($B8="","",IFERROR(IF(INDIRECT("'"&$B8&"'!$B$24")="","",INDIRECT("'"&$B8&"'!$B$24")),"")) | BO8: =IF($B8="","",IFERROR(IF(INDIRECT("'"&$B8&"'!$B$25")="","",INDIRECT("'"&$B8&"'!$B$25")),"")) | BP8: =IF($B8="","",IFERROR(IF(INDIRECT("'"&$B8&"'!$B$26")="","",INDIRECT("'"&$B8&"'!$B$26")),"")) | BQ8: =IF($B8="","",IFERROR(IF(INDIRECT("'"&$B8&"'!$B$27")="","",INDIRECT("'"&$B8&"'!$B$27")),"")) | BR8: =IF($B8="","",IFERROR(IF(INDIRECT("'"&$B8&"'!$B$28")="","",INDIRECT("'"&$B8&"'!$B$28")),"")) | BS8: =IF($B8="","",IF(AK8="","",IF(ROUND(AK8-SUM(BN8:BR8),2)>0,"Verificar — pagamento sem fonte",IF(ROUND(AK8-SUM(BN8:BR8),2)<0,"Verificar — fonte > pago","OK"))))
A9: =IF('2027'!$E$13="","",'2027'!$E$13) -> 28/2018 | C9: =IF('2027'!$B$13="","",'2027'!$B$13) -> 024.000146/2025-43 | D9: =IF('2027'!$C$13="","",'2027'!$C$13) -> LUCAS GOMES PATRICIO | E9: =IF('2027'!$D$13="","",'2027'!$D$13) -> 019.472.152-30 | F9: =IF('2027'!$E$13="","",'2027'!$E$13) -> 28/2018 | G9: =IF('2027'!$F$13="","",'2027'!$F$13) -> Contrato de Locação de Imóveis | H9: =IF('2027'!$H$13="","",'2027'!$H$13) -> Locação do imóvel onde funciona a sede administrativa do Distrito de União Bandeirantes. | J9: =IF('2027'!$I$13="","",'2027'!$I$13) -> Contrato continuado | K9: =IF($B9="","",IFERROR(IF(INDIRECT("'"&$B9&"'!$B$10")="","",INDIRECT("'"&$B9&"'!$B$10")),"")) | L9: =IF('2027'!$J$13="","",'2027'!$J$13) -> Global | M9: =IF('2027'!$K$13="","",'2027'!$K$13) -> 4/17/2018 | N9: =IF('2027'!$L$13="","",'2027'!$L$13) -> 10/15/2026 | O9: =IF($B9="","","SMD") | Q9: =IF($B9="","",IFERROR(IF(INDIRECT("'"&$B9&"'!$B$11")="","",INDIRECT("'"&$B9&"'!$B$11")),"")) | R9: =IF($B9="","",IFERROR(IF(INDIRECT("'"&$B9&"'!$F$11")="","",INDIRECT("'"&$B9&"'!$F$11")),"")) | S9: =IF($B9="","",IFERROR(IF(INDIRECT("'"&$B9&"'!$J$11")="","",INDIRECT("'"&$B9&"'!$J$11")),"")) | T9: =IF($B9="","",IFERROR(IF(INDIRECT("'"&$B9&"'!$J$10")="","",INDIRECT("'"&$B9&"'!$J$10")),"")) | U9: =IF($B9="","",IFERROR(IF(INDIRECT("'"&$B9&"'!$F$10")="","",INDIRECT("'"&$B9&"'!$F$10")),"")) | V9: =IF('2027'!$G$13="","",'2027'!$G$13) -> Dispensa | X9: =IF($B9="","",IFERROR(IF(INDIRECT("'"&$B9&"'!$F$12")="","",INDIRECT("'"&$B9&"'!$F$12")),"")) | Y9: =IF($B9="","",IFERROR(IF(INDIRECT("'"&$B9&"'!$B$12")="","",INDIRECT("'"&$B9&"'!$B$12")),"")) | Z9: =IF($B9="","",IFERROR(IF(INDIRECT("'"&$B9&"'!$J$13")="","",INDIRECT("'"&$B9&"'!$J$13")),"")) | AB9: =IF($B9="","",IFERROR(IF(INDIRECT("'"&$B9&"'!$J$4")="","",INDIRECT("'"&$B9&"'!$J$4")),"")) | AC9: =IF($B9="","",2026) | AD9: =IF('2027'!$M$13="","",'2027'!$M$13) -> 1200 | AE9: =IF('2027'!$N$13="","",'2027'!$N$13) -> 4 | AF9: =IF('2027'!$O$13="","",'2027'!$O$13) -> 4800 | AI9: =IF('2027'!$Q$13="","",'2027'!$Q$13) -> 11440 | AJ9: =IF($B9="","",IFERROR(IF(INDIRECT("'"&$B9&"'!$D$21")="","",INDIRECT("'"&$B9&"'!$D$21")),"")) | AK9: =IF($B9="","",IFERROR(IF(INDIRECT("'"&$B9&"'!$E$21")="","",INDIRECT("'"&$B9&"'!$E$21")),"")) | AL9: =IF('2027'!$R$13="","",'2027'!$R$13) -> -6640 | AM9: =IFERROR(AI9-AJ9,0) -> 11440 | AN9: =IFERROR(AJ9-AK9,0) -> 0 | AO9: =IF('2027'!$S$13="","",'2027'!$S$13) -> 2.3833333 | AP9: =IFERROR(AK9/AF9,0) -> 0 | AQ9: =IF($B9="","",IFERROR(IF(INDIRECT("'"&$B9&"'!$K$21")="","",INDIRECT("'"&$B9&"'!$K$21")),"")) | AR9: =IF('2027'!$T$13="","",'2027'!$T$13) -> - | AS9: =IF('2027'!$U$13="","",'2027'!$U$13) -> 0 | AT9: =IF($B9="","",IFERROR(IF(INDIRECT("'"&$B9&"'!$B$15")="","",INDIRECT("'"&$B9&"'!$B$15")),"")) | AV9: =IF($B9="","",IFERROR(IF(INDIRECT("'"&$B9&"'!$B$14")="","",INDIRECT("'"&$B9&"'!$B$14")),"")) | AW9: =IF($B9="","",AY9) | AX9: =IF($B9="","",IFERROR(IF(INDIRECT("'"&$B9&"'!$F$14")="","",INDIRECT("'"&$B9&"'!$F$14")),"")) | AY9: =IF($B9="","",IFERROR(IF(INDIRECT("'"&$B9&"'!$D$35")="","",INDIRECT("'"&$B9&"'!$D$35")),"")) | AZ9: =IF($B9="","",IFERROR(IF(INDIRECT("'"&$B9&"'!$J$14")="","",INDIRECT("'"&$B9&"'!$J$14")),"")) | BA9: =IF($B9="","",IFERROR(IF(INDIRECT("'"&$B9&"'!$I$21")="","",INDIRECT("'"&$B9&"'!$I$21")),"")) | BB9: =IF($B9="","",IFERROR(IF(INDIRECT("'"&$B9&"'!$C$67")="","",INDIRECT("'"&$B9&"'!$C$67")),"")) | BC9: =IF($B9="","",IFERROR(IF(INDIRECT("'"&$B9&"'!$D$68")="","",INDIRECT("'"&$B9&"'!$D$68")),"")) | BD9: =IFERROR(Z9+BB9-BC9,0) -> 0 | BE9: =IF($B9="","",IFERROR(IF(INDIRECT("'"&$B9&"'!$J$21")="","",INDIRECT("'"&$B9&"'!$J$21")),"")) | BF9: =IF($B9="","",IFERROR(IF(INDIRECT("'"&$B9&"'!$F$15")="","",INDIRECT("'"&$B9&"'!$F$15")),"")) | BG9: =IFERROR(N9-TODAY(),"") | BH9: =IF(N9="","",IF(AND(N9-TODAY()>=0,N9-TODAY()<=90),"Sim","Não")) -> #VALUE! | BI9: =IF(N9="","",IF(N9<TODAY(),"Sim","Não")) -> Não | BJ9: =IF(AF9=0,"",IF(IFERROR(AL9/AF9,0)<0.2,"Sim","Não")) -> Sim | BK9: =IF(AF9=0,"",IF(IFERROR(AK9/AF9,0)>0.9,"Sim","Não")) -> Não | BL9: =IF(AY9="","",IF(TODAY()-AY9>60,"Sim","Não")) | BM9: =IF('2027'!$V$13="","",'2027'!$V$13) -> Oitavo termo aditivo vigente por seis meses a partir de 16/04/2026. A necessidade foi projetada para os 12 meses de 2027, mediante nova locação ou instrumento cabível. Referência de 2026: R$ 11.440,00 empenhados. O saldo compartilhado do elemento 3.3.90.36 foi registrado na linha de Extrema. | BN9: =IF($B9="","",IFERROR(IF(INDIRECT("'"&$B9&"'!$B$24")="","",INDIRECT("'"&$B9&"'!$B$24")),"")) | BO9: =IF($B9="","",IFERROR(IF(INDIRECT("'"&$B9&"'!$B$25")="","",INDIRECT("'"&$B9&"'!$B$25")),"")) | BP9: =IF($B9="","",IFERROR(IF(INDIRECT("'"&$B9&"'!$B$26")="","",INDIRECT("'"&$B9&"'!$B$26")),"")) | BQ9: =IF($B9="","",IFERROR(IF(INDIRECT("'"&$B9&"'!$B$27")="","",INDIRECT("'"&$B9&"'!$B$27")),"")) | BR9: =IF($B9="","",IFERROR(IF(INDIRECT("'"&$B9&"'!$B$28")="","",INDIRECT("'"&$B9&"'!$B$28")),"")) | BS9: =IF($B9="","",IF(AK9="","",IF(ROUND(AK9-SUM(BN9:BR9),2)>0,"Verificar — pagamento sem fonte",IF(ROUND(AK9-SUM(BN9:BR9),2)<0,"Verificar — fonte > pago","OK"))))
A10: =IF('2027'!$E$14="","",'2027'!$E$14) -> 64/2025 | C10: =IF('2027'!$B$14="","",'2027'!$B$14) -> 024.000050/2025-85 | D10: =IF('2027'!$C$14="","",'2027'!$C$14) -> KAELE LTDA | E10: =IF('2027'!$D$14="","",'2027'!$D$14) -> 04.819.323/0001-62 | F10: =IF('2027'!$E$14="","",'2027'!$E$14) -> 64/2025 | G10: =IF('2027'!$F$14="","",'2027'!$F$14) -> Contrato de Prestação de Serviços Contínuos | H10: =IF('2027'!$H$14="","",'2027'!$H$14) -> Locação de 2 caminhonetes 4x4, sem condutor, para deslocamentos em ramais e localidades de difícil acesso. | J10: =IF('2027'!$I$14="","",'2027'!$I$14) -> Contrato continuado | K10: =IF($B10="","",IFERROR(IF(INDIRECT("'"&$B10&"'!$B$10")="","",INDIRECT("'"&$B10&"'!$B$10")),"")) | L10: =IF('2027'!$J$14="","",'2027'!$J$14) -> Global | M10: =IF('2027'!$K$14="","",'2027'!$K$14) -> 45728 | N10: =IF('2027'!$L$14="","",'2027'!$L$14) -> 46065 | O10: =IF($B10="","","SMD") | Q10: =IF($B10="","",IFERROR(IF(INDIRECT("'"&$B10&"'!$B$11")="","",INDIRECT("'"&$B10&"'!$B$11")),"")) | R10: =IF($B10="","",IFERROR(IF(INDIRECT("'"&$B10&"'!$F$11")="","",INDIRECT("'"&$B10&"'!$F$11")),"")) | S10: =IF($B10="","",IFERROR(IF(INDIRECT("'"&$B10&"'!$J$11")="","",INDIRECT("'"&$B10&"'!$J$11")),"")) | T10: =IF($B10="","",IFERROR(IF(INDIRECT("'"&$B10&"'!$J$10")="","",INDIRECT("'"&$B10&"'!$J$10")),"")) | U10: =IF($B10="","",IFERROR(IF(INDIRECT("'"&$B10&"'!$F$10")="","",INDIRECT("'"&$B10&"'!$F$10")),"")) | V10: =IF('2027'!$G$14="","",'2027'!$G$14) -> Carona (ARP Externa) | X10: =IF($B10="","",IFERROR(IF(INDIRECT("'"&$B10&"'!$F$12")="","",INDIRECT("'"&$B10&"'!$F$12")),"")) | Y10: =IF($B10="","",IFERROR(IF(INDIRECT("'"&$B10&"'!$B$12")="","",INDIRECT("'"&$B10&"'!$B$12")),"")) | Z10: =IF($B10="","",IFERROR(IF(INDIRECT("'"&$B10&"'!$J$13")="","",INDIRECT("'"&$B10&"'!$J$13")),"")) | AB10: =IF($B10="","",IFERROR(IF(INDIRECT("'"&$B10&"'!$J$4")="","",INDIRECT("'"&$B10&"'!$J$4")),"")) | AC10: =IF($B10="","",2026) | AD10: =IF('2027'!$M$14="","",'2027'!$M$14) -> 26220 | AE10: =IF('2027'!$N$14="","",'2027'!$N$14) -> 12 | AF10: =IF('2027'!$O$14="","",'2027'!$O$14) -> 314640 | AI10: =IF('2027'!$Q$14="","",'2027'!$Q$14) -> 314640 | AJ10: =IF($B10="","",IFERROR(IF(INDIRECT("'"&$B10&"'!$D$21")="","",INDIRECT("'"&$B10&"'!$D$21")),"")) | AK10: =IF($B10="","",IFERROR(IF(INDIRECT("'"&$B10&"'!$E$21")="","",INDIRECT("'"&$B10&"'!$E$21")),"")) | AL10: =IF('2027'!$R$14="","",'2027'!$R$14) -> 0 | AM10: =IFERROR(AI10-AJ10,0) -> 314640 | AN10: =IFERROR(AJ10-AK10,0) -> 0 | AO10: =IF('2027'!$S$14="","",'2027'!$S$14) -> 1 | AP10: =IFERROR(AK10/AF10,0) -> 0 | AQ10: =IF($B10="","",IFERROR(IF(INDIRECT("'"&$B10&"'!$K$21")="","",INDIRECT("'"&$B10&"'!$K$21")),"")) | AR10: =IF('2027'!$T$14="","",'2027'!$T$14) -> - | AS10: =IF('2027'!$U$14="","",'2027'!$U$14) -> 0 | AT10: =IF($B10="","",IFERROR(IF(INDIRECT("'"&$B10&"'!$B$15")="","",INDIRECT("'"&$B10&"'!$B$15")),"")) | AV10: =IF($B10="","",IFERROR(IF(INDIRECT("'"&$B10&"'!$B$14")="","",INDIRECT("'"&$B10&"'!$B$14")),"")) | AW10: =IF($B10="","",AY10) | AX10: =IF($B10="","",IFERROR(IF(INDIRECT("'"&$B10&"'!$F$14")="","",INDIRECT("'"&$B10&"'!$F$14")),"")) | AY10: =IF($B10="","",IFERROR(IF(INDIRECT("'"&$B10&"'!$D$35")="","",INDIRECT("'"&$B10&"'!$D$35")),"")) | AZ10: =IF($B10="","",IFERROR(IF(INDIRECT("'"&$B10&"'!$J$14")="","",INDIRECT("'"&$B10&"'!$J$14")),"")) | BA10: =IF($B10="","",IFERROR(IF(INDIRECT("'"&$B10&"'!$I$21")="","",INDIRECT("'"&$B10&"'!$I$21")),"")) | BB10: =IF($B10="","",IFERROR(IF(INDIRECT("'"&$B10&"'!$C$67")="","",INDIRECT("'"&$B10&"'!$C$67")),"")) | BC10: =IF($B10="","",IFERROR(IF(INDIRECT("'"&$B10&"'!$D$68")="","",INDIRECT("'"&$B10&"'!$D$68")),"")) | BD10: =IFERROR(Z10+BB10-BC10,0) -> 0 | BE10: =IF($B10="","",IFERROR(IF(INDIRECT("'"&$B10&"'!$J$21")="","",INDIRECT("'"&$B10&"'!$J$21")),"")) | BF10: =IF($B10="","",IFERROR(IF(INDIRECT("'"&$B10&"'!$F$15")="","",INDIRECT("'"&$B10&"'!$F$15")),"")) | BG10: =IFERROR(N10-TODAY(),"") -> -193 | BH10: =IF(N10="","",IF(AND(N10-TODAY()>=0,N10-TODAY()<=90),"Sim","Não")) -> Não | BI10: =IF(N10="","",IF(N10<TODAY(),"Sim","Não")) -> Sim | BJ10: =IF(AF10=0,"",IF(IFERROR(AL10/AF10,0)<0.2,"Sim","Não")) -> Sim | BK10: =IF(AF10=0,"",IF(IFERROR(AK10/AF10,0)>0.9,"Sim","Não")) -> Não | BL10: =IF(AY10="","",IF(TODAY()-AY10>60,"Sim","Não")) | BM10: =IF('2027'!$V$14="","",'2027'!$V$14) -> Contrato com prazo de 12 meses contado da assinatura em 03/12/2025. A continuidade foi projetada para todo o exercício de 2027. Referência de 2026: R$ 314.640,00 empenhados. O saldo compartilhado do elemento 3.3.90.33 foi registrado na linha do Contrato nº 66/2024. | BN10: =IF($B10="","",IFERROR(IF(INDIRECT("'"&$B10&"'!$B$24")="","",INDIRECT("'"&$B10&"'!$B$24")),"")) | BO10: =IF($B10="","",IFERROR(IF(INDIRECT("'"&$B10&"'!$B$25")="","",INDIRECT("'"&$B10&"'!$B$25")),"")) | BP10: =IF($B10="","",IFERROR(IF(INDIRECT("'"&$B10&"'!$B$26")="","",INDIRECT("'"&$B10&"'!$B$26")),"")) | BQ10: =IF($B10="","",IFERROR(IF(INDIRECT("'"&$B10&"'!$B$27")="","",INDIRECT("'"&$B10&"'!$B$27")),"")) | BR10: =IF($B10="","",IFERROR(IF(INDIRECT("'"&$B10&"'!$B$28")="","",INDIRECT("'"&$B10&"'!$B$28")),"")) | BS10: =IF($B10="","",IF(AK10="","",IF(ROUND(AK10-SUM(BN10:BR10),2)>0,"Verificar — pagamento sem fonte",IF(ROUND(AK10-SUM(BN10:BR10),2)<0,"Verificar — fonte > pago","OK"))))
A11: =IF('2027'!$E$15="","",'2027'!$E$15) | C11: =IF('2027'!$B$15="","",'2027'!$B$15) | D11: =IF('2027'!$C$15="","",'2027'!$C$15) -> LOCAÇÃO NOVO IMOVEL SEDE SMD EM UNIÃO BANDEIRANTES. | E11: =IF('2027'!$D$15="","",'2027'!$D$15) | F11: =IF('2027'!$E$15="","",'2027'!$E$15) | G11: =IF('2027'!$F$15="","",'2027'!$F$15) | H11: =IF('2027'!$H$15="","",'2027'!$H$15) -> Locação do imóvel onde funciona a sede administrativa do Distrito de União Bandeirantes. | J11: =IF('2027'!$I$15="","",'2027'!$I$15) | K11: =IF($B11="","",IFERROR(IF(INDIRECT("'"&$B11&"'!$B$10")="","",INDIRECT("'"&$B11&"'!$B$10")),"")) | L11: =IF('2027'!$J$15="","",'2027'!$J$15) | M11: =IF('2027'!$K$15="","",'2027'!$K$15) | N11: =IF('2027'!$L$15="","",'2027'!$L$15) | O11: =IF($B11="","","SMD") | Q11: =IF($B11="","",IFERROR(IF(INDIRECT("'"&$B11&"'!$B$11")="","",INDIRECT("'"&$B11&"'!$B$11")),"")) | R11: =IF($B11="","",IFERROR(IF(INDIRECT("'"&$B11&"'!$F$11")="","",INDIRECT("'"&$B11&"'!$F$11")),"")) | S11: =IF($B11="","",IFERROR(IF(INDIRECT("'"&$B11&"'!$J$11")="","",INDIRECT("'"&$B11&"'!$J$11")),"")) | T11: =IF($B11="","",IFERROR(IF(INDIRECT("'"&$B11&"'!$J$10")="","",INDIRECT("'"&$B11&"'!$J$10")),"")) | U11: =IF($B11="","",IFERROR(IF(INDIRECT("'"&$B11&"'!$F$10")="","",INDIRECT("'"&$B11&"'!$F$10")),"")) | V11: =IF('2027'!$G$15="","",'2027'!$G$15) | X11: =IF($B11="","",IFERROR(IF(INDIRECT("'"&$B11&"'!$F$12")="","",INDIRECT("'"&$B11&"'!$F$12")),"")) | Y11: =IF($B11="","",IFERROR(IF(INDIRECT("'"&$B11&"'!$B$12")="","",INDIRECT("'"&$B11&"'!$B$12")),"")) | Z11: =IF($B11="","",IFERROR(IF(INDIRECT("'"&$B11&"'!$J$13")="","",INDIRECT("'"&$B11&"'!$J$13")),"")) | AB11: =IF($B11="","",IFERROR(IF(INDIRECT("'"&$B11&"'!$J$4")="","",INDIRECT("'"&$B11&"'!$J$4")),"")) | AC11: =IF($B11="","",2026) | AD11: =IF('2027'!$M$15="","",'2027'!$M$15) -> 3000 | AE11: =IF('2027'!$N$15="","",'2027'!$N$15) -> 8 | AF11: =IF('2027'!$O$15="","",'2027'!$O$15) -> 24000 | AI11: =IF('2027'!$Q$15="","",'2027'!$Q$15) | AJ11: =IF($B11="","",IFERROR(IF(INDIRECT("'"&$B11&"'!$D$21")="","",INDIRECT("'"&$B11&"'!$D$21")),"")) | AK11: =IF($B11="","",IFERROR(IF(INDIRECT("'"&$B11&"'!$E$21")="","",INDIRECT("'"&$B11&"'!$E$21")),"")) | AL11: =IF('2027'!$R$15="","",'2027'!$R$15) -> 24000 | AM11: =IFERROR(AI11-AJ11,0) -> 0 | AN11: =IFERROR(AJ11-AK11,0) -> 0 | AO11: =IF('2027'!$S$15="","",'2027'!$S$15) -> 0 | AP11: =IFERROR(AK11/AF11,0) -> 0 | AQ11: =IF($B11="","",IFERROR(IF(INDIRECT("'"&$B11&"'!$K$21")="","",INDIRECT("'"&$B11&"'!$K$21")),"")) | AR11: =IF('2027'!$T$15="","",'2027'!$T$15) | AS11: =IF('2027'!$U$15="","",'2027'!$U$15) -> 24000 | AT11: =IF($B11="","",IFERROR(IF(INDIRECT("'"&$B11&"'!$B$15")="","",INDIRECT("'"&$B11&"'!$B$15")),"")) | AV11: =IF($B11="","",IFERROR(IF(INDIRECT("'"&$B11&"'!$B$14")="","",INDIRECT("'"&$B11&"'!$B$14")),"")) | AW11: =IF($B11="","",AY11) | AX11: =IF($B11="","",IFERROR(IF(INDIRECT("'"&$B11&"'!$F$14")="","",INDIRECT("'"&$B11&"'!$F$14")),"")) | AY11: =IF($B11="","",IFERROR(IF(INDIRECT("'"&$B11&"'!$D$35")="","",INDIRECT("'"&$B11&"'!$D$35")),"")) | AZ11: =IF($B11="","",IFERROR(IF(INDIRECT("'"&$B11&"'!$J$14")="","",INDIRECT("'"&$B11&"'!$J$14")),"")) | BA11: =IF($B11="","",IFERROR(IF(INDIRECT("'"&$B11&"'!$I$21")="","",INDIRECT("'"&$B11&"'!$I$21")),"")) | BB11: =IF($B11="","",IFERROR(IF(INDIRECT("'"&$B11&"'!$C$67")="","",INDIRECT("'"&$B11&"'!$C$67")),"")) | BC11: =IF($B11="","",IFERROR(IF(INDIRECT("'"&$B11&"'!$D$68")="","",INDIRECT("'"&$B11&"'!$D$68")),"")) | BD11: =IFERROR(Z11+BB11-BC11,0) -> 0 | BE11: =IF($B11="","",IFERROR(IF(INDIRECT("'"&$B11&"'!$J$21")="","",INDIRECT("'"&$B11&"'!$J$21")),"")) | BF11: =IF($B11="","",IFERROR(IF(INDIRECT("'"&$B11&"'!$F$15")="","",INDIRECT("'"&$B11&"'!$F$15")),"")) | BG11: =IFERROR(N11-TODAY(),"") -> -46258 | BH11: =IF(N11="","",IF(AND(N11-TODAY()>=0,N11-TODAY()<=90),"Sim","Não")) | BI11: =IF(N11="","",IF(N11<TODAY(),"Sim","Não")) | BJ11: =IF(AF11=0,"",IF(IFERROR(AL11/AF11,0)<0.2,"Sim","Não")) -> Não | BK11: =IF(AF11=0,"",IF(IFERROR(AK11/AF11,0)>0.9,"Sim","Não")) -> Não | BL11: =IF(AY11="","",IF(TODAY()-AY11>60,"Sim","Não")) | BM11: =IF('2027'!$V$15="","",'2027'!$V$15) -> Previsão para locação de novo imóvel destinado à sede administrativa do Distrito de União Bandeirantes, em substituição ao imóvel atualmente utilizado, cuja estrutura não oferece condições adequadas para o atendimento à população, o desenvolvimento das atividades administrativas e a guarda dos equipamentos da SMD. Prevê-se a prorrogação temporária da locação atual, de outubro de 2026 até abril de 2027, para assegurar a continuidade do atendimento, com início da instrução do novo processo em janeiro de 2027. A seleção observará a adequação do imóvel, a avaliação mercadológica, a regularidade documental e a busca pelo menor valor compatível com as necessidades da unidade, em atenção à economicidade e ao interesse público. | BN11: =IF($B11="","",IFERROR(IF(INDIRECT("'"&$B11&"'!$B$24")="","",INDIRECT("'"&$B11&"'!$B$24")),"")) | BO11: =IF($B11="","",IFERROR(IF(INDIRECT("'"&$B11&"'!$B$25")="","",INDIRECT("'"&$B11&"'!$B$25")),"")) | BP11: =IF($B11="","",IFERROR(IF(INDIRECT("'"&$B11&"'!$B$26")="","",INDIRECT("'"&$B11&"'!$B$26")),"")) | BQ11: =IF($B11="","",IFERROR(IF(INDIRECT("'"&$B11&"'!$B$27")="","",INDIRECT("'"&$B11&"'!$B$27")),"")) | BR11: =IF($B11="","",IFERROR(IF(INDIRECT("'"&$B11&"'!$B$28")="","",INDIRECT("'"&$B11&"'!$B$28")),"")) | BS11: =IF($B11="","",IF(AK11="","",IF(ROUND(AK11-SUM(BN11:BR11),2)>0,"Verificar — pagamento sem fonte",IF(ROUND(AK11-SUM(BN11:BR11),2)<0,"Verificar — fonte > pago","OK"))))
A12: =IF('2027'!$E$16="","",'2027'!$E$16) | C12: =IF('2027'!$B$16="","",'2027'!$B$16) | D12: =IF('2027'!$C$16="","",'2027'!$C$16) | E12: =IF('2027'!$D$16="","",'2027'!$D$16) | F12: =IF('2027'!$E$16="","",'2027'!$E$16) | G12: =IF('2027'!$F$16="","",'2027'!$F$16) | H12: =IF('2027'!$H$16="","",'2027'!$H$16) | J12: =IF('2027'!$I$16="","",'2027'!$I$16) | K12: =IF($B12="","",IFERROR(IF(INDIRECT("'"&$B12&"'!$B$10")="","",INDIRECT("'"&$B12&"'!$B$10")),"")) | L12: =IF('2027'!$J$16="","",'2027'!$J$16) | M12: =IF('2027'!$K$16="","",'2027'!$K$16) | N12: =IF('2027'!$L$16="","",'2027'!$L$16) | O12: =IF($B12="","","SMD") | Q12: =IF($B12="","",IFERROR(IF(INDIRECT("'"&$B12&"'!$B$11")="","",INDIRECT("'"&$B12&"'!$B$11")),"")) | R12: =IF($B12="","",IFERROR(IF(INDIRECT("'"&$B12&"'!$F$11")="","",INDIRECT("'"&$B12&"'!$F$11")),"")) | S12: =IF($B12="","",IFERROR(IF(INDIRECT("'"&$B12&"'!$J$11")="","",INDIRECT("'"&$B12&"'!$J$11")),"")) | T12: =IF($B12="","",IFERROR(IF(INDIRECT("'"&$B12&"'!$J$10")="","",INDIRECT("'"&$B12&"'!$J$10")),"")) | U12: =IF($B12="","",IFERROR(IF(INDIRECT("'"&$B12&"'!$F$10")="","",INDIRECT("'"&$B12&"'!$F$10")),"")) | V12: =IF('2027'!$G$16="","",'2027'!$G$16) | X12: =IF($B12="","",IFERROR(IF(INDIRECT("'"&$B12&"'!$F$12")="","",INDIRECT("'"&$B12&"'!$F$12")),"")) | Y12: =IF($B12="","",IFERROR(IF(INDIRECT("'"&$B12&"'!$B$12")="","",INDIRECT("'"&$B12&"'!$B$12")),"")) | Z12: =IF($B12="","",IFERROR(IF(INDIRECT("'"&$B12&"'!$J$13")="","",INDIRECT("'"&$B12&"'!$J$13")),"")) | AB12: =IF($B12="","",IFERROR(IF(INDIRECT("'"&$B12&"'!$J$4")="","",INDIRECT("'"&$B12&"'!$J$4")),"")) | AC12: =IF($B12="","",2026) | AD12: =IF('2027'!$M$16="","",'2027'!$M$16) | AE12: =IF('2027'!$N$16="","",'2027'!$N$16) | AF12: =IF('2027'!$O$16="","",'2027'!$O$16) -> 0 | AI12: =IF('2027'!$Q$16="","",'2027'!$Q$16) | AJ12: =IF($B12="","",IFERROR(IF(INDIRECT("'"&$B12&"'!$D$21")="","",INDIRECT("'"&$B12&"'!$D$21")),"")) | AK12: =IF($B12="","",IFERROR(IF(INDIRECT("'"&$B12&"'!$E$21")="","",INDIRECT("'"&$B12&"'!$E$21")),"")) | AL12: =IF('2027'!$R$16="","",'2027'!$R$16) -> 0 | AM12: =IFERROR(AI12-AJ12,0) -> 0 | AN12: =IFERROR(AJ12-AK12,0) -> 0 | AO12: =IF('2027'!$S$16="","",'2027'!$S$16) -> 0 | AP12: =IFERROR(AK12/AF12,0) -> 0 | AQ12: =IF($B12="","",IFERROR(IF(INDIRECT("'"&$B12&"'!$K$21")="","",INDIRECT("'"&$B12&"'!$K$21")),"")) | AR12: =IF('2027'!$T$16="","",'2027'!$T$16) | AS12: =IF('2027'!$U$16="","",'2027'!$U$16) -> 0 | AT12: =IF($B12="","",IFERROR(IF(INDIRECT("'"&$B12&"'!$B$15")="","",INDIRECT("'"&$B12&"'!$B$15")),"")) | AV12: =IF($B12="","",IFERROR(IF(INDIRECT("'"&$B12&"'!$B$14")="","",INDIRECT("'"&$B12&"'!$B$14")),"")) | AW12: =IF($B12="","",AY12) | AX12: =IF($B12="","",IFERROR(IF(INDIRECT("'"&$B12&"'!$F$14")="","",INDIRECT("'"&$B12&"'!$F$14")),"")) | AY12: =IF($B12="","",IFERROR(IF(INDIRECT("'"&$B12&"'!$D$35")="","",INDIRECT("'"&$B12&"'!$D$35")),"")) | AZ12: =IF($B12="","",IFERROR(IF(INDIRECT("'"&$B12&"'!$J$14")="","",INDIRECT("'"&$B12&"'!$J$14")),"")) | BA12: =IF($B12="","",IFERROR(IF(INDIRECT("'"&$B12&"'!$I$21")="","",INDIRECT("'"&$B12&"'!$I$21")),"")) | BB12: =IF($B12="","",IFERROR(IF(INDIRECT("'"&$B12&"'!$C$67")="","",INDIRECT("'"&$B12&"'!$C$67")),"")) | BC12: =IF($B12="","",IFERROR(IF(INDIRECT("'"&$B12&"'!$D$68")="","",INDIRECT("'"&$B12&"'!$D$68")),"")) | BD12: =IFERROR(Z12+BB12-BC12,0) -> 0 | BE12: =IF($B12="","",IFERROR(IF(INDIRECT("'"&$B12&"'!$J$21")="","",INDIRECT("'"&$B12&"'!$J$21")),"")) | BF12: =IF($B12="","",IFERROR(IF(INDIRECT("'"&$B12&"'!$F$15")="","",INDIRECT("'"&$B12&"'!$F$15")),"")) | BG12: =IFERROR(N12-TODAY(),"") -> -46258 | BH12: =IF(N12="","",IF(AND(N12-TODAY()>=0,N12-TODAY()<=90),"Sim","Não")) | BI12: =IF(N12="","",IF(N12<TODAY(),"Sim","Não")) | BJ12: =IF(AF12=0,"",IF(IFERROR(AL12/AF12,0)<0.2,"Sim","Não")) | BK12: =IF(AF12=0,"",IF(IFERROR(AK12/AF12,0)>0.9,"Sim","Não")) | BL12: =IF(AY12="","",IF(TODAY()-AY12>60,"Sim","Não")) | BM12: =IF('2027'!$V$16="","",'2027'!$V$16) | BN12: =IF($B12="","",IFERROR(IF(INDIRECT("'"&$B12&"'!$B$24")="","",INDIRECT("'"&$B12&"'!$B$24")),"")) | BO12: =IF($B12="","",IFERROR(IF(INDIRECT("'"&$B12&"'!$B$25")="","",INDIRECT("'"&$B12&"'!$B$25")),"")) | BP12: =IF($B12="","",IFERROR(IF(INDIRECT("'"&$B12&"'!$B$26")="","",INDIRECT("'"&$B12&"'!$B$26")),"")) | BQ12: =IF($B12="","",IFERROR(IF(INDIRECT("'"&$B12&"'!$B$27")="","",INDIRECT("'"&$B12&"'!$B$27")),"")) | BR12: =IF($B12="","",IFERROR(IF(INDIRECT("'"&$B12&"'!$B$28")="","",INDIRECT("'"&$B12&"'!$B$28")),"")) | BS12: =IF($B12="","",IF(AK12="","",IF(ROUND(AK12-SUM(BN12:BR12),2)>0,"Verificar — pagamento sem fonte",IF(ROUND(AK12-SUM(BN12:BR12),2)<0,"Verificar — fonte > pago","OK"))))
A13: =IF('2027'!$E$17="","",'2027'!$E$17) | C13: =IF('2027'!$B$17="","",'2027'!$B$17) | D13: =IF('2027'!$C$17="","",'2027'!$C$17) | E13: =IF('2027'!$D$17="","",'2027'!$D$17) | F13: =IF('2027'!$E$17="","",'2027'!$E$17) | G13: =IF('2027'!$F$17="","",'2027'!$F$17) | H13: =IF('2027'!$H$17="","",'2027'!$H$17) | J13: =IF('2027'!$I$17="","",'2027'!$I$17) | K13: =IF($B13="","",IFERROR(IF(INDIRECT("'"&$B13&"'!$B$10")="","",INDIRECT("'"&$B13&"'!$B$10")),"")) | L13: =IF('2027'!$J$17="","",'2027'!$J$17) | M13: =IF('2027'!$K$17="","",'2027'!$K$17) | N13: =IF('2027'!$L$17="","",'2027'!$L$17) | O13: =IF($B13="","","SMD") | Q13: =IF($B13="","",IFERROR(IF(INDIRECT("'"&$B13&"'!$B$11")="","",INDIRECT("'"&$B13&"'!$B$11")),"")) | R13: =IF($B13="","",IFERROR(IF(INDIRECT("'"&$B13&"'!$F$11")="","",INDIRECT("'"&$B13&"'!$F$11")),"")) | S13: =IF($B13="","",IFERROR(IF(INDIRECT("'"&$B13&"'!$J$11")="","",INDIRECT("'"&$B13&"'!$J$11")),"")) | T13: =IF($B13="","",IFERROR(IF(INDIRECT("'"&$B13&"'!$J$10")="","",INDIRECT("'"&$B13&"'!$J$10")),"")) | U13: =IF($B13="","",IFERROR(IF(INDIRECT("'"&$B13&"'!$F$10")="","",INDIRECT("'"&$B13&"'!$F$10")),"")) | V13: =IF('2027'!$G$17="","",'2027'!$G$17) | X13: =IF($B13="","",IFERROR(IF(INDIRECT("'"&$B13&"'!$F$12")="","",INDIRECT("'"&$B13&"'!$F$12")),"")) | Y13: =IF($B13="","",IFERROR(IF(INDIRECT("'"&$B13&"'!$B$12")="","",INDIRECT("'"&$B13&"'!$B$12")),"")) | Z13: =IF($B13="","",IFERROR(IF(INDIRECT("'"&$B13&"'!$J$13")="","",INDIRECT("'"&$B13&"'!$J$13")),"")) | AB13: =IF($B13="","",IFERROR(IF(INDIRECT("'"&$B13&"'!$J$4")="","",INDIRECT("'"&$B13&"'!$J$4")),"")) | AC13: =IF($B13="","",2026) | AD13: =IF('2027'!$M$17="","",'2027'!$M$17) | AE13: =IF('2027'!$N$17="","",'2027'!$N$17) | AF13: =IF('2027'!$O$17="","",'2027'!$O$17) -> 0 | AI13: =IF('2027'!$Q$17="","",'2027'!$Q$17) | AJ13: =IF($B13="","",IFERROR(IF(INDIRECT("'"&$B13&"'!$D$21")="","",INDIRECT("'"&$B13&"'!$D$21")),"")) | AK13: =IF($B13="","",IFERROR(IF(INDIRECT("'"&$B13&"'!$E$21")="","",INDIRECT("'"&$B13&"'!$E$21")),"")) | AL13: =IF('2027'!$R$17="","",'2027'!$R$17) -> 0 | AM13: =IFERROR(AI13-AJ13,0) -> 0 | AN13: =IFERROR(AJ13-AK13,0) -> 0 | AO13: =IF('2027'!$S$17="","",'2027'!$S$17) -> 0 | AP13: =IFERROR(AK13/AF13,0) -> 0 | AQ13: =IF($B13="","",IFERROR(IF(INDIRECT("'"&$B13&"'!$K$21")="","",INDIRECT("'"&$B13&"'!$K$21")),"")) | AR13: =IF('2027'!$T$17="","",'2027'!$T$17) | AS13: =IF('2027'!$U$17="","",'2027'!$U$17) -> 0 | AT13: =IF($B13="","",IFERROR(IF(INDIRECT("'"&$B13&"'!$B$15")="","",INDIRECT("'"&$B13&"'!$B$15")),"")) | AV13: =IF($B13="","",IFERROR(IF(INDIRECT("'"&$B13&"'!$B$14")="","",INDIRECT("'"&$B13&"'!$B$14")),"")) | AW13: =IF($B13="","",AY13) | AX13: =IF($B13="","",IFERROR(IF(INDIRECT("'"&$B13&"'!$F$14")="","",INDIRECT("'"&$B13&"'!$F$14")),"")) | AY13: =IF($B13="","",IFERROR(IF(INDIRECT("'"&$B13&"'!$D$35")="","",INDIRECT("'"&$B13&"'!$D$35")),"")) | AZ13: =IF($B13="","",IFERROR(IF(INDIRECT("'"&$B13&"'!$J$14")="","",INDIRECT("'"&$B13&"'!$J$14")),"")) | BA13: =IF($B13="","",IFERROR(IF(INDIRECT("'"&$B13&"'!$I$21")="","",INDIRECT("'"&$B13&"'!$I$21")),"")) | BB13: =IF($B13="","",IFERROR(IF(INDIRECT("'"&$B13&"'!$C$67")="","",INDIRECT("'"&$B13&"'!$C$67")),"")) | BC13: =IF($B13="","",IFERROR(IF(INDIRECT("'"&$B13&"'!$D$68")="","",INDIRECT("'"&$B13&"'!$D$68")),"")) | BD13: =IFERROR(Z13+BB13-BC13,0) -> 0 | BE13: =IF($B13="","",IFERROR(IF(INDIRECT("'"&$B13&"'!$J$21")="","",INDIRECT("'"&$B13&"'!$J$21")),"")) | BF13: =IF($B13="","",IFERROR(IF(INDIRECT("'"&$B13&"'!$F$15")="","",INDIRECT("'"&$B13&"'!$F$15")),"")) | BG13: =IFERROR(N13-TODAY(),"") -> -46258 | BH13: =IF(N13="","",IF(AND(N13-TODAY()>=0,N13-TODAY()<=90),"Sim","Não")) | BI13: =IF(N13="","",IF(N13<TODAY(),"Sim","Não")) | BJ13: =IF(AF13=0,"",IF(IFERROR(AL13/AF13,0)<0.2,"Sim","Não")) | BK13: =IF(AF13=0,"",IF(IFERROR(AK13/AF13,0)>0.9,"Sim","Não")) | BL13: =IF(AY13="","",IF(TODAY()-AY13>60,"Sim","Não")) | BM13: =IF('2027'!$V$17="","",'2027'!$V$17) | BN13: =IF($B13="","",IFERROR(IF(INDIRECT("'"&$B13&"'!$B$24")="","",INDIRECT("'"&$B13&"'!$B$24")),"")) | BO13: =IF($B13="","",IFERROR(IF(INDIRECT("'"&$B13&"'!$B$25")="","",INDIRECT("'"&$B13&"'!$B$25")),"")) | BP13: =IF($B13="","",IFERROR(IF(INDIRECT("'"&$B13&"'!$B$26")="","",INDIRECT("'"&$B13&"'!$B$26")),"")) | BQ13: =IF($B13="","",IFERROR(IF(INDIRECT("'"&$B13&"'!$B$27")="","",INDIRECT("'"&$B13&"'!$B$27")),"")) | BR13: =IF($B13="","",IFERROR(IF(INDIRECT("'"&$B13&"'!$B$28")="","",INDIRECT("'"&$B13&"'!$B$28")),"")) | BS13: =IF($B13="","",IF(AK13="","",IF(ROUND(AK13-SUM(BN13:BR13),2)>0,"Verificar — pagamento sem fonte",IF(ROUND(AK13-SUM(BN13:BR13),2)<0,"Verificar — fonte > pago","OK"))))
A14: =IF('2027'!$E$18="","",'2027'!$E$18) | C14: =IF('2027'!$B$18="","",'2027'!$B$18) | D14: =IF('2027'!$C$18="","",'2027'!$C$18) | E14: =IF('2027'!$D$18="","",'2027'!$D$18) | F14: =IF('2027'!$E$18="","",'2027'!$E$18) | G14: =IF('2027'!$F$18="","",'2027'!$F$18) | H14: =IF('2027'!$H$18="","",'2027'!$H$18) | J14: =IF('2027'!$I$18="","",'2027'!$I$18) | K14: =IF($B14="","",IFERROR(IF(INDIRECT("'"&$B14&"'!$B$10")="","",INDIRECT("'"&$B14&"'!$B$10")),"")) | L14: =IF('2027'!$J$18="","",'2027'!$J$18) | M14: =IF('2027'!$K$18="","",'2027'!$K$18) | N14: =IF('2027'!$L$18="","",'2027'!$L$18) | O14: =IF($B14="","","SMD") | Q14: =IF($B14="","",IFERROR(IF(INDIRECT("'"&$B14&"'!$B$11")="","",INDIRECT("'"&$B14&"'!$B$11")),"")) | R14: =IF($B14="","",IFERROR(IF(INDIRECT("'"&$B14&"'!$F$11")="","",INDIRECT("'"&$B14&"'!$F$11")),"")) | S14: =IF($B14="","",IFERROR(IF(INDIRECT("'"&$B14&"'!$J$11")="","",INDIRECT("'"&$B14&"'!$J$11")),"")) | T14: =IF($B14="","",IFERROR(IF(INDIRECT("'"&$B14&"'!$J$10")="","",INDIRECT("'"&$B14&"'!$J$10")),"")) | U14: =IF($B14="","",IFERROR(IF(INDIRECT("'"&$B14&"'!$F$10")="","",INDIRECT("'"&$B14&"'!$F$10")),"")) | V14: =IF('2027'!$G$18="","",'2027'!$G$18) | X14: =IF($B14="","",IFERROR(IF(INDIRECT("'"&$B14&"'!$F$12")="","",INDIRECT("'"&$B14&"'!$F$12")),"")) | Y14: =IF($B14="","",IFERROR(IF(INDIRECT("'"&$B14&"'!$B$12")="","",INDIRECT("'"&$B14&"'!$B$12")),"")) | Z14: =IF($B14="","",IFERROR(IF(INDIRECT("'"&$B14&"'!$J$13")="","",INDIRECT("'"&$B14&"'!$J$13")),"")) | AB14: =IF($B14="","",IFERROR(IF(INDIRECT("'"&$B14&"'!$J$4")="","",INDIRECT("'"&$B14&"'!$J$4")),"")) | AC14: =IF($B14="","",2026) | AD14: =IF('2027'!$M$18="","",'2027'!$M$18) | AE14: =IF('2027'!$N$18="","",'2027'!$N$18) | AF14: =IF('2027'!$O$18="","",'2027'!$O$18) -> 0 | AI14: =IF('2027'!$Q$18="","",'2027'!$Q$18) | AJ14: =IF($B14="","",IFERROR(IF(INDIRECT("'"&$B14&"'!$D$21")="","",INDIRECT("'"&$B14&"'!$D$21")),"")) | AK14: =IF($B14="","",IFERROR(IF(INDIRECT("'"&$B14&"'!$E$21")="","",INDIRECT("'"&$B14&"'!$E$21")),"")) | AL14: =IF('2027'!$R$18="","",'2027'!$R$18) -> 0 | AM14: =IFERROR(AI14-AJ14,0) -> 0 | AN14: =IFERROR(AJ14-AK14,0) -> 0 | AO14: =IF('2027'!$S$18="","",'2027'!$S$18) -> 0 | AP14: =IFERROR(AK14/AF14,0) -> 0 | AQ14: =IF($B14="","",IFERROR(IF(INDIRECT("'"&$B14&"'!$K$21")="","",INDIRECT("'"&$B14&"'!$K$21")),"")) | AR14: =IF('2027'!$T$18="","",'2027'!$T$18) | AS14: =IF('2027'!$U$18="","",'2027'!$U$18) -> 0 | AT14: =IF($B14="","",IFERROR(IF(INDIRECT("'"&$B14&"'!$B$15")="","",INDIRECT("'"&$B14&"'!$B$15")),"")) | AV14: =IF($B14="","",IFERROR(IF(INDIRECT("'"&$B14&"'!$B$14")="","",INDIRECT("'"&$B14&"'!$B$14")),"")) | AW14: =IF($B14="","",AY14) | AX14: =IF($B14="","",IFERROR(IF(INDIRECT("'"&$B14&"'!$F$14")="","",INDIRECT("'"&$B14&"'!$F$14")),"")) | AY14: =IF($B14="","",IFERROR(IF(INDIRECT("'"&$B14&"'!$D$35")="","",INDIRECT("'"&$B14&"'!$D$35")),"")) | AZ14: =IF($B14="","",IFERROR(IF(INDIRECT("'"&$B14&"'!$J$14")="","",INDIRECT("'"&$B14&"'!$J$14")),"")) | BA14: =IF($B14="","",IFERROR(IF(INDIRECT("'"&$B14&"'!$I$21")="","",INDIRECT("'"&$B14&"'!$I$21")),"")) | BB14: =IF($B14="","",IFERROR(IF(INDIRECT("'"&$B14&"'!$C$67")="","",INDIRECT("'"&$B14&"'!$C$67")),"")) | BC14: =IF($B14="","",IFERROR(IF(INDIRECT("'"&$B14&"'!$D$68")="","",INDIRECT("'"&$B14&"'!$D$68")),"")) | BD14: =IFERROR(Z14+BB14-BC14,0) -> 0 | BE14: =IF($B14="","",IFERROR(IF(INDIRECT("'"&$B14&"'!$J$21")="","",INDIRECT("'"&$B14&"'!$J$21")),"")) | BF14: =IF($B14="","",IFERROR(IF(INDIRECT("'"&$B14&"'!$F$15")="","",INDIRECT("'"&$B14&"'!$F$15")),"")) | BG14: =IFERROR(N14-TODAY(),"") -> -46258 | BH14: =IF(N14="","",IF(AND(N14-TODAY()>=0,N14-TODAY()<=90),"Sim","Não")) | BI14: =IF(N14="","",IF(N14<TODAY(),"Sim","Não")) | BJ14: =IF(AF14=0,"",IF(IFERROR(AL14/AF14,0)<0.2,"Sim","Não")) | BK14: =IF(AF14=0,"",IF(IFERROR(AK14/AF14,0)>0.9,"Sim","Não")) | BL14: =IF(AY14="","",IF(TODAY()-AY14>60,"Sim","Não")) | BM14: =IF('2027'!$V$18="","",'2027'!$V$18) | BN14: =IF($B14="","",IFERROR(IF(INDIRECT("'"&$B14&"'!$B$24")="","",INDIRECT("'"&$B14&"'!$B$24")),"")) | BO14: =IF($B14="","",IFERROR(IF(INDIRECT("'"&$B14&"'!$B$25")="","",INDIRECT("'"&$B14&"'!$B$25")),"")) | BP14: =IF($B14="","",IFERROR(IF(INDIRECT("'"&$B14&"'!$B$26")="","",INDIRECT("'"&$B14&"'!$B$26")),"")) | BQ14: =IF($B14="","",IFERROR(IF(INDIRECT("'"&$B14&"'!$B$27")="","",INDIRECT("'"&$B14&"'!$B$27")),"")) | BR14: =IF($B14="","",IFERROR(IF(INDIRECT("'"&$B14&"'!$B$28")="","",INDIRECT("'"&$B14&"'!$B$28")),"")) | BS14: =IF($B14="","",IF(AK14="","",IF(ROUND(AK14-SUM(BN14:BR14),2)>0,"Verificar — pagamento sem fonte",IF(ROUND(AK14-SUM(BN14:BR14),2)<0,"Verificar — fonte > pago","OK"))))
A15: =IF('2027'!$E$19="","",'2027'!$E$19) | C15: =IF('2027'!$B$19="","",'2027'!$B$19) | D15: =IF('2027'!$C$19="","",'2027'!$C$19) | E15: =IF('2027'!$D$19="","",'2027'!$D$19) | F15: =IF('2027'!$E$19="","",'2027'!$E$19) | G15: =IF('2027'!$F$19="","",'2027'!$F$19) | H15: =IF('2027'!$H$19="","",'2027'!$H$19) | J15: =IF('2027'!$I$19="","",'2027'!$I$19) | K15: =IF($B15="","",IFERROR(IF(INDIRECT("'"&$B15&"'!$B$10")="","",INDIRECT("'"&$B15&"'!$B$10")),"")) | L15: =IF('2027'!$J$19="","",'2027'!$J$19) | M15: =IF('2027'!$K$19="","",'2027'!$K$19) | N15: =IF('2027'!$L$19="","",'2027'!$L$19) | O15: =IF($B15="","","SMD") | Q15: =IF($B15="","",IFERROR(IF(INDIRECT("'"&$B15&"'!$B$11")="","",INDIRECT("'"&$B15&"'!$B$11")),"")) | R15: =IF($B15="","",IFERROR(IF(INDIRECT("'"&$B15&"'!$F$11")="","",INDIRECT("'"&$B15&"'!$F$11")),"")) | S15: =IF($B15="","",IFERROR(IF(INDIRECT("'"&$B15&"'!$J$11")="","",INDIRECT("'"&$B15&"'!$J$11")),"")) | T15: =IF($B15="","",IFERROR(IF(INDIRECT("'"&$B15&"'!$J$10")="","",INDIRECT("'"&$B15&"'!$J$10")),"")) | U15: =IF($B15="","",IFERROR(IF(INDIRECT("'"&$B15&"'!$F$10")="","",INDIRECT("'"&$B15&"'!$F$10")),"")) | V15: =IF('2027'!$G$19="","",'2027'!$G$19) | X15: =IF($B15="","",IFERROR(IF(INDIRECT("'"&$B15&"'!$F$12")="","",INDIRECT("'"&$B15&"'!$F$12")),"")) | Y15: =IF($B15="","",IFERROR(IF(INDIRECT("'"&$B15&"'!$B$12")="","",INDIRECT("'"&$B15&"'!$B$12")),"")) | Z15: =IF($B15="","",IFERROR(IF(INDIRECT("'"&$B15&"'!$J$13")="","",INDIRECT("'"&$B15&"'!$J$13")),"")) | AB15: =IF($B15="","",IFERROR(IF(INDIRECT("'"&$B15&"'!$J$4")="","",INDIRECT("'"&$B15&"'!$J$4")),"")) | AC15: =IF($B15="","",2026) | AD15: =IF('2027'!$M$19="","",'2027'!$M$19) | AE15: =IF('2027'!$N$19="","",'2027'!$N$19) | AF15: =IF('2027'!$O$19="","",'2027'!$O$19) -> 0 | AI15: =IF('2027'!$Q$19="","",'2027'!$Q$19) | AJ15: =IF($B15="","",IFERROR(IF(INDIRECT("'"&$B15&"'!$D$21")="","",INDIRECT("'"&$B15&"'!$D$21")),"")) | AK15: =IF($B15="","",IFERROR(IF(INDIRECT("'"&$B15&"'!$E$21")="","",INDIRECT("'"&$B15&"'!$E$21")),"")) | AL15: =IF('2027'!$R$19="","",'2027'!$R$19) -> 0 | AM15: =IFERROR(AI15-AJ15,0) -> 0 | AN15: =IFERROR(AJ15-AK15,0) -> 0 | AO15: =IF('2027'!$S$19="","",'2027'!$S$19) -> 0 | AP15: =IFERROR(AK15/AF15,0) -> 0 | AQ15: =IF($B15="","",IFERROR(IF(INDIRECT("'"&$B15&"'!$K$21")="","",INDIRECT("'"&$B15&"'!$K$21")),"")) | AR15: =IF('2027'!$T$19="","",'2027'!$T$19) | AS15: =IF('2027'!$U$19="","",'2027'!$U$19) -> 0 | AT15: =IF($B15="","",IFERROR(IF(INDIRECT("'"&$B15&"'!$B$15")="","",INDIRECT("'"&$B15&"'!$B$15")),"")) | AV15: =IF($B15="","",IFERROR(IF(INDIRECT("'"&$B15&"'!$B$14")="","",INDIRECT("'"&$B15&"'!$B$14")),"")) | AW15: =IF($B15="","",AY15) | AX15: =IF($B15="","",IFERROR(IF(INDIRECT("'"&$B15&"'!$F$14")="","",INDIRECT("'"&$B15&"'!$F$14")),"")) | AY15: =IF($B15="","",IFERROR(IF(INDIRECT("'"&$B15&"'!$D$35")="","",INDIRECT("'"&$B15&"'!$D$35")),"")) | AZ15: =IF($B15="","",IFERROR(IF(INDIRECT("'"&$B15&"'!$J$14")="","",INDIRECT("'"&$B15&"'!$J$14")),"")) | BA15: =IF($B15="","",IFERROR(IF(INDIRECT("'"&$B15&"'!$I$21")="","",INDIRECT("'"&$B15&"'!$I$21")),"")) | BB15: =IF($B15="","",IFERROR(IF(INDIRECT("'"&$B15&"'!$C$67")="","",INDIRECT("'"&$B15&"'!$C$67")),"")) | BC15: =IF($B15="","",IFERROR(IF(INDIRECT("'"&$B15&"'!$D$68")="","",INDIRECT("'"&$B15&"'!$D$68")),"")) | BD15: =IFERROR(Z15+BB15-BC15,0) -> 0 | BE15: =IF($B15="","",IFERROR(IF(INDIRECT("'"&$B15&"'!$J$21")="","",INDIRECT("'"&$B15&"'!$J$21")),"")) | BF15: =IF($B15="","",IFERROR(IF(INDIRECT("'"&$B15&"'!$F$15")="","",INDIRECT("'"&$B15&"'!$F$15")),"")) | BG15: =IFERROR(N15-TODAY(),"") -> -46258 | BH15: =IF(N15="","",IF(AND(N15-TODAY()>=0,N15-TODAY()<=90),"Sim","Não")) | BI15: =IF(N15="","",IF(N15<TODAY(),"Sim","Não")) | BJ15: =IF(AF15=0,"",IF(IFERROR(AL15/AF15,0)<0.2,"Sim","Não")) | BK15: =IF(AF15=0,"",IF(IFERROR(AK15/AF15,0)>0.9,"Sim","Não")) | BL15: =IF(AY15="","",IF(TODAY()-AY15>60,"Sim","Não")) | BM15: =IF('2027'!$V$19="","",'2027'!$V$19) | BN15: =IF($B15="","",IFERROR(IF(INDIRECT("'"&$B15&"'!$B$24")="","",INDIRECT("'"&$B15&"'!$B$24")),"")) | BO15: =IF($B15="","",IFERROR(IF(INDIRECT("'"&$B15&"'!$B$25")="","",INDIRECT("'"&$B15&"'!$B$25")),"")) | BP15: =IF($B15="","",IFERROR(IF(INDIRECT("'"&$B15&"'!$B$26")="","",INDIRECT("'"&$B15&"'!$B$26")),"")) | BQ15: =IF($B15="","",IFERROR(IF(INDIRECT("'"&$B15&"'!$B$27")="","",INDIRECT("'"&$B15&"'!$B$27")),"")) | BR15: =IF($B15="","",IFERROR(IF(INDIRECT("'"&$B15&"'!$B$28")="","",INDIRECT("'"&$B15&"'!$B$28")),"")) | BS15: =IF($B15="","",IF(AK15="","",IF(ROUND(AK15-SUM(BN15:BR15),2)>0,"Verificar — pagamento sem fonte",IF(ROUND(AK15-SUM(BN15:BR15),2)<0,"Verificar — fonte > pago","OK"))))
A16: =IF('2027'!$E$20="","",'2027'!$E$20) | C16: =IF('2027'!$B$20="","",'2027'!$B$20) | D16: =IF('2027'!$C$20="","",'2027'!$C$20) | E16: =IF('2027'!$D$20="","",'2027'!$D$20) | F16: =IF('2027'!$E$20="","",'2027'!$E$20) | G16: =IF('2027'!$F$20="","",'2027'!$F$20) | H16: =IF('2027'!$H$20="","",'2027'!$H$20) | J16: =IF('2027'!$I$20="","",'2027'!$I$20) | K16: =IF($B16="","",IFERROR(IF(INDIRECT("'"&$B16&"'!$B$10")="","",INDIRECT("'"&$B16&"'!$B$10")),"")) | L16: =IF('2027'!$J$20="","",'2027'!$J$20) | M16: =IF('2027'!$K$20="","",'2027'!$K$20) | N16: =IF('2027'!$L$20="","",'2027'!$L$20) | O16: =IF($B16="","","SMD") | Q16: =IF($B16="","",IFERROR(IF(INDIRECT("'"&$B16&"'!$B$11")="","",INDIRECT("'"&$B16&"'!$B$11")),"")) | R16: =IF($B16="","",IFERROR(IF(INDIRECT("'"&$B16&"'!$F$11")="","",INDIRECT("'"&$B16&"'!$F$11")),"")) | S16: =IF($B16="","",IFERROR(IF(INDIRECT("'"&$B16&"'!$J$11")="","",INDIRECT("'"&$B16&"'!$J$11")),"")) | T16: =IF($B16="","",IFERROR(IF(INDIRECT("'"&$B16&"'!$J$10")="","",INDIRECT("'"&$B16&"'!$J$10")),"")) | U16: =IF($B16="","",IFERROR(IF(INDIRECT("'"&$B16&"'!$F$10")="","",INDIRECT("'"&$B16&"'!$F$10")),"")) | V16: =IF('2027'!$G$20="","",'2027'!$G$20) | X16: =IF($B16="","",IFERROR(IF(INDIRECT("'"&$B16&"'!$F$12")="","",INDIRECT("'"&$B16&"'!$F$12")),"")) | Y16: =IF($B16="","",IFERROR(IF(INDIRECT("'"&$B16&"'!$B$12")="","",INDIRECT("'"&$B16&"'!$B$12")),"")) | Z16: =IF($B16="","",IFERROR(IF(INDIRECT("'"&$B16&"'!$J$13")="","",INDIRECT("'"&$B16&"'!$J$13")),"")) | AB16: =IF($B16="","",IFERROR(IF(INDIRECT("'"&$B16&"'!$J$4")="","",INDIRECT("'"&$B16&"'!$J$4")),"")) | AC16: =IF($B16="","",2026) | AD16: =IF('2027'!$M$20="","",'2027'!$M$20) | AE16: =IF('2027'!$N$20="","",'2027'!$N$20) | AF16: =IF('2027'!$O$20="","",'2027'!$O$20) -> 0 | AI16: =IF('2027'!$Q$20="","",'2027'!$Q$20) | AJ16: =IF($B16="","",IFERROR(IF(INDIRECT("'"&$B16&"'!$D$21")="","",INDIRECT("'"&$B16&"'!$D$21")),"")) | AK16: =IF($B16="","",IFERROR(IF(INDIRECT("'"&$B16&"'!$E$21")="","",INDIRECT("'"&$B16&"'!$E$21")),"")) | AL16: =IF('2027'!$R$20="","",'2027'!$R$20) -> 0 | AM16: =IFERROR(AI16-AJ16,0) -> 0 | AN16: =IFERROR(AJ16-AK16,0) -> 0 | AO16: =IF('2027'!$S$20="","",'2027'!$S$20) -> 0 | AP16: =IFERROR(AK16/AF16,0) -> 0 | AQ16: =IF($B16="","",IFERROR(IF(INDIRECT("'"&$B16&"'!$K$21")="","",INDIRECT("'"&$B16&"'!$K$21")),"")) | AR16: =IF('2027'!$T$20="","",'2027'!$T$20) | AS16: =IF('2027'!$U$20="","",'2027'!$U$20) -> 0 | AT16: =IF($B16="","",IFERROR(IF(INDIRECT("'"&$B16&"'!$B$15")="","",INDIRECT("'"&$B16&"'!$B$15")),"")) | AV16: =IF($B16="","",IFERROR(IF(INDIRECT("'"&$B16&"'!$B$14")="","",INDIRECT("'"&$B16&"'!$B$14")),"")) | AW16: =IF($B16="","",AY16) | AX16: =IF($B16="","",IFERROR(IF(INDIRECT("'"&$B16&"'!$F$14")="","",INDIRECT("'"&$B16&"'!$F$14")),"")) | AY16: =IF($B16="","",IFERROR(IF(INDIRECT("'"&$B16&"'!$D$35")="","",INDIRECT("'"&$B16&"'!$D$35")),"")) | AZ16: =IF($B16="","",IFERROR(IF(INDIRECT("'"&$B16&"'!$J$14")="","",INDIRECT("'"&$B16&"'!$J$14")),"")) | BA16: =IF($B16="","",IFERROR(IF(INDIRECT("'"&$B16&"'!$I$21")="","",INDIRECT("'"&$B16&"'!$I$21")),"")) | BB16: =IF($B16="","",IFERROR(IF(INDIRECT("'"&$B16&"'!$C$67")="","",INDIRECT("'"&$B16&"'!$C$67")),"")) | BC16: =IF($B16="","",IFERROR(IF(INDIRECT("'"&$B16&"'!$D$68")="","",INDIRECT("'"&$B16&"'!$D$68")),"")) | BD16: =IFERROR(Z16+BB16-BC16,0) -> 0 | BE16: =IF($B16="","",IFERROR(IF(INDIRECT("'"&$B16&"'!$J$21")="","",INDIRECT("'"&$B16&"'!$J$21")),"")) | BF16: =IF($B16="","",IFERROR(IF(INDIRECT("'"&$B16&"'!$F$15")="","",INDIRECT("'"&$B16&"'!$F$15")),"")) | BG16: =IFERROR(N16-TODAY(),"") -> -46258 | BH16: =IF(N16="","",IF(AND(N16-TODAY()>=0,N16-TODAY()<=90),"Sim","Não")) | BI16: =IF(N16="","",IF(N16<TODAY(),"Sim","Não")) | BJ16: =IF(AF16=0,"",IF(IFERROR(AL16/AF16,0)<0.2,"Sim","Não")) | BK16: =IF(AF16=0,"",IF(IFERROR(AK16/AF16,0)>0.9,"Sim","Não")) | BL16: =IF(AY16="","",IF(TODAY()-AY16>60,"Sim","Não")) | BM16: =IF('2027'!$V$20="","",'2027'!$V$20) | BN16: =IF($B16="","",IFERROR(IF(INDIRECT("'"&$B16&"'!$B$24")="","",INDIRECT("'"&$B16&"'!$B$24")),"")) | BO16: =IF($B16="","",IFERROR(IF(INDIRECT("'"&$B16&"'!$B$25")="","",INDIRECT("'"&$B16&"'!$B$25")),"")) | BP16: =IF($B16="","",IFERROR(IF(INDIRECT("'"&$B16&"'!$B$26")="","",INDIRECT("'"&$B16&"'!$B$26")),"")) | BQ16: =IF($B16="","",IFERROR(IF(INDIRECT("'"&$B16&"'!$B$27")="","",INDIRECT("'"&$B16&"'!$B$27")),"")) | BR16: =IF($B16="","",IFERROR(IF(INDIRECT("'"&$B16&"'!$B$28")="","",INDIRECT("'"&$B16&"'!$B$28")),"")) | BS16: =IF($B16="","",IF(AK16="","",IF(ROUND(AK16-SUM(BN16:BR16),2)>0,"Verificar — pagamento sem fonte",IF(ROUND(AK16-SUM(BN16:BR16),2)<0,"Verificar — fonte > pago","OK"))))
A17: =IF('2027'!$E$21="","",'2027'!$E$21) | C17: =IF('2027'!$B$21="","",'2027'!$B$21) | D17: =IF('2027'!$C$21="","",'2027'!$C$21) | E17: =IF('2027'!$D$21="","",'2027'!$D$21) | F17: =IF('2027'!$E$21="","",'2027'!$E$21) | G17: =IF('2027'!$F$21="","",'2027'!$F$21) | H17: =IF('2027'!$H$21="","",'2027'!$H$21) | J17: =IF('2027'!$I$21="","",'2027'!$I$21) | K17: =IF($B17="","",IFERROR(IF(INDIRECT("'"&$B17&"'!$B$10")="","",INDIRECT("'"&$B17&"'!$B$10")),"")) | L17: =IF('2027'!$J$21="","",'2027'!$J$21) | M17: =IF('2027'!$K$21="","",'2027'!$K$21) | N17: =IF('2027'!$L$21="","",'2027'!$L$21) | O17: =IF($B17="","","SMD") | Q17: =IF($B17="","",IFERROR(IF(INDIRECT("'"&$B17&"'!$B$11")="","",INDIRECT("'"&$B17&"'!$B$11")),"")) | R17: =IF($B17="","",IFERROR(IF(INDIRECT("'"&$B17&"'!$F$11")="","",INDIRECT("'"&$B17&"'!$F$11")),"")) | S17: =IF($B17="","",IFERROR(IF(INDIRECT("'"&$B17&"'!$J$11")="","",INDIRECT("'"&$B17&"'!$J$11")),"")) | T17: =IF($B17="","",IFERROR(IF(INDIRECT("'"&$B17&"'!$J$10")="","",INDIRECT("'"&$B17&"'!$J$10")),"")) | U17: =IF($B17="","",IFERROR(IF(INDIRECT("'"&$B17&"'!$F$10")="","",INDIRECT("'"&$B17&"'!$F$10")),"")) | V17: =IF('2027'!$G$21="","",'2027'!$G$21) | X17: =IF($B17="","",IFERROR(IF(INDIRECT("'"&$B17&"'!$F$12")="","",INDIRECT("'"&$B17&"'!$F$12")),"")) | Y17: =IF($B17="","",IFERROR(IF(INDIRECT("'"&$B17&"'!$B$12")="","",INDIRECT("'"&$B17&"'!$B$12")),"")) | Z17: =IF($B17="","",IFERROR(IF(INDIRECT("'"&$B17&"'!$J$13")="","",INDIRECT("'"&$B17&"'!$J$13")),"")) | AB17: =IF($B17="","",IFERROR(IF(INDIRECT("'"&$B17&"'!$J$4")="","",INDIRECT("'"&$B17&"'!$J$4")),"")) | AC17: =IF($B17="","",2026) | AD17: =IF('2027'!$M$21="","",'2027'!$M$21) | AE17: =IF('2027'!$N$21="","",'2027'!$N$21) | AF17: =IF('2027'!$O$21="","",'2027'!$O$21) -> 0 | AI17: =IF('2027'!$Q$21="","",'2027'!$Q$21) | AJ17: =IF($B17="","",IFERROR(IF(INDIRECT("'"&$B17&"'!$D$21")="","",INDIRECT("'"&$B17&"'!$D$21")),"")) | AK17: =IF($B17="","",IFERROR(IF(INDIRECT("'"&$B17&"'!$E$21")="","",INDIRECT("'"&$B17&"'!$E$21")),"")) | AL17: =IF('2027'!$R$21="","",'2027'!$R$21) -> 0 | AM17: =IFERROR(AI17-AJ17,0) -> 0 | AN17: =IFERROR(AJ17-AK17,0) -> 0 | AO17: =IF('2027'!$S$21="","",'2027'!$S$21) -> 0 | AP17: =IFERROR(AK17/AF17,0) -> 0 | AQ17: =IF($B17="","",IFERROR(IF(INDIRECT("'"&$B17&"'!$K$21")="","",INDIRECT("'"&$B17&"'!$K$21")),"")) | AR17: =IF('2027'!$T$21="","",'2027'!$T$21) | AS17: =IF('2027'!$U$21="","",'2027'!$U$21) -> 0 | AT17: =IF($B17="","",IFERROR(IF(INDIRECT("'"&$B17&"'!$B$15")="","",INDIRECT("'"&$B17&"'!$B$15")),"")) | AV17: =IF($B17="","",IFERROR(IF(INDIRECT("'"&$B17&"'!$B$14")="","",INDIRECT("'"&$B17&"'!$B$14")),"")) | AW17: =IF($B17="","",AY17) | AX17: =IF($B17="","",IFERROR(IF(INDIRECT("'"&$B17&"'!$F$14")="","",INDIRECT("'"&$B17&"'!$F$14")),"")) | AY17: =IF($B17="","",IFERROR(IF(INDIRECT("'"&$B17&"'!$D$35")="","",INDIRECT("'"&$B17&"'!$D$35")),"")) | AZ17: =IF($B17="","",IFERROR(IF(INDIRECT("'"&$B17&"'!$J$14")="","",INDIRECT("'"&$B17&"'!$J$14")),"")) | BA17: =IF($B17="","",IFERROR(IF(INDIRECT("'"&$B17&"'!$I$21")="","",INDIRECT("'"&$B17&"'!$I$21")),"")) | BB17: =IF($B17="","",IFERROR(IF(INDIRECT("'"&$B17&"'!$C$67")="","",INDIRECT("'"&$B17&"'!$C$67")),"")) | BC17: =IF($B17="","",IFERROR(IF(INDIRECT("'"&$B17&"'!$D$68")="","",INDIRECT("'"&$B17&"'!$D$68")),"")) | BD17: =IFERROR(Z17+BB17-BC17,0) -> 0 | BE17: =IF($B17="","",IFERROR(IF(INDIRECT("'"&$B17&"'!$J$21")="","",INDIRECT("'"&$B17&"'!$J$21")),"")) | BF17: =IF($B17="","",IFERROR(IF(INDIRECT("'"&$B17&"'!$F$15")="","",INDIRECT("'"&$B17&"'!$F$15")),"")) | BG17: =IFERROR(N17-TODAY(),"") -> -46258 | BH17: =IF(N17="","",IF(AND(N17-TODAY()>=0,N17-TODAY()<=90),"Sim","Não")) | BI17: =IF(N17="","",IF(N17<TODAY(),"Sim","Não")) | BJ17: =IF(AF17=0,"",IF(IFERROR(AL17/AF17,0)<0.2,"Sim","Não")) | BK17: =IF(AF17=0,"",IF(IFERROR(AK17/AF17,0)>0.9,"Sim","Não")) | BL17: =IF(AY17="","",IF(TODAY()-AY17>60,"Sim","Não")) | BM17: =IF('2027'!$V$21="","",'2027'!$V$21) | BN17: =IF($B17="","",IFERROR(IF(INDIRECT("'"&$B17&"'!$B$24")="","",INDIRECT("'"&$B17&"'!$B$24")),"")) | BO17: =IF($B17="","",IFERROR(IF(INDIRECT("'"&$B17&"'!$B$25")="","",INDIRECT("'"&$B17&"'!$B$25")),"")) | BP17: =IF($B17="","",IFERROR(IF(INDIRECT("'"&$B17&"'!$B$26")="","",INDIRECT("'"&$B17&"'!$B$26")),"")) | BQ17: =IF($B17="","",IFERROR(IF(INDIRECT("'"&$B17&"'!$B$27")="","",INDIRECT("'"&$B17&"'!$B$27")),"")) | BR17: =IF($B17="","",IFERROR(IF(INDIRECT("'"&$B17&"'!$B$28")="","",INDIRECT("'"&$B17&"'!$B$28")),"")) | BS17: =IF($B17="","",IF(AK17="","",IF(ROUND(AK17-SUM(BN17:BR17),2)>0,"Verificar — pagamento sem fonte",IF(ROUND(AK17-SUM(BN17:BR17),2)<0,"Verificar — fonte > pago","OK"))))
A18: =IF('2027'!$E$22="","",'2027'!$E$22) | C18: =IF('2027'!$B$22="","",'2027'!$B$22) | D18: =IF('2027'!$C$22="","",'2027'!$C$22) | E18: =IF('2027'!$D$22="","",'2027'!$D$22) | F18: =IF('2027'!$E$22="","",'2027'!$E$22) | G18: =IF('2027'!$F$22="","",'2027'!$F$22) | H18: =IF('2027'!$H$22="","",'2027'!$H$22) | J18: =IF('2027'!$I$22="","",'2027'!$I$22) | K18: =IF($B18="","",IFERROR(IF(INDIRECT("'"&$B18&"'!$B$10")="","",INDIRECT("'"&$B18&"'!$B$10")),"")) | L18: =IF('2027'!$J$22="","",'2027'!$J$22) | M18: =IF('2027'!$K$22="","",'2027'!$K$22) | N18: =IF('2027'!$L$22="","",'2027'!$L$22) | O18: =IF($B18="","","SMD") | Q18: =IF($B18="","",IFERROR(IF(INDIRECT("'"&$B18&"'!$B$11")="","",INDIRECT("'"&$B18&"'!$B$11")),"")) | R18: =IF($B18="","",IFERROR(IF(INDIRECT("'"&$B18&"'!$F$11")="","",INDIRECT("'"&$B18&"'!$F$11")),"")) | S18: =IF($B18="","",IFERROR(IF(INDIRECT("'"&$B18&"'!$J$11")="","",INDIRECT("'"&$B18&"'!$J$11")),"")) | T18: =IF($B18="","",IFERROR(IF(INDIRECT("'"&$B18&"'!$J$10")="","",INDIRECT("'"&$B18&"'!$J$10")),"")) | U18: =IF($B18="","",IFERROR(IF(INDIRECT("'"&$B18&"'!$F$10")="","",INDIRECT("'"&$B18&"'!$F$10")),"")) | V18: =IF('2027'!$G$22="","",'2027'!$G$22) | X18: =IF($B18="","",IFERROR(IF(INDIRECT("'"&$B18&"'!$F$12")="","",INDIRECT("'"&$B18&"'!$F$12")),"")) | Y18: =IF($B18="","",IFERROR(IF(INDIRECT("'"&$B18&"'!$B$12")="","",INDIRECT("'"&$B18&"'!$B$12")),"")) | Z18: =IF($B18="","",IFERROR(IF(INDIRECT("'"&$B18&"'!$J$13")="","",INDIRECT("'"&$B18&"'!$J$13")),"")) | AB18: =IF($B18="","",IFERROR(IF(INDIRECT("'"&$B18&"'!$J$4")="","",INDIRECT("'"&$B18&"'!$J$4")),"")) | AC18: =IF($B18="","",2026) | AD18: =IF('2027'!$M$22="","",'2027'!$M$22) | AE18: =IF('2027'!$N$22="","",'2027'!$N$22) | AF18: =IF('2027'!$O$22="","",'2027'!$O$22) -> 0 | AI18: =IF('2027'!$Q$22="","",'2027'!$Q$22) | AJ18: =IF($B18="","",IFERROR(IF(INDIRECT("'"&$B18&"'!$D$21")="","",INDIRECT("'"&$B18&"'!$D$21")),"")) | AK18: =IF($B18="","",IFERROR(IF(INDIRECT("'"&$B18&"'!$E$21")="","",INDIRECT("'"&$B18&"'!$E$21")),"")) | AL18: =IF('2027'!$R$22="","",'2027'!$R$22) -> 0 | AM18: =IFERROR(AI18-AJ18,0) -> 0 | AN18: =IFERROR(AJ18-AK18,0) -> 0 | AO18: =IF('2027'!$S$22="","",'2027'!$S$22) -> 0 | AP18: =IFERROR(AK18/AF18,0) -> 0 | AQ18: =IF($B18="","",IFERROR(IF(INDIRECT("'"&$B18&"'!$K$21")="","",INDIRECT("'"&$B18&"'!$K$21")),"")) | AR18: =IF('2027'!$T$22="","",'2027'!$T$22) | AS18: =IF('2027'!$U$22="","",'2027'!$U$22) -> 0 | AT18: =IF($B18="","",IFERROR(IF(INDIRECT("'"&$B18&"'!$B$15")="","",INDIRECT("'"&$B18&"'!$B$15")),"")) | AV18: =IF($B18="","",IFERROR(IF(INDIRECT("'"&$B18&"'!$B$14")="","",INDIRECT("'"&$B18&"'!$B$14")),"")) | AW18: =IF($B18="","",AY18) | AX18: =IF($B18="","",IFERROR(IF(INDIRECT("'"&$B18&"'!$F$14")="","",INDIRECT("'"&$B18&"'!$F$14")),"")) | AY18: =IF($B18="","",IFERROR(IF(INDIRECT("'"&$B18&"'!$D$35")="","",INDIRECT("'"&$B18&"'!$D$35")),"")) | AZ18: =IF($B18="","",IFERROR(IF(INDIRECT("'"&$B18&"'!$J$14")="","",INDIRECT("'"&$B18&"'!$J$14")),"")) | BA18: =IF($B18="","",IFERROR(IF(INDIRECT("'"&$B18&"'!$I$21")="","",INDIRECT("'"&$B18&"'!$I$21")),"")) | BB18: =IF($B18="","",IFERROR(IF(INDIRECT("'"&$B18&"'!$C$67")="","",INDIRECT("'"&$B18&"'!$C$67")),"")) | BC18: =IF($B18="","",IFERROR(IF(INDIRECT("'"&$B18&"'!$D$68")="","",INDIRECT("'"&$B18&"'!$D$68")),"")) | BD18: =IFERROR(Z18+BB18-BC18,0) -> 0 | BE18: =IF($B18="","",IFERROR(IF(INDIRECT("'"&$B18&"'!$J$21")="","",INDIRECT("'"&$B18&"'!$J$21")),"")) | BF18: =IF($B18="","",IFERROR(IF(INDIRECT("'"&$B18&"'!$F$15")="","",INDIRECT("'"&$B18&"'!$F$15")),"")) | BG18: =IFERROR(N18-TODAY(),"") -> -46258 | BH18: =IF(N18="","",IF(AND(N18-TODAY()>=0,N18-TODAY()<=90),"Sim","Não")) | BI18: =IF(N18="","",IF(N18<TODAY(),"Sim","Não")) | BJ18: =IF(AF18=0,"",IF(IFERROR(AL18/AF18,0)<0.2,"Sim","Não")) | BK18: =IF(AF18=0,"",IF(IFERROR(AK18/AF18,0)>0.9,"Sim","Não")) | BL18: =IF(AY18="","",IF(TODAY()-AY18>60,"Sim","Não")) | BM18: =IF('2027'!$V$22="","",'2027'!$V$22) | BN18: =IF($B18="","",IFERROR(IF(INDIRECT("'"&$B18&"'!$B$24")="","",INDIRECT("'"&$B18&"'!$B$24")),"")) | BO18: =IF($B18="","",IFERROR(IF(INDIRECT("'"&$B18&"'!$B$25")="","",INDIRECT("'"&$B18&"'!$B$25")),"")) | BP18: =IF($B18="","",IFERROR(IF(INDIRECT("'"&$B18&"'!$B$26")="","",INDIRECT("'"&$B18&"'!$B$26")),"")) | BQ18: =IF($B18="","",IFERROR(IF(INDIRECT("'"&$B18&"'!$B$27")="","",INDIRECT("'"&$B18&"'!$B$27")),"")) | BR18: =IF($B18="","",IFERROR(IF(INDIRECT("'"&$B18&"'!$B$28")="","",INDIRECT("'"&$B18&"'!$B$28")),"")) | BS18: =IF($B18="","",IF(AK18="","",IF(ROUND(AK18-SUM(BN18:BR18),2)>0,"Verificar — pagamento sem fonte",IF(ROUND(AK18-SUM(BN18:BR18),2)<0,"Verificar — fonte > pago","OK"))))
A19: =IF('2027'!$E$23="","",'2027'!$E$23) | C19: =IF('2027'!$B$23="","",'2027'!$B$23) | D19: =IF('2027'!$C$23="","",'2027'!$C$23) | E19: =IF('2027'!$D$23="","",'2027'!$D$23) | F19: =IF('2027'!$E$23="","",'2027'!$E$23) | G19: =IF('2027'!$F$23="","",'2027'!$F$23) | H19: =IF('2027'!$H$23="","",'2027'!$H$23) | J19: =IF('2027'!$I$23="","",'2027'!$I$23) | K19: =IF($B19="","",IFERROR(IF(INDIRECT("'"&$B19&"'!$B$10")="","",INDIRECT("'"&$B19&"'!$B$10")),"")) | L19: =IF('2027'!$J$23="","",'2027'!$J$23) | M19: =IF('2027'!$K$23="","",'2027'!$K$23) | N19: =IF('2027'!$L$23="","",'2027'!$L$23) | O19: =IF($B19="","","SMD") | Q19: =IF($B19="","",IFERROR(IF(INDIRECT("'"&$B19&"'!$B$11")="","",INDIRECT("'"&$B19&"'!$B$11")),"")) | R19: =IF($B19="","",IFERROR(IF(INDIRECT("'"&$B19&"'!$F$11")="","",INDIRECT("'"&$B19&"'!$F$11")),"")) | S19: =IF($B19="","",IFERROR(IF(INDIRECT("'"&$B19&"'!$J$11")="","",INDIRECT("'"&$B19&"'!$J$11")),"")) | T19: =IF($B19="","",IFERROR(IF(INDIRECT("'"&$B19&"'!$J$10")="","",INDIRECT("'"&$B19&"'!$J$10")),"")) | U19: =IF($B19="","",IFERROR(IF(INDIRECT("'"&$B19&"'!$F$10")="","",INDIRECT("'"&$B19&"'!$F$10")),"")) | V19: =IF('2027'!$G$23="","",'2027'!$G$23) | X19: =IF($B19="","",IFERROR(IF(INDIRECT("'"&$B19&"'!$F$12")="","",INDIRECT("'"&$B19&"'!$F$12")),"")) | Y19: =IF($B19="","",IFERROR(IF(INDIRECT("'"&$B19&"'!$B$12")="","",INDIRECT("'"&$B19&"'!$B$12")),"")) | Z19: =IF($B19="","",IFERROR(IF(INDIRECT("'"&$B19&"'!$J$13")="","",INDIRECT("'"&$B19&"'!$J$13")),"")) | AB19: =IF($B19="","",IFERROR(IF(INDIRECT("'"&$B19&"'!$J$4")="","",INDIRECT("'"&$B19&"'!$J$4")),"")) | AC19: =IF($B19="","",2026) | AD19: =IF('2027'!$M$23="","",'2027'!$M$23) | AE19: =IF('2027'!$N$23="","",'2027'!$N$23) | AF19: =IF('2027'!$O$23="","",'2027'!$O$23) -> 0 | AI19: =IF('2027'!$Q$23="","",'2027'!$Q$23) | AJ19: =IF($B19="","",IFERROR(IF(INDIRECT("'"&$B19&"'!$D$21")="","",INDIRECT("'"&$B19&"'!$D$21")),"")) | AK19: =IF($B19="","",IFERROR(IF(INDIRECT("'"&$B19&"'!$E$21")="","",INDIRECT("'"&$B19&"'!$E$21")),"")) | AL19: =IF('2027'!$R$23="","",'2027'!$R$23) -> 0 | AM19: =IFERROR(AI19-AJ19,0) -> 0 | AN19: =IFERROR(AJ19-AK19,0) -> 0 | AO19: =IF('2027'!$S$23="","",'2027'!$S$23) -> 0 | AP19: =IFERROR(AK19/AF19,0) -> 0 | AQ19: =IF($B19="","",IFERROR(IF(INDIRECT("'"&$B19&"'!$K$21")="","",INDIRECT("'"&$B19&"'!$K$21")),"")) | AR19: =IF('2027'!$T$23="","",'2027'!$T$23) | AS19: =IF('2027'!$U$23="","",'2027'!$U$23) -> 0 | AT19: =IF($B19="","",IFERROR(IF(INDIRECT("'"&$B19&"'!$B$15")="","",INDIRECT("'"&$B19&"'!$B$15")),"")) | AV19: =IF($B19="","",IFERROR(IF(INDIRECT("'"&$B19&"'!$B$14")="","",INDIRECT("'"&$B19&"'!$B$14")),"")) | AW19: =IF($B19="","",AY19) | AX19: =IF($B19="","",IFERROR(IF(INDIRECT("'"&$B19&"'!$F$14")="","",INDIRECT("'"&$B19&"'!$F$14")),"")) | AY19: =IF($B19="","",IFERROR(IF(INDIRECT("'"&$B19&"'!$D$35")="","",INDIRECT("'"&$B19&"'!$D$35")),"")) | AZ19: =IF($B19="","",IFERROR(IF(INDIRECT("'"&$B19&"'!$J$14")="","",INDIRECT("'"&$B19&"'!$J$14")),"")) | BA19: =IF($B19="","",IFERROR(IF(INDIRECT("'"&$B19&"'!$I$21")="","",INDIRECT("'"&$B19&"'!$I$21")),"")) | BB19: =IF($B19="","",IFERROR(IF(INDIRECT("'"&$B19&"'!$C$67")="","",INDIRECT("'"&$B19&"'!$C$67")),"")) | BC19: =IF($B19="","",IFERROR(IF(INDIRECT("'"&$B19&"'!$D$68")="","",INDIRECT("'"&$B19&"'!$D$68")),"")) | BD19: =IFERROR(Z19+BB19-BC19,0) -> 0 | BE19: =IF($B19="","",IFERROR(IF(INDIRECT("'"&$B19&"'!$J$21")="","",INDIRECT("'"&$B19&"'!$J$21")),"")) | BF19: =IF($B19="","",IFERROR(IF(INDIRECT("'"&$B19&"'!$F$15")="","",INDIRECT("'"&$B19&"'!$F$15")),"")) | BG19: =IFERROR(N19-TODAY(),"") -> -46258 | BH19: =IF(N19="","",IF(AND(N19-TODAY()>=0,N19-TODAY()<=90),"Sim","Não")) | BI19: =IF(N19="","",IF(N19<TODAY(),"Sim","Não")) | BJ19: =IF(AF19=0,"",IF(IFERROR(AL19/AF19,0)<0.2,"Sim","Não")) | BK19: =IF(AF19=0,"",IF(IFERROR(AK19/AF19,0)>0.9,"Sim","Não")) | BL19: =IF(AY19="","",IF(TODAY()-AY19>60,"Sim","Não")) | BM19: =IF('2027'!$V$23="","",'2027'!$V$23) | BN19: =IF($B19="","",IFERROR(IF(INDIRECT("'"&$B19&"'!$B$24")="","",INDIRECT("'"&$B19&"'!$B$24")),"")) | BO19: =IF($B19="","",IFERROR(IF(INDIRECT("'"&$B19&"'!$B$25")="","",INDIRECT("'"&$B19&"'!$B$25")),"")) | BP19: =IF($B19="","",IFERROR(IF(INDIRECT("'"&$B19&"'!$B$26")="","",INDIRECT("'"&$B19&"'!$B$26")),"")) | BQ19: =IF($B19="","",IFERROR(IF(INDIRECT("'"&$B19&"'!$B$27")="","",INDIRECT("'"&$B19&"'!$B$27")),"")) | BR19: =IF($B19="","",IFERROR(IF(INDIRECT("'"&$B19&"'!$B$28")="","",INDIRECT("'"&$B19&"'!$B$28")),"")) | BS19: =IF($B19="","",IF(AK19="","",IF(ROUND(AK19-SUM(BN19:BR19),2)>0,"Verificar — pagamento sem fonte",IF(ROUND(AK19-SUM(BN19:BR19),2)<0,"Verificar — fonte > pago","OK"))))
A20: =IF('2027'!$E$24="","",'2027'!$E$24) | C20: =IF('2027'!$B$24="","",'2027'!$B$24) | D20: =IF('2027'!$C$24="","",'2027'!$C$24) | E20: =IF('2027'!$D$24="","",'2027'!$D$24) | F20: =IF('2027'!$E$24="","",'2027'!$E$24) | G20: =IF('2027'!$F$24="","",'2027'!$F$24) | H20: =IF('2027'!$H$24="","",'2027'!$H$24) | J20: =IF('2027'!$I$24="","",'2027'!$I$24) | K20: =IF($B20="","",IFERROR(IF(INDIRECT("'"&$B20&"'!$B$10")="","",INDIRECT("'"&$B20&"'!$B$10")),"")) | L20: =IF('2027'!$J$24="","",'2027'!$J$24) | M20: =IF('2027'!$K$24="","",'2027'!$K$24) | N20: =IF('2027'!$L$24="","",'2027'!$L$24) | O20: =IF($B20="","","SMD") | Q20: =IF($B20="","",IFERROR(IF(INDIRECT("'"&$B20&"'!$B$11")="","",INDIRECT("'"&$B20&"'!$B$11")),"")) | R20: =IF($B20="","",IFERROR(IF(INDIRECT("'"&$B20&"'!$F$11")="","",INDIRECT("'"&$B20&"'!$F$11")),"")) | S20: =IF($B20="","",IFERROR(IF(INDIRECT("'"&$B20&"'!$J$11")="","",INDIRECT("'"&$B20&"'!$J$11")),"")) | T20: =IF($B20="","",IFERROR(IF(INDIRECT("'"&$B20&"'!$J$10")="","",INDIRECT("'"&$B20&"'!$J$10")),"")) | U20: =IF($B20="","",IFERROR(IF(INDIRECT("'"&$B20&"'!$F$10")="","",INDIRECT("'"&$B20&"'!$F$10")),"")) | V20: =IF('2027'!$G$24="","",'2027'!$G$24) | X20: =IF($B20="","",IFERROR(IF(INDIRECT("'"&$B20&"'!$F$12")="","",INDIRECT("'"&$B20&"'!$F$12")),"")) | Y20: =IF($B20="","",IFERROR(IF(INDIRECT("'"&$B20&"'!$B$12")="","",INDIRECT("'"&$B20&"'!$B$12")),"")) | Z20: =IF($B20="","",IFERROR(IF(INDIRECT("'"&$B20&"'!$J$13")="","",INDIRECT("'"&$B20&"'!$J$13")),"")) | AB20: =IF($B20="","",IFERROR(IF(INDIRECT("'"&$B20&"'!$J$4")="","",INDIRECT("'"&$B20&"'!$J$4")),"")) | AC20: =IF($B20="","",2026) | AD20: =IF('2027'!$M$24="","",'2027'!$M$24) | AE20: =IF('2027'!$N$24="","",'2027'!$N$24) | AF20: =IF('2027'!$O$24="","",'2027'!$O$24) -> 0 | AI20: =IF('2027'!$Q$24="","",'2027'!$Q$24) | AJ20: =IF($B20="","",IFERROR(IF(INDIRECT("'"&$B20&"'!$D$21")="","",INDIRECT("'"&$B20&"'!$D$21")),"")) | AK20: =IF($B20="","",IFERROR(IF(INDIRECT("'"&$B20&"'!$E$21")="","",INDIRECT("'"&$B20&"'!$E$21")),"")) | AL20: =IF('2027'!$R$24="","",'2027'!$R$24) -> 0 | AM20: =IFERROR(AI20-AJ20,0) -> 0 | AN20: =IFERROR(AJ20-AK20,0) -> 0 | AO20: =IF('2027'!$S$24="","",'2027'!$S$24) -> 0 | AP20: =IFERROR(AK20/AF20,0) -> 0 | AQ20: =IF($B20="","",IFERROR(IF(INDIRECT("'"&$B20&"'!$K$21")="","",INDIRECT("'"&$B20&"'!$K$21")),"")) | AR20: =IF('2027'!$T$24="","",'2027'!$T$24) | AS20: =IF('2027'!$U$24="","",'2027'!$U$24) -> 0 | AT20: =IF($B20="","",IFERROR(IF(INDIRECT("'"&$B20&"'!$B$15")="","",INDIRECT("'"&$B20&"'!$B$15")),"")) | AV20: =IF($B20="","",IFERROR(IF(INDIRECT("'"&$B20&"'!$B$14")="","",INDIRECT("'"&$B20&"'!$B$14")),"")) | AW20: =IF($B20="","",AY20) | AX20: =IF($B20="","",IFERROR(IF(INDIRECT("'"&$B20&"'!$F$14")="","",INDIRECT("'"&$B20&"'!$F$14")),"")) | AY20: =IF($B20="","",IFERROR(IF(INDIRECT("'"&$B20&"'!$D$35")="","",INDIRECT("'"&$B20&"'!$D$35")),"")) | AZ20: =IF($B20="","",IFERROR(IF(INDIRECT("'"&$B20&"'!$J$14")="","",INDIRECT("'"&$B20&"'!$J$14")),"")) | BA20: =IF($B20="","",IFERROR(IF(INDIRECT("'"&$B20&"'!$I$21")="","",INDIRECT("'"&$B20&"'!$I$21")),"")) | BB20: =IF($B20="","",IFERROR(IF(INDIRECT("'"&$B20&"'!$C$67")="","",INDIRECT("'"&$B20&"'!$C$67")),"")) | BC20: =IF($B20="","",IFERROR(IF(INDIRECT("'"&$B20&"'!$D$68")="","",INDIRECT("'"&$B20&"'!$D$68")),"")) | BD20: =IFERROR(Z20+BB20-BC20,0) -> 0 | BE20: =IF($B20="","",IFERROR(IF(INDIRECT("'"&$B20&"'!$J$21")="","",INDIRECT("'"&$B20&"'!$J$21")),"")) | BF20: =IF($B20="","",IFERROR(IF(INDIRECT("'"&$B20&"'!$F$15")="","",INDIRECT("'"&$B20&"'!$F$15")),"")) | BG20: =IFERROR(N20-TODAY(),"") -> -46258 | BH20: =IF(N20="","",IF(AND(N20-TODAY()>=0,N20-TODAY()<=90),"Sim","Não")) | BI20: =IF(N20="","",IF(N20<TODAY(),"Sim","Não")) | BJ20: =IF(AF20=0,"",IF(IFERROR(AL20/AF20,0)<0.2,"Sim","Não")) | BK20: =IF(AF20=0,"",IF(IFERROR(AK20/AF20,0)>0.9,"Sim","Não")) | BL20: =IF(AY20="","",IF(TODAY()-AY20>60,"Sim","Não")) | BM20: =IF('2027'!$V$24="","",'2027'!$V$24) | BN20: =IF($B20="","",IFERROR(IF(INDIRECT("'"&$B20&"'!$B$24")="","",INDIRECT("'"&$B20&"'!$B$24")),"")) | BO20: =IF($B20="","",IFERROR(IF(INDIRECT("'"&$B20&"'!$B$25")="","",INDIRECT("'"&$B20&"'!$B$25")),"")) | BP20: =IF($B20="","",IFERROR(IF(INDIRECT("'"&$B20&"'!$B$26")="","",INDIRECT("'"&$B20&"'!$B$26")),"")) | BQ20: =IF($B20="","",IFERROR(IF(INDIRECT("'"&$B20&"'!$B$27")="","",INDIRECT("'"&$B20&"'!$B$27")),"")) | BR20: =IF($B20="","",IFERROR(IF(INDIRECT("'"&$B20&"'!$B$28")="","",INDIRECT("'"&$B20&"'!$B$28")),"")) | BS20: =IF($B20="","",IF(AK20="","",IF(ROUND(AK20-SUM(BN20:BR20),2)>0,"Verificar — pagamento sem fonte",IF(ROUND(AK20-SUM(BN20:BR20),2)<0,"Verificar — fonte > pago","OK"))))
A21: =IF('2027'!$E$25="","",'2027'!$E$25) | C21: =IF('2027'!$B$25="","",'2027'!$B$25) | D21: =IF('2027'!$C$25="","",'2027'!$C$25) | E21: =IF('2027'!$D$25="","",'2027'!$D$25) | F21: =IF('2027'!$E$25="","",'2027'!$E$25) | G21: =IF('2027'!$F$25="","",'2027'!$F$25) | H21: =IF('2027'!$H$25="","",'2027'!$H$25) | J21: =IF('2027'!$I$25="","",'2027'!$I$25) | K21: =IF($B21="","",IFERROR(IF(INDIRECT("'"&$B21&"'!$B$10")="","",INDIRECT("'"&$B21&"'!$B$10")),"")) | L21: =IF('2027'!$J$25="","",'2027'!$J$25) | M21: =IF('2027'!$K$25="","",'2027'!$K$25) | N21: =IF('2027'!$L$25="","",'2027'!$L$25) | O21: =IF($B21="","","SMD") | Q21: =IF($B21="","",IFERROR(IF(INDIRECT("'"&$B21&"'!$B$11")="","",INDIRECT("'"&$B21&"'!$B$11")),"")) | R21: =IF($B21="","",IFERROR(IF(INDIRECT("'"&$B21&"'!$F$11")="","",INDIRECT("'"&$B21&"'!$F$11")),"")) | S21: =IF($B21="","",IFERROR(IF(INDIRECT("'"&$B21&"'!$J$11")="","",INDIRECT("'"&$B21&"'!$J$11")),"")) | T21: =IF($B21="","",IFERROR(IF(INDIRECT("'"&$B21&"'!$J$10")="","",INDIRECT("'"&$B21&"'!$J$10")),"")) | U21: =IF($B21="","",IFERROR(IF(INDIRECT("'"&$B21&"'!$F$10")="","",INDIRECT("'"&$B21&"'!$F$10")),"")) | V21: =IF('2027'!$G$25="","",'2027'!$G$25) | X21: =IF($B21="","",IFERROR(IF(INDIRECT("'"&$B21&"'!$F$12")="","",INDIRECT("'"&$B21&"'!$F$12")),"")) | Y21: =IF($B21="","",IFERROR(IF(INDIRECT("'"&$B21&"'!$B$12")="","",INDIRECT("'"&$B21&"'!$B$12")),"")) | Z21: =IF($B21="","",IFERROR(IF(INDIRECT("'"&$B21&"'!$J$13")="","",INDIRECT("'"&$B21&"'!$J$13")),"")) | AB21: =IF($B21="","",IFERROR(IF(INDIRECT("'"&$B21&"'!$J$4")="","",INDIRECT("'"&$B21&"'!$J$4")),"")) | AC21: =IF($B21="","",2026) | AD21: =IF('2027'!$M$25="","",'2027'!$M$25) | AE21: =IF('2027'!$N$25="","",'2027'!$N$25) | AF21: =IF('2027'!$O$25="","",'2027'!$O$25) -> 0 | AI21: =IF('2027'!$Q$25="","",'2027'!$Q$25) | AJ21: =IF($B21="","",IFERROR(IF(INDIRECT("'"&$B21&"'!$D$21")="","",INDIRECT("'"&$B21&"'!$D$21")),"")) | AK21: =IF($B21="","",IFERROR(IF(INDIRECT("'"&$B21&"'!$E$21")="","",INDIRECT("'"&$B21&"'!$E$21")),"")) | AL21: =IF('2027'!$R$25="","",'2027'!$R$25) -> 0 | AM21: =IFERROR(AI21-AJ21,0) -> 0 | AN21: =IFERROR(AJ21-AK21,0) -> 0 | AO21: =IF('2027'!$S$25="","",'2027'!$S$25) -> 0 | AP21: =IFERROR(AK21/AF21,0) -> 0 | AQ21: =IF($B21="","",IFERROR(IF(INDIRECT("'"&$B21&"'!$K$21")="","",INDIRECT("'"&$B21&"'!$K$21")),"")) | AR21: =IF('2027'!$T$25="","",'2027'!$T$25) | AS21: =IF('2027'!$U$25="","",'2027'!$U$25) -> 0 | AT21: =IF($B21="","",IFERROR(IF(INDIRECT("'"&$B21&"'!$B$15")="","",INDIRECT("'"&$B21&"'!$B$15")),"")) | AV21: =IF($B21="","",IFERROR(IF(INDIRECT("'"&$B21&"'!$B$14")="","",INDIRECT("'"&$B21&"'!$B$14")),"")) | AW21: =IF($B21="","",AY21) | AX21: =IF($B21="","",IFERROR(IF(INDIRECT("'"&$B21&"'!$F$14")="","",INDIRECT("'"&$B21&"'!$F$14")),"")) | AY21: =IF($B21="","",IFERROR(IF(INDIRECT("'"&$B21&"'!$D$35")="","",INDIRECT("'"&$B21&"'!$D$35")),"")) | AZ21: =IF($B21="","",IFERROR(IF(INDIRECT("'"&$B21&"'!$J$14")="","",INDIRECT("'"&$B21&"'!$J$14")),"")) | BA21: =IF($B21="","",IFERROR(IF(INDIRECT("'"&$B21&"'!$I$21")="","",INDIRECT("'"&$B21&"'!$I$21")),"")) | BB21: =IF($B21="","",IFERROR(IF(INDIRECT("'"&$B21&"'!$C$67")="","",INDIRECT("'"&$B21&"'!$C$67")),"")) | BC21: =IF($B21="","",IFERROR(IF(INDIRECT("'"&$B21&"'!$D$68")="","",INDIRECT("'"&$B21&"'!$D$68")),"")) | BD21: =IFERROR(Z21+BB21-BC21,0) -> 0 | BE21: =IF($B21="","",IFERROR(IF(INDIRECT("'"&$B21&"'!$J$21")="","",INDIRECT("'"&$B21&"'!$J$21")),"")) | BF21: =IF($B21="","",IFERROR(IF(INDIRECT("'"&$B21&"'!$F$15")="","",INDIRECT("'"&$B21&"'!$F$15")),"")) | BG21: =IFERROR(N21-TODAY(),"") -> -46258 | BH21: =IF(N21="","",IF(AND(N21-TODAY()>=0,N21-TODAY()<=90),"Sim","Não")) | BI21: =IF(N21="","",IF(N21<TODAY(),"Sim","Não")) | BJ21: =IF(AF21=0,"",IF(IFERROR(AL21/AF21,0)<0.2,"Sim","Não")) | BK21: =IF(AF21=0,"",IF(IFERROR(AK21/AF21,0)>0.9,"Sim","Não")) | BL21: =IF(AY21="","",IF(TODAY()-AY21>60,"Sim","Não")) | BM21: =IF('2027'!$V$25="","",'2027'!$V$25) | BN21: =IF($B21="","",IFERROR(IF(INDIRECT("'"&$B21&"'!$B$24")="","",INDIRECT("'"&$B21&"'!$B$24")),"")) | BO21: =IF($B21="","",IFERROR(IF(INDIRECT("'"&$B21&"'!$B$25")="","",INDIRECT("'"&$B21&"'!$B$25")),"")) | BP21: =IF($B21="","",IFERROR(IF(INDIRECT("'"&$B21&"'!$B$26")="","",INDIRECT("'"&$B21&"'!$B$26")),"")) | BQ21: =IF($B21="","",IFERROR(IF(INDIRECT("'"&$B21&"'!$B$27")="","",INDIRECT("'"&$B21&"'!$B$27")),"")) | BR21: =IF($B21="","",IFERROR(IF(INDIRECT("'"&$B21&"'!$B$28")="","",INDIRECT("'"&$B21&"'!$B$28")),"")) | BS21: =IF($B21="","",IF(AK21="","",IF(ROUND(AK21-SUM(BN21:BR21),2)>0,"Verificar — pagamento sem fonte",IF(ROUND(AK21-SUM(BN21:BR21),2)<0,"Verificar — fonte > pago","OK"))))
A22: =IF('2027'!$E$26="","",'2027'!$E$26) | C22: =IF('2027'!$B$26="","",'2027'!$B$26) | D22: =IF('2027'!$C$26="","",'2027'!$C$26) | E22: =IF('2027'!$D$26="","",'2027'!$D$26) | F22: =IF('2027'!$E$26="","",'2027'!$E$26) | G22: =IF('2027'!$F$26="","",'2027'!$F$26) | H22: =IF('2027'!$H$26="","",'2027'!$H$26) | J22: =IF('2027'!$I$26="","",'2027'!$I$26) | K22: =IF($B22="","",IFERROR(IF(INDIRECT("'"&$B22&"'!$B$10")="","",INDIRECT("'"&$B22&"'!$B$10")),"")) | L22: =IF('2027'!$J$26="","",'2027'!$J$26) | M22: =IF('2027'!$K$26="","",'2027'!$K$26) | N22: =IF('2027'!$L$26="","",'2027'!$L$26) | O22: =IF($B22="","","SMD") | Q22: =IF($B22="","",IFERROR(IF(INDIRECT("'"&$B22&"'!$B$11")="","",INDIRECT("'"&$B22&"'!$B$11")),"")) | R22: =IF($B22="","",IFERROR(IF(INDIRECT("'"&$B22&"'!$F$11")="","",INDIRECT("'"&$B22&"'!$F$11")),"")) | S22: =IF($B22="","",IFERROR(IF(INDIRECT("'"&$B22&"'!$J$11")="","",INDIRECT("'"&$B22&"'!$J$11")),"")) | T22: =IF($B22="","",IFERROR(IF(INDIRECT("'"&$B22&"'!$J$10")="","",INDIRECT("'"&$B22&"'!$J$10")),"")) | U22: =IF($B22="","",IFERROR(IF(INDIRECT("'"&$B22&"'!$F$10")="","",INDIRECT("'"&$B22&"'!$F$10")),"")) | V22: =IF('2027'!$G$26="","",'2027'!$G$26) | X22: =IF($B22="","",IFERROR(IF(INDIRECT("'"&$B22&"'!$F$12")="","",INDIRECT("'"&$B22&"'!$F$12")),"")) | Y22: =IF($B22="","",IFERROR(IF(INDIRECT("'"&$B22&"'!$B$12")="","",INDIRECT("'"&$B22&"'!$B$12")),"")) | Z22: =IF($B22="","",IFERROR(IF(INDIRECT("'"&$B22&"'!$J$13")="","",INDIRECT("'"&$B22&"'!$J$13")),"")) | AB22: =IF($B22="","",IFERROR(IF(INDIRECT("'"&$B22&"'!$J$4")="","",INDIRECT("'"&$B22&"'!$J$4")),"")) | AC22: =IF($B22="","",2026) | AD22: =IF('2027'!$M$26="","",'2027'!$M$26) | AE22: =IF('2027'!$N$26="","",'2027'!$N$26) | AF22: =IF('2027'!$O$26="","",'2027'!$O$26) -> 0 | AI22: =IF('2027'!$Q$26="","",'2027'!$Q$26) | AJ22: =IF($B22="","",IFERROR(IF(INDIRECT("'"&$B22&"'!$D$21")="","",INDIRECT("'"&$B22&"'!$D$21")),"")) | AK22: =IF($B22="","",IFERROR(IF(INDIRECT("'"&$B22&"'!$E$21")="","",INDIRECT("'"&$B22&"'!$E$21")),"")) | AL22: =IF('2027'!$R$26="","",'2027'!$R$26) -> 0 | AM22: =IFERROR(AI22-AJ22,0) -> 0 | AN22: =IFERROR(AJ22-AK22,0) -> 0 | AO22: =IF('2027'!$S$26="","",'2027'!$S$26) -> 0 | AP22: =IFERROR(AK22/AF22,0) -> 0 | AQ22: =IF($B22="","",IFERROR(IF(INDIRECT("'"&$B22&"'!$K$21")="","",INDIRECT("'"&$B22&"'!$K$21")),"")) | AR22: =IF('2027'!$T$26="","",'2027'!$T$26) | AS22: =IF('2027'!$U$26="","",'2027'!$U$26) -> 0 | AT22: =IF($B22="","",IFERROR(IF(INDIRECT("'"&$B22&"'!$B$15")="","",INDIRECT("'"&$B22&"'!$B$15")),"")) | AV22: =IF($B22="","",IFERROR(IF(INDIRECT("'"&$B22&"'!$B$14")="","",INDIRECT("'"&$B22&"'!$B$14")),"")) | AW22: =IF($B22="","",AY22) | AX22: =IF($B22="","",IFERROR(IF(INDIRECT("'"&$B22&"'!$F$14")="","",INDIRECT("'"&$B22&"'!$F$14")),"")) | AY22: =IF($B22="","",IFERROR(IF(INDIRECT("'"&$B22&"'!$D$35")="","",INDIRECT("'"&$B22&"'!$D$35")),"")) | AZ22: =IF($B22="","",IFERROR(IF(INDIRECT("'"&$B22&"'!$J$14")="","",INDIRECT("'"&$B22&"'!$J$14")),"")) | BA22: =IF($B22="","",IFERROR(IF(INDIRECT("'"&$B22&"'!$I$21")="","",INDIRECT("'"&$B22&"'!$I$21")),"")) | BB22: =IF($B22="","",IFERROR(IF(INDIRECT("'"&$B22&"'!$C$67")="","",INDIRECT("'"&$B22&"'!$C$67")),"")) | BC22: =IF($B22="","",IFERROR(IF(INDIRECT("'"&$B22&"'!$D$68")="","",INDIRECT("'"&$B22&"'!$D$68")),"")) | BD22: =IFERROR(Z22+BB22-BC22,0) -> 0 | BE22: =IF($B22="","",IFERROR(IF(INDIRECT("'"&$B22&"'!$J$21")="","",INDIRECT("'"&$B22&"'!$J$21")),"")) | BF22: =IF($B22="","",IFERROR(IF(INDIRECT("'"&$B22&"'!$F$15")="","",INDIRECT("'"&$B22&"'!$F$15")),"")) | BG22: =IFERROR(N22-TODAY(),"") -> -46258 | BH22: =IF(N22="","",IF(AND(N22-TODAY()>=0,N22-TODAY()<=90),"Sim","Não")) | BI22: =IF(N22="","",IF(N22<TODAY(),"Sim","Não")) | BJ22: =IF(AF22=0,"",IF(IFERROR(AL22/AF22,0)<0.2,"Sim","Não")) | BK22: =IF(AF22=0,"",IF(IFERROR(AK22/AF22,0)>0.9,"Sim","Não")) | BL22: =IF(AY22="","",IF(TODAY()-AY22>60,"Sim","Não")) | BM22: =IF('2027'!$V$26="","",'2027'!$V$26) | BN22: =IF($B22="","",IFERROR(IF(INDIRECT("'"&$B22&"'!$B$24")="","",INDIRECT("'"&$B22&"'!$B$24")),"")) | BO22: =IF($B22="","",IFERROR(IF(INDIRECT("'"&$B22&"'!$B$25")="","",INDIRECT("'"&$B22&"'!$B$25")),"")) | BP22: =IF($B22="","",IFERROR(IF(INDIRECT("'"&$B22&"'!$B$26")="","",INDIRECT("'"&$B22&"'!$B$26")),"")) | BQ22: =IF($B22="","",IFERROR(IF(INDIRECT("'"&$B22&"'!$B$27")="","",INDIRECT("'"&$B22&"'!$B$27")),"")) | BR22: =IF($B22="","",IFERROR(IF(INDIRECT("'"&$B22&"'!$B$28")="","",INDIRECT("'"&$B22&"'!$B$28")),"")) | BS22: =IF($B22="","",IF(AK22="","",IF(ROUND(AK22-SUM(BN22:BR22),2)>0,"Verificar — pagamento sem fonte",IF(ROUND(AK22-SUM(BN22:BR22),2)<0,"Verificar — fonte > pago","OK"))))
A23: =IF('2027'!$E$27="","",'2027'!$E$27) | C23: =IF('2027'!$B$27="","",'2027'!$B$27) | D23: =IF('2027'!$C$27="","",'2027'!$C$27) | E23: =IF('2027'!$D$27="","",'2027'!$D$27) | F23: =IF('2027'!$E$27="","",'2027'!$E$27) | G23: =IF('2027'!$F$27="","",'2027'!$F$27) | H23: =IF('2027'!$H$27="","",'2027'!$H$27) | J23: =IF('2027'!$I$27="","",'2027'!$I$27) | K23: =IF($B23="","",IFERROR(IF(INDIRECT("'"&$B23&"'!$B$10")="","",INDIRECT("'"&$B23&"'!$B$10")),"")) | L23: =IF('2027'!$J$27="","",'2027'!$J$27) | M23: =IF('2027'!$K$27="","",'2027'!$K$27) | N23: =IF('2027'!$L$27="","",'2027'!$L$27) | O23: =IF($B23="","","SMD") | Q23: =IF($B23="","",IFERROR(IF(INDIRECT("'"&$B23&"'!$B$11")="","",INDIRECT("'"&$B23&"'!$B$11")),"")) | R23: =IF($B23="","",IFERROR(IF(INDIRECT("'"&$B23&"'!$F$11")="","",INDIRECT("'"&$B23&"'!$F$11")),"")) | S23: =IF($B23="","",IFERROR(IF(INDIRECT("'"&$B23&"'!$J$11")="","",INDIRECT("'"&$B23&"'!$J$11")),"")) | T23: =IF($B23="","",IFERROR(IF(INDIRECT("'"&$B23&"'!$J$10")="","",INDIRECT("'"&$B23&"'!$J$10")),"")) | U23: =IF($B23="","",IFERROR(IF(INDIRECT("'"&$B23&"'!$F$10")="","",INDIRECT("'"&$B23&"'!$F$10")),"")) | V23: =IF('2027'!$G$27="","",'2027'!$G$27) | X23: =IF($B23="","",IFERROR(IF(INDIRECT("'"&$B23&"'!$F$12")="","",INDIRECT("'"&$B23&"'!$F$12")),"")) | Y23: =IF($B23="","",IFERROR(IF(INDIRECT("'"&$B23&"'!$B$12")="","",INDIRECT("'"&$B23&"'!$B$12")),"")) | Z23: =IF($B23="","",IFERROR(IF(INDIRECT("'"&$B23&"'!$J$13")="","",INDIRECT("'"&$B23&"'!$J$13")),"")) | AB23: =IF($B23="","",IFERROR(IF(INDIRECT("'"&$B23&"'!$J$4")="","",INDIRECT("'"&$B23&"'!$J$4")),"")) | AC23: =IF($B23="","",2026) | AD23: =IF('2027'!$M$27="","",'2027'!$M$27) | AE23: =IF('2027'!$N$27="","",'2027'!$N$27) | AF23: =IF('2027'!$O$27="","",'2027'!$O$27) -> 0 | AI23: =IF('2027'!$Q$27="","",'2027'!$Q$27) | AJ23: =IF($B23="","",IFERROR(IF(INDIRECT("'"&$B23&"'!$D$21")="","",INDIRECT("'"&$B23&"'!$D$21")),"")) | AK23: =IF($B23="","",IFERROR(IF(INDIRECT("'"&$B23&"'!$E$21")="","",INDIRECT("'"&$B23&"'!$E$21")),"")) | AL23: =IF('2027'!$R$27="","",'2027'!$R$27) -> 0 | AM23: =IFERROR(AI23-AJ23,0) -> 0 | AN23: =IFERROR(AJ23-AK23,0) -> 0 | AO23: =IF('2027'!$S$27="","",'2027'!$S$27) -> 0 | AP23: =IFERROR(AK23/AF23,0) -> 0 | AQ23: =IF($B23="","",IFERROR(IF(INDIRECT("'"&$B23&"'!$K$21")="","",INDIRECT("'"&$B23&"'!$K$21")),"")) | AR23: =IF('2027'!$T$27="","",'2027'!$T$27) | AS23: =IF('2027'!$U$27="","",'2027'!$U$27) -> 0 | AT23: =IF($B23="","",IFERROR(IF(INDIRECT("'"&$B23&"'!$B$15")="","",INDIRECT("'"&$B23&"'!$B$15")),"")) | AV23: =IF($B23="","",IFERROR(IF(INDIRECT("'"&$B23&"'!$B$14")="","",INDIRECT("'"&$B23&"'!$B$14")),"")) | AW23: =IF($B23="","",AY23) | AX23: =IF($B23="","",IFERROR(IF(INDIRECT("'"&$B23&"'!$F$14")="","",INDIRECT("'"&$B23&"'!$F$14")),"")) | AY23: =IF($B23="","",IFERROR(IF(INDIRECT("'"&$B23&"'!$D$35")="","",INDIRECT("'"&$B23&"'!$D$35")),"")) | AZ23: =IF($B23="","",IFERROR(IF(INDIRECT("'"&$B23&"'!$J$14")="","",INDIRECT("'"&$B23&"'!$J$14")),"")) | BA23: =IF($B23="","",IFERROR(IF(INDIRECT("'"&$B23&"'!$I$21")="","",INDIRECT("'"&$B23&"'!$I$21")),"")) | BB23: =IF($B23="","",IFERROR(IF(INDIRECT("'"&$B23&"'!$C$67")="","",INDIRECT("'"&$B23&"'!$C$67")),"")) | BC23: =IF($B23="","",IFERROR(IF(INDIRECT("'"&$B23&"'!$D$68")="","",INDIRECT("'"&$B23&"'!$D$68")),"")) | BD23: =IFERROR(Z23+BB23-BC23,0) -> 0 | BE23: =IF($B23="","",IFERROR(IF(INDIRECT("'"&$B23&"'!$J$21")="","",INDIRECT("'"&$B23&"'!$J$21")),"")) | BF23: =IF($B23="","",IFERROR(IF(INDIRECT("'"&$B23&"'!$F$15")="","",INDIRECT("'"&$B23&"'!$F$15")),"")) | BG23: =IFERROR(N23-TODAY(),"") -> -46258 | BH23: =IF(N23="","",IF(AND(N23-TODAY()>=0,N23-TODAY()<=90),"Sim","Não")) | BI23: =IF(N23="","",IF(N23<TODAY(),"Sim","Não")) | BJ23: =IF(AF23=0,"",IF(IFERROR(AL23/AF23,0)<0.2,"Sim","Não")) | BK23: =IF(AF23=0,"",IF(IFERROR(AK23/AF23,0)>0.9,"Sim","Não")) | BL23: =IF(AY23="","",IF(TODAY()-AY23>60,"Sim","Não")) | BM23: =IF('2027'!$V$27="","",'2027'!$V$27) | BN23: =IF($B23="","",IFERROR(IF(INDIRECT("'"&$B23&"'!$B$24")="","",INDIRECT("'"&$B23&"'!$B$24")),"")) | BO23: =IF($B23="","",IFERROR(IF(INDIRECT("'"&$B23&"'!$B$25")="","",INDIRECT("'"&$B23&"'!$B$25")),"")) | BP23: =IF($B23="","",IFERROR(IF(INDIRECT("'"&$B23&"'!$B$26")="","",INDIRECT("'"&$B23&"'!$B$26")),"")) | BQ23: =IF($B23="","",IFERROR(IF(INDIRECT("'"&$B23&"'!$B$27")="","",INDIRECT("'"&$B23&"'!$B$27")),"")) | BR23: =IF($B23="","",IFERROR(IF(INDIRECT("'"&$B23&"'!$B$28")="","",INDIRECT("'"&$B23&"'!$B$28")),"")) | BS23: =IF($B23="","",IF(AK23="","",IF(ROUND(AK23-SUM(BN23:BR23),2)>0,"Verificar — pagamento sem fonte",IF(ROUND(AK23-SUM(BN23:BR23),2)<0,"Verificar — fonte > pago","OK"))))
A24: =IF('2027'!$E$28="","",'2027'!$E$28) | C24: =IF('2027'!$B$28="","",'2027'!$B$28) | D24: =IF('2027'!$C$28="","",'2027'!$C$28) | E24: =IF('2027'!$D$28="","",'2027'!$D$28) | F24: =IF('2027'!$E$28="","",'2027'!$E$28) | G24: =IF('2027'!$F$28="","",'2027'!$F$28) | H24: =IF('2027'!$H$28="","",'2027'!$H$28) | J24: =IF('2027'!$I$28="","",'2027'!$I$28) | K24: =IF($B24="","",IFERROR(IF(INDIRECT("'"&$B24&"'!$B$10")="","",INDIRECT("'"&$B24&"'!$B$10")),"")) | L24: =IF('2027'!$J$28="","",'2027'!$J$28) | M24: =IF('2027'!$K$28="","",'2027'!$K$28) | N24: =IF('2027'!$L$28="","",'2027'!$L$28) | O24: =IF($B24="","","SMD") | Q24: =IF($B24="","",IFERROR(IF(INDIRECT("'"&$B24&"'!$B$11")="","",INDIRECT("'"&$B24&"'!$B$11")),"")) | R24: =IF($B24="","",IFERROR(IF(INDIRECT("'"&$B24&"'!$F$11")="","",INDIRECT("'"&$B24&"'!$F$11")),"")) | S24: =IF($B24="","",IFERROR(IF(INDIRECT("'"&$B24&"'!$J$11")="","",INDIRECT("'"&$B24&"'!$J$11")),"")) | T24: =IF($B24="","",IFERROR(IF(INDIRECT("'"&$B24&"'!$J$10")="","",INDIRECT("'"&$B24&"'!$J$10")),"")) | U24: =IF($B24="","",IFERROR(IF(INDIRECT("'"&$B24&"'!$F$10")="","",INDIRECT("'"&$B24&"'!$F$10")),"")) | V24: =IF('2027'!$G$28="","",'2027'!$G$28) | X24: =IF($B24="","",IFERROR(IF(INDIRECT("'"&$B24&"'!$F$12")="","",INDIRECT("'"&$B24&"'!$F$12")),"")) | Y24: =IF($B24="","",IFERROR(IF(INDIRECT("'"&$B24&"'!$B$12")="","",INDIRECT("'"&$B24&"'!$B$12")),"")) | Z24: =IF($B24="","",IFERROR(IF(INDIRECT("'"&$B24&"'!$J$13")="","",INDIRECT("'"&$B24&"'!$J$13")),"")) | AB24: =IF($B24="","",IFERROR(IF(INDIRECT("'"&$B24&"'!$J$4")="","",INDIRECT("'"&$B24&"'!$J$4")),"")) | AC24: =IF($B24="","",2026) | AD24: =IF('2027'!$M$28="","",'2027'!$M$28) | AE24: =IF('2027'!$N$28="","",'2027'!$N$28) | AF24: =IF('2027'!$O$28="","",'2027'!$O$28) -> 0 | AI24: =IF('2027'!$Q$28="","",'2027'!$Q$28) | AJ24: =IF($B24="","",IFERROR(IF(INDIRECT("'"&$B24&"'!$D$21")="","",INDIRECT("'"&$B24&"'!$D$21")),"")) | AK24: =IF($B24="","",IFERROR(IF(INDIRECT("'"&$B24&"'!$E$21")="","",INDIRECT("'"&$B24&"'!$E$21")),"")) | AL24: =IF('2027'!$R$28="","",'2027'!$R$28) -> 0 | AM24: =IFERROR(AI24-AJ24,0) -> 0 | AN24: =IFERROR(AJ24-AK24,0) -> 0 | AO24: =IF('2027'!$S$28="","",'2027'!$S$28) -> 0 | AP24: =IFERROR(AK24/AF24,0) -> 0 | AQ24: =IF($B24="","",IFERROR(IF(INDIRECT("'"&$B24&"'!$K$21")="","",INDIRECT("'"&$B24&"'!$K$21")),"")) | AR24: =IF('2027'!$T$28="","",'2027'!$T$28) | AS24: =IF('2027'!$U$28="","",'2027'!$U$28) -> 0 | AT24: =IF($B24="","",IFERROR(IF(INDIRECT("'"&$B24&"'!$B$15")="","",INDIRECT("'"&$B24&"'!$B$15")),"")) | AV24: =IF($B24="","",IFERROR(IF(INDIRECT("'"&$B24&"'!$B$14")="","",INDIRECT("'"&$B24&"'!$B$14")),"")) | AW24: =IF($B24="","",AY24) | AX24: =IF($B24="","",IFERROR(IF(INDIRECT("'"&$B24&"'!$F$14")="","",INDIRECT("'"&$B24&"'!$F$14")),"")) | AY24: =IF($B24="","",IFERROR(IF(INDIRECT("'"&$B24&"'!$D$35")="","",INDIRECT("'"&$B24&"'!$D$35")),"")) | AZ24: =IF($B24="","",IFERROR(IF(INDIRECT("'"&$B24&"'!$J$14")="","",INDIRECT("'"&$B24&"'!$J$14")),"")) | BA24: =IF($B24="","",IFERROR(IF(INDIRECT("'"&$B24&"'!$I$21")="","",INDIRECT("'"&$B24&"'!$I$21")),"")) | BB24: =IF($B24="","",IFERROR(IF(INDIRECT("'"&$B24&"'!$C$67")="","",INDIRECT("'"&$B24&"'!$C$67")),"")) | BC24: =IF($B24="","",IFERROR(IF(INDIRECT("'"&$B24&"'!$D$68")="","",INDIRECT("'"&$B24&"'!$D$68")),"")) | BD24: =IFERROR(Z24+BB24-BC24,0) -> 0 | BE24: =IF($B24="","",IFERROR(IF(INDIRECT("'"&$B24&"'!$J$21")="","",INDIRECT("'"&$B24&"'!$J$21")),"")) | BF24: =IF($B24="","",IFERROR(IF(INDIRECT("'"&$B24&"'!$F$15")="","",INDIRECT("'"&$B24&"'!$F$15")),"")) | BG24: =IFERROR(N24-TODAY(),"") -> -46258 | BH24: =IF(N24="","",IF(AND(N24-TODAY()>=0,N24-TODAY()<=90),"Sim","Não")) | BI24: =IF(N24="","",IF(N24<TODAY(),"Sim","Não")) | BJ24: =IF(AF24=0,"",IF(IFERROR(AL24/AF24,0)<0.2,"Sim","Não")) | BK24: =IF(AF24=0,"",IF(IFERROR(AK24/AF24,0)>0.9,"Sim","Não")) | BL24: =IF(AY24="","",IF(TODAY()-AY24>60,"Sim","Não")) | BM24: =IF('2027'!$V$28="","",'2027'!$V$28) | BN24: =IF($B24="","",IFERROR(IF(INDIRECT("'"&$B24&"'!$B$24")="","",INDIRECT("'"&$B24&"'!$B$24")),"")) | BO24: =IF($B24="","",IFERROR(IF(INDIRECT("'"&$B24&"'!$B$25")="","",INDIRECT("'"&$B24&"'!$B$25")),"")) | BP24: =IF($B24="","",IFERROR(IF(INDIRECT("'"&$B24&"'!$B$26")="","",INDIRECT("'"&$B24&"'!$B$26")),"")) | BQ24: =IF($B24="","",IFERROR(IF(INDIRECT("'"&$B24&"'!$B$27")="","",INDIRECT("'"&$B24&"'!$B$27")),"")) | BR24: =IF($B24="","",IFERROR(IF(INDIRECT("'"&$B24&"'!$B$28")="","",INDIRECT("'"&$B24&"'!$B$28")),"")) | BS24: =IF($B24="","",IF(AK24="","",IF(ROUND(AK24-SUM(BN24:BR24),2)>0,"Verificar — pagamento sem fonte",IF(ROUND(AK24-SUM(BN24:BR24),2)<0,"Verificar — fonte > pago","OK"))))
A25: =IF('2027'!$E$29="","",'2027'!$E$29) | C25: =IF('2027'!$B$29="","",'2027'!$B$29) | D25: =IF('2027'!$C$29="","",'2027'!$C$29) | E25: =IF('2027'!$D$29="","",'2027'!$D$29) | F25: =IF('2027'!$E$29="","",'2027'!$E$29) | G25: =IF('2027'!$F$29="","",'2027'!$F$29) | H25: =IF('2027'!$H$29="","",'2027'!$H$29) | J25: =IF('2027'!$I$29="","",'2027'!$I$29) | K25: =IF($B25="","",IFERROR(IF(INDIRECT("'"&$B25&"'!$B$10")="","",INDIRECT("'"&$B25&"'!$B$10")),"")) | L25: =IF('2027'!$J$29="","",'2027'!$J$29) | M25: =IF('2027'!$K$29="","",'2027'!$K$29) | N25: =IF('2027'!$L$29="","",'2027'!$L$29) | O25: =IF($B25="","","SMD") | Q25: =IF($B25="","",IFERROR(IF(INDIRECT("'"&$B25&"'!$B$11")="","",INDIRECT("'"&$B25&"'!$B$11")),"")) | R25: =IF($B25="","",IFERROR(IF(INDIRECT("'"&$B25&"'!$F$11")="","",INDIRECT("'"&$B25&"'!$F$11")),"")) | S25: =IF($B25="","",IFERROR(IF(INDIRECT("'"&$B25&"'!$J$11")="","",INDIRECT("'"&$B25&"'!$J$11")),"")) | T25: =IF($B25="","",IFERROR(IF(INDIRECT("'"&$B25&"'!$J$10")="","",INDIRECT("'"&$B25&"'!$J$10")),"")) | U25: =IF($B25="","",IFERROR(IF(INDIRECT("'"&$B25&"'!$F$10")="","",INDIRECT("'"&$B25&"'!$F$10")),"")) | V25: =IF('2027'!$G$29="","",'2027'!$G$29) | X25: =IF($B25="","",IFERROR(IF(INDIRECT("'"&$B25&"'!$F$12")="","",INDIRECT("'"&$B25&"'!$F$12")),"")) | Y25: =IF($B25="","",IFERROR(IF(INDIRECT("'"&$B25&"'!$B$12")="","",INDIRECT("'"&$B25&"'!$B$12")),"")) | Z25: =IF($B25="","",IFERROR(IF(INDIRECT("'"&$B25&"'!$J$13")="","",INDIRECT("'"&$B25&"'!$J$13")),"")) | AB25: =IF($B25="","",IFERROR(IF(INDIRECT("'"&$B25&"'!$J$4")="","",INDIRECT("'"&$B25&"'!$J$4")),"")) | AC25: =IF($B25="","",2026) | AD25: =IF('2027'!$M$29="","",'2027'!$M$29) | AE25: =IF('2027'!$N$29="","",'2027'!$N$29) | AF25: =IF('2027'!$O$29="","",'2027'!$O$29) -> 0 | AI25: =IF('2027'!$Q$29="","",'2027'!$Q$29) | AJ25: =IF($B25="","",IFERROR(IF(INDIRECT("'"&$B25&"'!$D$21")="","",INDIRECT("'"&$B25&"'!$D$21")),"")) | AK25: =IF($B25="","",IFERROR(IF(INDIRECT("'"&$B25&"'!$E$21")="","",INDIRECT("'"&$B25&"'!$E$21")),"")) | AL25: =IF('2027'!$R$29="","",'2027'!$R$29) -> 0 | AM25: =IFERROR(AI25-AJ25,0) -> 0 | AN25: =IFERROR(AJ25-AK25,0) -> 0 | AO25: =IF('2027'!$S$29="","",'2027'!$S$29) -> 0 | AP25: =IFERROR(AK25/AF25,0) -> 0 | AQ25: =IF($B25="","",IFERROR(IF(INDIRECT("'"&$B25&"'!$K$21")="","",INDIRECT("'"&$B25&"'!$K$21")),"")) | AR25: =IF('2027'!$T$29="","",'2027'!$T$29) | AS25: =IF('2027'!$U$29="","",'2027'!$U$29) -> 0 | AT25: =IF($B25="","",IFERROR(IF(INDIRECT("'"&$B25&"'!$B$15")="","",INDIRECT("'"&$B25&"'!$B$15")),"")) | AV25: =IF($B25="","",IFERROR(IF(INDIRECT("'"&$B25&"'!$B$14")="","",INDIRECT("'"&$B25&"'!$B$14")),"")) | AW25: =IF($B25="","",AY25) | AX25: =IF($B25="","",IFERROR(IF(INDIRECT("'"&$B25&"'!$F$14")="","",INDIRECT("'"&$B25&"'!$F$14")),"")) | AY25: =IF($B25="","",IFERROR(IF(INDIRECT("'"&$B25&"'!$D$35")="","",INDIRECT("'"&$B25&"'!$D$35")),"")) | AZ25: =IF($B25="","",IFERROR(IF(INDIRECT("'"&$B25&"'!$J$14")="","",INDIRECT("'"&$B25&"'!$J$14")),"")) | BA25: =IF($B25="","",IFERROR(IF(INDIRECT("'"&$B25&"'!$I$21")="","",INDIRECT("'"&$B25&"'!$I$21")),"")) | BB25: =IF($B25="","",IFERROR(IF(INDIRECT("'"&$B25&"'!$C$67")="","",INDIRECT("'"&$B25&"'!$C$67")),"")) | BC25: =IF($B25="","",IFERROR(IF(INDIRECT("'"&$B25&"'!$D$68")="","",INDIRECT("'"&$B25&"'!$D$68")),"")) | BD25: =IFERROR(Z25+BB25-BC25,0) -> 0 | BE25: =IF($B25="","",IFERROR(IF(INDIRECT("'"&$B25&"'!$J$21")="","",INDIRECT("'"&$B25&"'!$J$21")),"")) | BF25: =IF($B25="","",IFERROR(IF(INDIRECT("'"&$B25&"'!$F$15")="","",INDIRECT("'"&$B25&"'!$F$15")),"")) | BG25: =IFERROR(N25-TODAY(),"") -> -46258 | BH25: =IF(N25="","",IF(AND(N25-TODAY()>=0,N25-TODAY()<=90),"Sim","Não")) | BI25: =IF(N25="","",IF(N25<TODAY(),"Sim","Não")) | BJ25: =IF(AF25=0,"",IF(IFERROR(AL25/AF25,0)<0.2,"Sim","Não")) | BK25: =IF(AF25=0,"",IF(IFERROR(AK25/AF25,0)>0.9,"Sim","Não")) | BL25: =IF(AY25="","",IF(TODAY()-AY25>60,"Sim","Não")) | BM25: =IF('2027'!$V$29="","",'2027'!$V$29) | BN25: =IF($B25="","",IFERROR(IF(INDIRECT("'"&$B25&"'!$B$24")="","",INDIRECT("'"&$B25&"'!$B$24")),"")) | BO25: =IF($B25="","",IFERROR(IF(INDIRECT("'"&$B25&"'!$B$25")="","",INDIRECT("'"&$B25&"'!$B$25")),"")) | BP25: =IF($B25="","",IFERROR(IF(INDIRECT("'"&$B25&"'!$B$26")="","",INDIRECT("'"&$B25&"'!$B$26")),"")) | BQ25: =IF($B25="","",IFERROR(IF(INDIRECT("'"&$B25&"'!$B$27")="","",INDIRECT("'"&$B25&"'!$B$27")),"")) | BR25: =IF($B25="","",IFERROR(IF(INDIRECT("'"&$B25&"'!$B$28")="","",INDIRECT("'"&$B25&"'!$B$28")),"")) | BS25: =IF($B25="","",IF(AK25="","",IF(ROUND(AK25-SUM(BN25:BR25),2)>0,"Verificar — pagamento sem fonte",IF(ROUND(AK25-SUM(BN25:BR25),2)<0,"Verificar — fonte > pago","OK"))))
A26: =IF('2027'!$E$30="","",'2027'!$E$30) | C26: =IF('2027'!$B$30="","",'2027'!$B$30) | D26: =IF('2027'!$C$30="","",'2027'!$C$30) | E26: =IF('2027'!$D$30="","",'2027'!$D$30) | F26: =IF('2027'!$E$30="","",'2027'!$E$30) | G26: =IF('2027'!$F$30="","",'2027'!$F$30) | H26: =IF('2027'!$H$30="","",'2027'!$H$30) | J26: =IF('2027'!$I$30="","",'2027'!$I$30) | K26: =IF($B26="","",IFERROR(IF(INDIRECT("'"&$B26&"'!$B$10")="","",INDIRECT("'"&$B26&"'!$B$10")),"")) | L26: =IF('2027'!$J$30="","",'2027'!$J$30) | M26: =IF('2027'!$K$30="","",'2027'!$K$30) | N26: =IF('2027'!$L$30="","",'2027'!$L$30) | O26: =IF($B26="","","SMD") | Q26: =IF($B26="","",IFERROR(IF(INDIRECT("'"&$B26&"'!$B$11")="","",INDIRECT("'"&$B26&"'!$B$11")),"")) | R26: =IF($B26="","",IFERROR(IF(INDIRECT("'"&$B26&"'!$F$11")="","",INDIRECT("'"&$B26&"'!$F$11")),"")) | S26: =IF($B26="","",IFERROR(IF(INDIRECT("'"&$B26&"'!$J$11")="","",INDIRECT("'"&$B26&"'!$J$11")),"")) | T26: =IF($B26="","",IFERROR(IF(INDIRECT("'"&$B26&"'!$J$10")="","",INDIRECT("'"&$B26&"'!$J$10")),"")) | U26: =IF($B26="","",IFERROR(IF(INDIRECT("'"&$B26&"'!$F$10")="","",INDIRECT("'"&$B26&"'!$F$10")),"")) | V26: =IF('2027'!$G$30="","",'2027'!$G$30) | X26: =IF($B26="","",IFERROR(IF(INDIRECT("'"&$B26&"'!$F$12")="","",INDIRECT("'"&$B26&"'!$F$12")),"")) | Y26: =IF($B26="","",IFERROR(IF(INDIRECT("'"&$B26&"'!$B$12")="","",INDIRECT("'"&$B26&"'!$B$12")),"")) | Z26: =IF($B26="","",IFERROR(IF(INDIRECT("'"&$B26&"'!$J$13")="","",INDIRECT("'"&$B26&"'!$J$13")),"")) | AB26: =IF($B26="","",IFERROR(IF(INDIRECT("'"&$B26&"'!$J$4")="","",INDIRECT("'"&$B26&"'!$J$4")),"")) | AC26: =IF($B26="","",2026) | AD26: =IF('2027'!$M$30="","",'2027'!$M$30) | AE26: =IF('2027'!$N$30="","",'2027'!$N$30) | AF26: =IF('2027'!$O$30="","",'2027'!$O$30) -> 0 | AI26: =IF('2027'!$Q$30="","",'2027'!$Q$30) | AJ26: =IF($B26="","",IFERROR(IF(INDIRECT("'"&$B26&"'!$D$21")="","",INDIRECT("'"&$B26&"'!$D$21")),"")) | AK26: =IF($B26="","",IFERROR(IF(INDIRECT("'"&$B26&"'!$E$21")="","",INDIRECT("'"&$B26&"'!$E$21")),"")) | AL26: =IF('2027'!$R$30="","",'2027'!$R$30) -> 0 | AM26: =IFERROR(AI26-AJ26,0) -> 0 | AN26: =IFERROR(AJ26-AK26,0) -> 0 | AO26: =IF('2027'!$S$30="","",'2027'!$S$30) -> 0 | AP26: =IFERROR(AK26/AF26,0) -> 0 | AQ26: =IF($B26="","",IFERROR(IF(INDIRECT("'"&$B26&"'!$K$21")="","",INDIRECT("'"&$B26&"'!$K$21")),"")) | AR26: =IF('2027'!$T$30="","",'2027'!$T$30) | AS26: =IF('2027'!$U$30="","",'2027'!$U$30) -> 0 | AT26: =IF($B26="","",IFERROR(IF(INDIRECT("'"&$B26&"'!$B$15")="","",INDIRECT("'"&$B26&"'!$B$15")),"")) | AV26: =IF($B26="","",IFERROR(IF(INDIRECT("'"&$B26&"'!$B$14")="","",INDIRECT("'"&$B26&"'!$B$14")),"")) | AW26: =IF($B26="","",AY26) | AX26: =IF($B26="","",IFERROR(IF(INDIRECT("'"&$B26&"'!$F$14")="","",INDIRECT("'"&$B26&"'!$F$14")),"")) | AY26: =IF($B26="","",IFERROR(IF(INDIRECT("'"&$B26&"'!$D$35")="","",INDIRECT("'"&$B26&"'!$D$35")),"")) | AZ26: =IF($B26="","",IFERROR(IF(INDIRECT("'"&$B26&"'!$J$14")="","",INDIRECT("'"&$B26&"'!$J$14")),"")) | BA26: =IF($B26="","",IFERROR(IF(INDIRECT("'"&$B26&"'!$I$21")="","",INDIRECT("'"&$B26&"'!$I$21")),"")) | BB26: =IF($B26="","",IFERROR(IF(INDIRECT("'"&$B26&"'!$C$67")="","",INDIRECT("'"&$B26&"'!$C$67")),"")) | BC26: =IF($B26="","",IFERROR(IF(INDIRECT("'"&$B26&"'!$D$68")="","",INDIRECT("'"&$B26&"'!$D$68")),"")) | BD26: =IFERROR(Z26+BB26-BC26,0) -> 0 | BE26: =IF($B26="","",IFERROR(IF(INDIRECT("'"&$B26&"'!$J$21")="","",INDIRECT("'"&$B26&"'!$J$21")),"")) | BF26: =IF($B26="","",IFERROR(IF(INDIRECT("'"&$B26&"'!$F$15")="","",INDIRECT("'"&$B26&"'!$F$15")),"")) | BG26: =IFERROR(N26-TODAY(),"") -> -46258 | BH26: =IF(N26="","",IF(AND(N26-TODAY()>=0,N26-TODAY()<=90),"Sim","Não")) | BI26: =IF(N26="","",IF(N26<TODAY(),"Sim","Não")) | BJ26: =IF(AF26=0,"",IF(IFERROR(AL26/AF26,0)<0.2,"Sim","Não")) | BK26: =IF(AF26=0,"",IF(IFERROR(AK26/AF26,0)>0.9,"Sim","Não")) | BL26: =IF(AY26="","",IF(TODAY()-AY26>60,"Sim","Não")) | BM26: =IF('2027'!$V$30="","",'2027'!$V$30) | BN26: =IF($B26="","",IFERROR(IF(INDIRECT("'"&$B26&"'!$B$24")="","",INDIRECT("'"&$B26&"'!$B$24")),"")) | BO26: =IF($B26="","",IFERROR(IF(INDIRECT("'"&$B26&"'!$B$25")="","",INDIRECT("'"&$B26&"'!$B$25")),"")) | BP26: =IF($B26="","",IFERROR(IF(INDIRECT("'"&$B26&"'!$B$26")="","",INDIRECT("'"&$B26&"'!$B$26")),"")) | BQ26: =IF($B26="","",IFERROR(IF(INDIRECT("'"&$B26&"'!$B$27")="","",INDIRECT("'"&$B26&"'!$B$27")),"")) | BR26: =IF($B26="","",IFERROR(IF(INDIRECT("'"&$B26&"'!$B$28")="","",INDIRECT("'"&$B26&"'!$B$28")),"")) | BS26: =IF($B26="","",IF(AK26="","",IF(ROUND(AK26-SUM(BN26:BR26),2)>0,"Verificar — pagamento sem fonte",IF(ROUND(AK26-SUM(BN26:BR26),2)<0,"Verificar — fonte > pago","OK"))))
A27: =IF('2027'!$E$31="","",'2027'!$E$31) | C27: =IF('2027'!$B$31="","",'2027'!$B$31) | D27: =IF('2027'!$C$31="","",'2027'!$C$31) | E27: =IF('2027'!$D$31="","",'2027'!$D$31) | F27: =IF('2027'!$E$31="","",'2027'!$E$31) | G27: =IF('2027'!$F$31="","",'2027'!$F$31) | H27: =IF('2027'!$H$31="","",'2027'!$H$31) | J27: =IF('2027'!$I$31="","",'2027'!$I$31) | K27: =IF($B27="","",IFERROR(IF(INDIRECT("'"&$B27&"'!$B$10")="","",INDIRECT("'"&$B27&"'!$B$10")),"")) | L27: =IF('2027'!$J$31="","",'2027'!$J$31) | M27: =IF('2027'!$K$31="","",'2027'!$K$31) | N27: =IF('2027'!$L$31="","",'2027'!$L$31) | O27: =IF($B27="","","SMD") | Q27: =IF($B27="","",IFERROR(IF(INDIRECT("'"&$B27&"'!$B$11")="","",INDIRECT("'"&$B27&"'!$B$11")),"")) | R27: =IF($B27="","",IFERROR(IF(INDIRECT("'"&$B27&"'!$F$11")="","",INDIRECT("'"&$B27&"'!$F$11")),"")) | S27: =IF($B27="","",IFERROR(IF(INDIRECT("'"&$B27&"'!$J$11")="","",INDIRECT("'"&$B27&"'!$J$11")),"")) | T27: =IF($B27="","",IFERROR(IF(INDIRECT("'"&$B27&"'!$J$10")="","",INDIRECT("'"&$B27&"'!$J$10")),"")) | U27: =IF($B27="","",IFERROR(IF(INDIRECT("'"&$B27&"'!$F$10")="","",INDIRECT("'"&$B27&"'!$F$10")),"")) | V27: =IF('2027'!$G$31="","",'2027'!$G$31) | X27: =IF($B27="","",IFERROR(IF(INDIRECT("'"&$B27&"'!$F$12")="","",INDIRECT("'"&$B27&"'!$F$12")),"")) | Y27: =IF($B27="","",IFERROR(IF(INDIRECT("'"&$B27&"'!$B$12")="","",INDIRECT("'"&$B27&"'!$B$12")),"")) | Z27: =IF($B27="","",IFERROR(IF(INDIRECT("'"&$B27&"'!$J$13")="","",INDIRECT("'"&$B27&"'!$J$13")),"")) | AB27: =IF($B27="","",IFERROR(IF(INDIRECT("'"&$B27&"'!$J$4")="","",INDIRECT("'"&$B27&"'!$J$4")),"")) | AC27: =IF($B27="","",2026) | AD27: =IF('2027'!$M$31="","",'2027'!$M$31) | AE27: =IF('2027'!$N$31="","",'2027'!$N$31) | AF27: =IF('2027'!$O$31="","",'2027'!$O$31) -> 0 | AI27: =IF('2027'!$Q$31="","",'2027'!$Q$31) | AJ27: =IF($B27="","",IFERROR(IF(INDIRECT("'"&$B27&"'!$D$21")="","",INDIRECT("'"&$B27&"'!$D$21")),"")) | AK27: =IF($B27="","",IFERROR(IF(INDIRECT("'"&$B27&"'!$E$21")="","",INDIRECT("'"&$B27&"'!$E$21")),"")) | AL27: =IF('2027'!$R$31="","",'2027'!$R$31) -> 0 | AM27: =IFERROR(AI27-AJ27,0) -> 0 | AN27: =IFERROR(AJ27-AK27,0) -> 0 | AO27: =IF('2027'!$S$31="","",'2027'!$S$31) -> 0 | AP27: =IFERROR(AK27/AF27,0) -> 0 | AQ27: =IF($B27="","",IFERROR(IF(INDIRECT("'"&$B27&"'!$K$21")="","",INDIRECT("'"&$B27&"'!$K$21")),"")) | AR27: =IF('2027'!$T$31="","",'2027'!$T$31) | AS27: =IF('2027'!$U$31="","",'2027'!$U$31) -> 0 | AT27: =IF($B27="","",IFERROR(IF(INDIRECT("'"&$B27&"'!$B$15")="","",INDIRECT("'"&$B27&"'!$B$15")),"")) | AV27: =IF($B27="","",IFERROR(IF(INDIRECT("'"&$B27&"'!$B$14")="","",INDIRECT("'"&$B27&"'!$B$14")),"")) | AW27: =IF($B27="","",AY27) | AX27: =IF($B27="","",IFERROR(IF(INDIRECT("'"&$B27&"'!$F$14")="","",INDIRECT("'"&$B27&"'!$F$14")),"")) | AY27: =IF($B27="","",IFERROR(IF(INDIRECT("'"&$B27&"'!$D$35")="","",INDIRECT("'"&$B27&"'!$D$35")),"")) | AZ27: =IF($B27="","",IFERROR(IF(INDIRECT("'"&$B27&"'!$J$14")="","",INDIRECT("'"&$B27&"'!$J$14")),"")) | BA27: =IF($B27="","",IFERROR(IF(INDIRECT("'"&$B27&"'!$I$21")="","",INDIRECT("'"&$B27&"'!$I$21")),"")) | BB27: =IF($B27="","",IFERROR(IF(INDIRECT("'"&$B27&"'!$C$67")="","",INDIRECT("'"&$B27&"'!$C$67")),"")) | BC27: =IF($B27="","",IFERROR(IF(INDIRECT("'"&$B27&"'!$D$68")="","",INDIRECT("'"&$B27&"'!$D$68")),"")) | BD27: =IFERROR(Z27+BB27-BC27,0) -> 0 | BE27: =IF($B27="","",IFERROR(IF(INDIRECT("'"&$B27&"'!$J$21")="","",INDIRECT("'"&$B27&"'!$J$21")),"")) | BF27: =IF($B27="","",IFERROR(IF(INDIRECT("'"&$B27&"'!$F$15")="","",INDIRECT("'"&$B27&"'!$F$15")),"")) | BG27: =IFERROR(N27-TODAY(),"") -> -46258 | BH27: =IF(N27="","",IF(AND(N27-TODAY()>=0,N27-TODAY()<=90),"Sim","Não")) | BI27: =IF(N27="","",IF(N27<TODAY(),"Sim","Não")) | BJ27: =IF(AF27=0,"",IF(IFERROR(AL27/AF27,0)<0.2,"Sim","Não")) | BK27: =IF(AF27=0,"",IF(IFERROR(AK27/AF27,0)>0.9,"Sim","Não")) | BL27: =IF(AY27="","",IF(TODAY()-AY27>60,"Sim","Não")) | BM27: =IF('2027'!$V$31="","",'2027'!$V$31) | BN27: =IF($B27="","",IFERROR(IF(INDIRECT("'"&$B27&"'!$B$24")="","",INDIRECT("'"&$B27&"'!$B$24")),"")) | BO27: =IF($B27="","",IFERROR(IF(INDIRECT("'"&$B27&"'!$B$25")="","",INDIRECT("'"&$B27&"'!$B$25")),"")) | BP27: =IF($B27="","",IFERROR(IF(INDIRECT("'"&$B27&"'!$B$26")="","",INDIRECT("'"&$B27&"'!$B$26")),"")) | BQ27: =IF($B27="","",IFERROR(IF(INDIRECT("'"&$B27&"'!$B$27")="","",INDIRECT("'"&$B27&"'!$B$27")),"")) | BR27: =IF($B27="","",IFERROR(IF(INDIRECT("'"&$B27&"'!$B$28")="","",INDIRECT("'"&$B27&"'!$B$28")),"")) | BS27: =IF($B27="","",IF(AK27="","",IF(ROUND(AK27-SUM(BN27:BR27),2)>0,"Verificar — pagamento sem fonte",IF(ROUND(AK27-SUM(BN27:BR27),2)<0,"Verificar — fonte > pago","OK"))))
A28: =IF('2027'!$E$32="","",'2027'!$E$32) | C28: =IF('2027'!$B$32="","",'2027'!$B$32) | D28: =IF('2027'!$C$32="","",'2027'!$C$32) | E28: =IF('2027'!$D$32="","",'2027'!$D$32) | F28: =IF('2027'!$E$32="","",'2027'!$E$32) | G28: =IF('2027'!$F$32="","",'2027'!$F$32) | H28: =IF('2027'!$H$32="","",'2027'!$H$32) | J28: =IF('2027'!$I$32="","",'2027'!$I$32) | K28: =IF($B28="","",IFERROR(IF(INDIRECT("'"&$B28&"'!$B$10")="","",INDIRECT("'"&$B28&"'!$B$10")),"")) | L28: =IF('2027'!$J$32="","",'2027'!$J$32) | M28: =IF('2027'!$K$32="","",'2027'!$K$32) | N28: =IF('2027'!$L$32="","",'2027'!$L$32) | O28: =IF($B28="","","SMD") | Q28: =IF($B28="","",IFERROR(IF(INDIRECT("'"&$B28&"'!$B$11")="","",INDIRECT("'"&$B28&"'!$B$11")),"")) | R28: =IF($B28="","",IFERROR(IF(INDIRECT("'"&$B28&"'!$F$11")="","",INDIRECT("'"&$B28&"'!$F$11")),"")) | S28: =IF($B28="","",IFERROR(IF(INDIRECT("'"&$B28&"'!$J$11")="","",INDIRECT("'"&$B28&"'!$J$11")),"")) | T28: =IF($B28="","",IFERROR(IF(INDIRECT("'"&$B28&"'!$J$10")="","",INDIRECT("'"&$B28&"'!$J$10")),"")) | U28: =IF($B28="","",IFERROR(IF(INDIRECT("'"&$B28&"'!$F$10")="","",INDIRECT("'"&$B28&"'!$F$10")),"")) | V28: =IF('2027'!$G$32="","",'2027'!$G$32) | X28: =IF($B28="","",IFERROR(IF(INDIRECT("'"&$B28&"'!$F$12")="","",INDIRECT("'"&$B28&"'!$F$12")),"")) | Y28: =IF($B28="","",IFERROR(IF(INDIRECT("'"&$B28&"'!$B$12")="","",INDIRECT("'"&$B28&"'!$B$12")),"")) | Z28: =IF($B28="","",IFERROR(IF(INDIRECT("'"&$B28&"'!$J$13")="","",INDIRECT("'"&$B28&"'!$J$13")),"")) | AB28: =IF($B28="","",IFERROR(IF(INDIRECT("'"&$B28&"'!$J$4")="","",INDIRECT("'"&$B28&"'!$J$4")),"")) | AC28: =IF($B28="","",2026) | AD28: =IF('2027'!$M$32="","",'2027'!$M$32) | AE28: =IF('2027'!$N$32="","",'2027'!$N$32) | AF28: =IF('2027'!$O$32="","",'2027'!$O$32) -> 0 | AI28: =IF('2027'!$Q$32="","",'2027'!$Q$32) | AJ28: =IF($B28="","",IFERROR(IF(INDIRECT("'"&$B28&"'!$D$21")="","",INDIRECT("'"&$B28&"'!$D$21")),"")) | AK28: =IF($B28="","",IFERROR(IF(INDIRECT("'"&$B28&"'!$E$21")="","",INDIRECT("'"&$B28&"'!$E$21")),"")) | AL28: =IF('2027'!$R$32="","",'2027'!$R$32) -> 0 | AM28: =IFERROR(AI28-AJ28,0) -> 0 | AN28: =IFERROR(AJ28-AK28,0) -> 0 | AO28: =IF('2027'!$S$32="","",'2027'!$S$32) -> 0 | AP28: =IFERROR(AK28/AF28,0) -> 0 | AQ28: =IF($B28="","",IFERROR(IF(INDIRECT("'"&$B28&"'!$K$21")="","",INDIRECT("'"&$B28&"'!$K$21")),"")) | AR28: =IF('2027'!$T$32="","",'2027'!$T$32) | AS28: =IF('2027'!$U$32="","",'2027'!$U$32) -> 0 | AT28: =IF($B28="","",IFERROR(IF(INDIRECT("'"&$B28&"'!$B$15")="","",INDIRECT("'"&$B28&"'!$B$15")),"")) | AV28: =IF($B28="","",IFERROR(IF(INDIRECT("'"&$B28&"'!$B$14")="","",INDIRECT("'"&$B28&"'!$B$14")),"")) | AW28: =IF($B28="","",AY28) | AX28: =IF($B28="","",IFERROR(IF(INDIRECT("'"&$B28&"'!$F$14")="","",INDIRECT("'"&$B28&"'!$F$14")),"")) | AY28: =IF($B28="","",IFERROR(IF(INDIRECT("'"&$B28&"'!$D$35")="","",INDIRECT("'"&$B28&"'!$D$35")),"")) | AZ28: =IF($B28="","",IFERROR(IF(INDIRECT("'"&$B28&"'!$J$14")="","",INDIRECT("'"&$B28&"'!$J$14")),"")) | BA28: =IF($B28="","",IFERROR(IF(INDIRECT("'"&$B28&"'!$I$21")="","",INDIRECT("'"&$B28&"'!$I$21")),"")) | BB28: =IF($B28="","",IFERROR(IF(INDIRECT("'"&$B28&"'!$C$67")="","",INDIRECT("'"&$B28&"'!$C$67")),"")) | BC28: =IF($B28="","",IFERROR(IF(INDIRECT("'"&$B28&"'!$D$68")="","",INDIRECT("'"&$B28&"'!$D$68")),"")) | BD28: =IFERROR(Z28+BB28-BC28,0) -> 0 | BE28: =IF($B28="","",IFERROR(IF(INDIRECT("'"&$B28&"'!$J$21")="","",INDIRECT("'"&$B28&"'!$J$21")),"")) | BF28: =IF($B28="","",IFERROR(IF(INDIRECT("'"&$B28&"'!$F$15")="","",INDIRECT("'"&$B28&"'!$F$15")),"")) | BG28: =IFERROR(N28-TODAY(),"") -> -46258 | BH28: =IF(N28="","",IF(AND(N28-TODAY()>=0,N28-TODAY()<=90),"Sim","Não")) | BI28: =IF(N28="","",IF(N28<TODAY(),"Sim","Não")) | BJ28: =IF(AF28=0,"",IF(IFERROR(AL28/AF28,0)<0.2,"Sim","Não")) | BK28: =IF(AF28=0,"",IF(IFERROR(AK28/AF28,0)>0.9,"Sim","Não")) | BL28: =IF(AY28="","",IF(TODAY()-AY28>60,"Sim","Não")) | BM28: =IF('2027'!$V$32="","",'2027'!$V$32) | BN28: =IF($B28="","",IFERROR(IF(INDIRECT("'"&$B28&"'!$B$24")="","",INDIRECT("'"&$B28&"'!$B$24")),"")) | BO28: =IF($B28="","",IFERROR(IF(INDIRECT("'"&$B28&"'!$B$25")="","",INDIRECT("'"&$B28&"'!$B$25")),"")) | BP28: =IF($B28="","",IFERROR(IF(INDIRECT("'"&$B28&"'!$B$26")="","",INDIRECT("'"&$B28&"'!$B$26")),"")) | BQ28: =IF($B28="","",IFERROR(IF(INDIRECT("'"&$B28&"'!$B$27")="","",INDIRECT("'"&$B28&"'!$B$27")),"")) | BR28: =IF($B28="","",IFERROR(IF(INDIRECT("'"&$B28&"'!$B$28")="","",INDIRECT("'"&$B28&"'!$B$28")),"")) | BS28: =IF($B28="","",IF(AK28="","",IF(ROUND(AK28-SUM(BN28:BR28),2)>0,"Verificar — pagamento sem fonte",IF(ROUND(AK28-SUM(BN28:BR28),2)<0,"Verificar — fonte > pago","OK"))))
A29: =IF('2027'!$E$33="","",'2027'!$E$33) | C29: =IF('2027'!$B$33="","",'2027'!$B$33) | D29: =IF('2027'!$C$33="","",'2027'!$C$33) | E29: =IF('2027'!$D$33="","",'2027'!$D$33) | F29: =IF('2027'!$E$33="","",'2027'!$E$33) | G29: =IF('2027'!$F$33="","",'2027'!$F$33) | H29: =IF('2027'!$H$33="","",'2027'!$H$33) | J29: =IF('2027'!$I$33="","",'2027'!$I$33) | K29: =IF($B29="","",IFERROR(IF(INDIRECT("'"&$B29&"'!$B$10")="","",INDIRECT("'"&$B29&"'!$B$10")),"")) | L29: =IF('2027'!$J$33="","",'2027'!$J$33) | M29: =IF('2027'!$K$33="","",'2027'!$K$33) | N29: =IF('2027'!$L$33="","",'2027'!$L$33) | O29: =IF($B29="","","SMD") | Q29: =IF($B29="","",IFERROR(IF(INDIRECT("'"&$B29&"'!$B$11")="","",INDIRECT("'"&$B29&"'!$B$11")),"")) | R29: =IF($B29="","",IFERROR(IF(INDIRECT("'"&$B29&"'!$F$11")="","",INDIRECT("'"&$B29&"'!$F$11")),"")) | S29: =IF($B29="","",IFERROR(IF(INDIRECT("'"&$B29&"'!$J$11")="","",INDIRECT("'"&$B29&"'!$J$11")),"")) | T29: =IF($B29="","",IFERROR(IF(INDIRECT("'"&$B29&"'!$J$10")="","",INDIRECT("'"&$B29&"'!$J$10")),"")) | U29: =IF($B29="","",IFERROR(IF(INDIRECT("'"&$B29&"'!$F$10")="","",INDIRECT("'"&$B29&"'!$F$10")),"")) | V29: =IF('2027'!$G$33="","",'2027'!$G$33) | X29: =IF($B29="","",IFERROR(IF(INDIRECT("'"&$B29&"'!$F$12")="","",INDIRECT("'"&$B29&"'!$F$12")),"")) | Y29: =IF($B29="","",IFERROR(IF(INDIRECT("'"&$B29&"'!$B$12")="","",INDIRECT("'"&$B29&"'!$B$12")),"")) | Z29: =IF($B29="","",IFERROR(IF(INDIRECT("'"&$B29&"'!$J$13")="","",INDIRECT("'"&$B29&"'!$J$13")),"")) | AB29: =IF($B29="","",IFERROR(IF(INDIRECT("'"&$B29&"'!$J$4")="","",INDIRECT("'"&$B29&"'!$J$4")),"")) | AC29: =IF($B29="","",2026) | AD29: =IF('2027'!$M$33="","",'2027'!$M$33) | AE29: =IF('2027'!$N$33="","",'2027'!$N$33) | AF29: =IF('2027'!$O$33="","",'2027'!$O$33) -> 0 | AI29: =IF('2027'!$Q$33="","",'2027'!$Q$33) | AJ29: =IF($B29="","",IFERROR(IF(INDIRECT("'"&$B29&"'!$D$21")="","",INDIRECT("'"&$B29&"'!$D$21")),"")) | AK29: =IF($B29="","",IFERROR(IF(INDIRECT("'"&$B29&"'!$E$21")="","",INDIRECT("'"&$B29&"'!$E$21")),"")) | AL29: =IF('2027'!$R$33="","",'2027'!$R$33) -> 0 | AM29: =IFERROR(AI29-AJ29,0) -> 0 | AN29: =IFERROR(AJ29-AK29,0) -> 0 | AO29: =IF('2027'!$S$33="","",'2027'!$S$33) -> 0 | AP29: =IFERROR(AK29/AF29,0) -> 0 | AQ29: =IF($B29="","",IFERROR(IF(INDIRECT("'"&$B29&"'!$K$21")="","",INDIRECT("'"&$B29&"'!$K$21")),"")) | AR29: =IF('2027'!$T$33="","",'2027'!$T$33) | AS29: =IF('2027'!$U$33="","",'2027'!$U$33) -> 0 | AT29: =IF($B29="","",IFERROR(IF(INDIRECT("'"&$B29&"'!$B$15")="","",INDIRECT("'"&$B29&"'!$B$15")),"")) | AV29: =IF($B29="","",IFERROR(IF(INDIRECT("'"&$B29&"'!$B$14")="","",INDIRECT("'"&$B29&"'!$B$14")),"")) | AW29: =IF($B29="","",AY29) | AX29: =IF($B29="","",IFERROR(IF(INDIRECT("'"&$B29&"'!$F$14")="","",INDIRECT("'"&$B29&"'!$F$14")),"")) | AY29: =IF($B29="","",IFERROR(IF(INDIRECT("'"&$B29&"'!$D$35")="","",INDIRECT("'"&$B29&"'!$D$35")),"")) | AZ29: =IF($B29="","",IFERROR(IF(INDIRECT("'"&$B29&"'!$J$14")="","",INDIRECT("'"&$B29&"'!$J$14")),"")) | BA29: =IF($B29="","",IFERROR(IF(INDIRECT("'"&$B29&"'!$I$21")="","",INDIRECT("'"&$B29&"'!$I$21")),"")) | BB29: =IF($B29="","",IFERROR(IF(INDIRECT("'"&$B29&"'!$C$67")="","",INDIRECT("'"&$B29&"'!$C$67")),"")) | BC29: =IF($B29="","",IFERROR(IF(INDIRECT("'"&$B29&"'!$D$68")="","",INDIRECT("'"&$B29&"'!$D$68")),"")) | BD29: =IFERROR(Z29+BB29-BC29,0) -> 0 | BE29: =IF($B29="","",IFERROR(IF(INDIRECT("'"&$B29&"'!$J$21")="","",INDIRECT("'"&$B29&"'!$J$21")),"")) | BF29: =IF($B29="","",IFERROR(IF(INDIRECT("'"&$B29&"'!$F$15")="","",INDIRECT("'"&$B29&"'!$F$15")),"")) | BG29: =IFERROR(N29-TODAY(),"") -> -46258 | BH29: =IF(N29="","",IF(AND(N29-TODAY()>=0,N29-TODAY()<=90),"Sim","Não")) | BI29: =IF(N29="","",IF(N29<TODAY(),"Sim","Não")) | BJ29: =IF(AF29=0,"",IF(IFERROR(AL29/AF29,0)<0.2,"Sim","Não")) | BK29: =IF(AF29=0,"",IF(IFERROR(AK29/AF29,0)>0.9,"Sim","Não")) | BL29: =IF(AY29="","",IF(TODAY()-AY29>60,"Sim","Não")) | BM29: =IF('2027'!$V$33="","",'2027'!$V$33) | BN29: =IF($B29="","",IFERROR(IF(INDIRECT("'"&$B29&"'!$B$24")="","",INDIRECT("'"&$B29&"'!$B$24")),"")) | BO29: =IF($B29="","",IFERROR(IF(INDIRECT("'"&$B29&"'!$B$25")="","",INDIRECT("'"&$B29&"'!$B$25")),"")) | BP29: =IF($B29="","",IFERROR(IF(INDIRECT("'"&$B29&"'!$B$26")="","",INDIRECT("'"&$B29&"'!$B$26")),"")) | BQ29: =IF($B29="","",IFERROR(IF(INDIRECT("'"&$B29&"'!$B$27")="","",INDIRECT("'"&$B29&"'!$B$27")),"")) | BR29: =IF($B29="","",IFERROR(IF(INDIRECT("'"&$B29&"'!$B$28")="","",INDIRECT("'"&$B29&"'!$B$28")),"")) | BS29: =IF($B29="","",IF(AK29="","",IF(ROUND(AK29-SUM(BN29:BR29),2)>0,"Verificar — pagamento sem fonte",IF(ROUND(AK29-SUM(BN29:BR29),2)<0,"Verificar — fonte > pago","OK"))))
A30: =IF('2027'!$E$34="","",'2027'!$E$34) | C30: =IF('2027'!$B$34="","",'2027'!$B$34) | D30: =IF('2027'!$C$34="","",'2027'!$C$34) | E30: =IF('2027'!$D$34="","",'2027'!$D$34) | F30: =IF('2027'!$E$34="","",'2027'!$E$34) | G30: =IF('2027'!$F$34="","",'2027'!$F$34) | H30: =IF('2027'!$H$34="","",'2027'!$H$34) | J30: =IF('2027'!$I$34="","",'2027'!$I$34) | K30: =IF($B30="","",IFERROR(IF(INDIRECT("'"&$B30&"'!$B$10")="","",INDIRECT("'"&$B30&"'!$B$10")),"")) | L30: =IF('2027'!$J$34="","",'2027'!$J$34) | M30: =IF('2027'!$K$34="","",'2027'!$K$34) | N30: =IF('2027'!$L$34="","",'2027'!$L$34) | O30: =IF($B30="","","SMD") | Q30: =IF($B30="","",IFERROR(IF(INDIRECT("'"&$B30&"'!$B$11")="","",INDIRECT("'"&$B30&"'!$B$11")),"")) | R30: =IF($B30="","",IFERROR(IF(INDIRECT("'"&$B30&"'!$F$11")="","",INDIRECT("'"&$B30&"'!$F$11")),"")) | S30: =IF($B30="","",IFERROR(IF(INDIRECT("'"&$B30&"'!$J$11")="","",INDIRECT("'"&$B30&"'!$J$11")),"")) | T30: =IF($B30="","",IFERROR(IF(INDIRECT("'"&$B30&"'!$J$10")="","",INDIRECT("'"&$B30&"'!$J$10")),"")) | U30: =IF($B30="","",IFERROR(IF(INDIRECT("'"&$B30&"'!$F$10")="","",INDIRECT("'"&$B30&"'!$F$10")),"")) | V30: =IF('2027'!$G$34="","",'2027'!$G$34) | X30: =IF($B30="","",IFERROR(IF(INDIRECT("'"&$B30&"'!$F$12")="","",INDIRECT("'"&$B30&"'!$F$12")),"")) | Y30: =IF($B30="","",IFERROR(IF(INDIRECT("'"&$B30&"'!$B$12")="","",INDIRECT("'"&$B30&"'!$B$12")),"")) | Z30: =IF($B30="","",IFERROR(IF(INDIRECT("'"&$B30&"'!$J$13")="","",INDIRECT("'"&$B30&"'!$J$13")),"")) | AB30: =IF($B30="","",IFERROR(IF(INDIRECT("'"&$B30&"'!$J$4")="","",INDIRECT("'"&$B30&"'!$J$4")),"")) | AC30: =IF($B30="","",2026) | AD30: =IF('2027'!$M$34="","",'2027'!$M$34) | AE30: =IF('2027'!$N$34="","",'2027'!$N$34) | AF30: =IF('2027'!$O$34="","",'2027'!$O$34) -> 0 | AI30: =IF('2027'!$Q$34="","",'2027'!$Q$34) | AJ30: =IF($B30="","",IFERROR(IF(INDIRECT("'"&$B30&"'!$D$21")="","",INDIRECT("'"&$B30&"'!$D$21")),"")) | AK30: =IF($B30="","",IFERROR(IF(INDIRECT("'"&$B30&"'!$E$21")="","",INDIRECT("'"&$B30&"'!$E$21")),"")) | AL30: =IF('2027'!$R$34="","",'2027'!$R$34) -> 0 | AM30: =IFERROR(AI30-AJ30,0) -> 0 | AN30: =IFERROR(AJ30-AK30,0) -> 0 | AO30: =IF('2027'!$S$34="","",'2027'!$S$34) -> 0 | AP30: =IFERROR(AK30/AF30,0) -> 0 | AQ30: =IF($B30="","",IFERROR(IF(INDIRECT("'"&$B30&"'!$K$21")="","",INDIRECT("'"&$B30&"'!$K$21")),"")) | AR30: =IF('2027'!$T$34="","",'2027'!$T$34) | AS30: =IF('2027'!$U$34="","",'2027'!$U$34) -> 0 | AT30: =IF($B30="","",IFERROR(IF(INDIRECT("'"&$B30&"'!$B$15")="","",INDIRECT("'"&$B30&"'!$B$15")),"")) | AV30: =IF($B30="","",IFERROR(IF(INDIRECT("'"&$B30&"'!$B$14")="","",INDIRECT("'"&$B30&"'!$B$14")),"")) | AW30: =IF($B30="","",AY30) | AX30: =IF($B30="","",IFERROR(IF(INDIRECT("'"&$B30&"'!$F$14")="","",INDIRECT("'"&$B30&"'!$F$14")),"")) | AY30: =IF($B30="","",IFERROR(IF(INDIRECT("'"&$B30&"'!$D$35")="","",INDIRECT("'"&$B30&"'!$D$35")),"")) | AZ30: =IF($B30="","",IFERROR(IF(INDIRECT("'"&$B30&"'!$J$14")="","",INDIRECT("'"&$B30&"'!$J$14")),"")) | BA30: =IF($B30="","",IFERROR(IF(INDIRECT("'"&$B30&"'!$I$21")="","",INDIRECT("'"&$B30&"'!$I$21")),"")) | BB30: =IF($B30="","",IFERROR(IF(INDIRECT("'"&$B30&"'!$C$67")="","",INDIRECT("'"&$B30&"'!$C$67")),"")) | BC30: =IF($B30="","",IFERROR(IF(INDIRECT("'"&$B30&"'!$D$68")="","",INDIRECT("'"&$B30&"'!$D$68")),"")) | BD30: =IFERROR(Z30+BB30-BC30,0) -> 0 | BE30: =IF($B30="","",IFERROR(IF(INDIRECT("'"&$B30&"'!$J$21")="","",INDIRECT("'"&$B30&"'!$J$21")),"")) | BF30: =IF($B30="","",IFERROR(IF(INDIRECT("'"&$B30&"'!$F$15")="","",INDIRECT("'"&$B30&"'!$F$15")),"")) | BG30: =IFERROR(N30-TODAY(),"") -> -46258 | BH30: =IF(N30="","",IF(AND(N30-TODAY()>=0,N30-TODAY()<=90),"Sim","Não")) | BI30: =IF(N30="","",IF(N30<TODAY(),"Sim","Não")) | BJ30: =IF(AF30=0,"",IF(IFERROR(AL30/AF30,0)<0.2,"Sim","Não")) | BK30: =IF(AF30=0,"",IF(IFERROR(AK30/AF30,0)>0.9,"Sim","Não")) | BL30: =IF(AY30="","",IF(TODAY()-AY30>60,"Sim","Não")) | BM30: =IF('2027'!$V$34="","",'2027'!$V$34) | BN30: =IF($B30="","",IFERROR(IF(INDIRECT("'"&$B30&"'!$B$24")="","",INDIRECT("'"&$B30&"'!$B$24")),"")) | BO30: =IF($B30="","",IFERROR(IF(INDIRECT("'"&$B30&"'!$B$25")="","",INDIRECT("'"&$B30&"'!$B$25")),"")) | BP30: =IF($B30="","",IFERROR(IF(INDIRECT("'"&$B30&"'!$B$26")="","",INDIRECT("'"&$B30&"'!$B$26")),"")) | BQ30: =IF($B30="","",IFERROR(IF(INDIRECT("'"&$B30&"'!$B$27")="","",INDIRECT("'"&$B30&"'!$B$27")),"")) | BR30: =IF($B30="","",IFERROR(IF(INDIRECT("'"&$B30&"'!$B$28")="","",INDIRECT("'"&$B30&"'!$B$28")),"")) | BS30: =IF($B30="","",IF(AK30="","",IF(ROUND(AK30-SUM(BN30:BR30),2)>0,"Verificar — pagamento sem fonte",IF(ROUND(AK30-SUM(BN30:BR30),2)<0,"Verificar — fonte > pago","OK"))))
A31: =IF('2027'!$E$35="","",'2027'!$E$35) | C31: =IF('2027'!$B$35="","",'2027'!$B$35) | D31: =IF('2027'!$C$35="","",'2027'!$C$35) | E31: =IF('2027'!$D$35="","",'2027'!$D$35) | F31: =IF('2027'!$E$35="","",'2027'!$E$35) | G31: =IF('2027'!$F$35="","",'2027'!$F$35) | H31: =IF('2027'!$H$35="","",'2027'!$H$35) | J31: =IF('2027'!$I$35="","",'2027'!$I$35) | K31: =IF($B31="","",IFERROR(IF(INDIRECT("'"&$B31&"'!$B$10")="","",INDIRECT("'"&$B31&"'!$B$10")),"")) | L31: =IF('2027'!$J$35="","",'2027'!$J$35) | M31: =IF('2027'!$K$35="","",'2027'!$K$35) | N31: =IF('2027'!$L$35="","",'2027'!$L$35) | O31: =IF($B31="","","SMD") | Q31: =IF($B31="","",IFERROR(IF(INDIRECT("'"&$B31&"'!$B$11")="","",INDIRECT("'"&$B31&"'!$B$11")),"")) | R31: =IF($B31="","",IFERROR(IF(INDIRECT("'"&$B31&"'!$F$11")="","",INDIRECT("'"&$B31&"'!$F$11")),"")) | S31: =IF($B31="","",IFERROR(IF(INDIRECT("'"&$B31&"'!$J$11")="","",INDIRECT("'"&$B31&"'!$J$11")),"")) | T31: =IF($B31="","",IFERROR(IF(INDIRECT("'"&$B31&"'!$J$10")="","",INDIRECT("'"&$B31&"'!$J$10")),"")) | U31: =IF($B31="","",IFERROR(IF(INDIRECT("'"&$B31&"'!$F$10")="","",INDIRECT("'"&$B31&"'!$F$10")),"")) | V31: =IF('2027'!$G$35="","",'2027'!$G$35) | X31: =IF($B31="","",IFERROR(IF(INDIRECT("'"&$B31&"'!$F$12")="","",INDIRECT("'"&$B31&"'!$F$12")),"")) | Y31: =IF($B31="","",IFERROR(IF(INDIRECT("'"&$B31&"'!$B$12")="","",INDIRECT("'"&$B31&"'!$B$12")),"")) | Z31: =IF($B31="","",IFERROR(IF(INDIRECT("'"&$B31&"'!$J$13")="","",INDIRECT("'"&$B31&"'!$J$13")),"")) | AB31: =IF($B31="","",IFERROR(IF(INDIRECT("'"&$B31&"'!$J$4")="","",INDIRECT("'"&$B31&"'!$J$4")),"")) | AC31: =IF($B31="","",2026) | AD31: =IF('2027'!$M$35="","",'2027'!$M$35) | AE31: =IF('2027'!$N$35="","",'2027'!$N$35) | AF31: =IF('2027'!$O$35="","",'2027'!$O$35) -> 0 | AI31: =IF('2027'!$Q$35="","",'2027'!$Q$35) | AJ31: =IF($B31="","",IFERROR(IF(INDIRECT("'"&$B31&"'!$D$21")="","",INDIRECT("'"&$B31&"'!$D$21")),"")) | AK31: =IF($B31="","",IFERROR(IF(INDIRECT("'"&$B31&"'!$E$21")="","",INDIRECT("'"&$B31&"'!$E$21")),"")) | AL31: =IF('2027'!$R$35="","",'2027'!$R$35) -> 0 | AM31: =IFERROR(AI31-AJ31,0) -> 0 | AN31: =IFERROR(AJ31-AK31,0) -> 0 | AO31: =IF('2027'!$S$35="","",'2027'!$S$35) -> 0 | AP31: =IFERROR(AK31/AF31,0) -> 0 | AQ31: =IF($B31="","",IFERROR(IF(INDIRECT("'"&$B31&"'!$K$21")="","",INDIRECT("'"&$B31&"'!$K$21")),"")) | AR31: =IF('2027'!$T$35="","",'2027'!$T$35) | AS31: =IF('2027'!$U$35="","",'2027'!$U$35) -> 0 | AT31: =IF($B31="","",IFERROR(IF(INDIRECT("'"&$B31&"'!$B$15")="","",INDIRECT("'"&$B31&"'!$B$15")),"")) | AV31: =IF($B31="","",IFERROR(IF(INDIRECT("'"&$B31&"'!$B$14")="","",INDIRECT("'"&$B31&"'!$B$14")),"")) | AW31: =IF($B31="","",AY31) | AX31: =IF($B31="","",IFERROR(IF(INDIRECT("'"&$B31&"'!$F$14")="","",INDIRECT("'"&$B31&"'!$F$14")),"")) | AY31: =IF($B31="","",IFERROR(IF(INDIRECT("'"&$B31&"'!$D$35")="","",INDIRECT("'"&$B31&"'!$D$35")),"")) | AZ31: =IF($B31="","",IFERROR(IF(INDIRECT("'"&$B31&"'!$J$14")="","",INDIRECT("'"&$B31&"'!$J$14")),"")) | BA31: =IF($B31="","",IFERROR(IF(INDIRECT("'"&$B31&"'!$I$21")="","",INDIRECT("'"&$B31&"'!$I$21")),"")) | BB31: =IF($B31="","",IFERROR(IF(INDIRECT("'"&$B31&"'!$C$67")="","",INDIRECT("'"&$B31&"'!$C$67")),"")) | BC31: =IF($B31="","",IFERROR(IF(INDIRECT("'"&$B31&"'!$D$68")="","",INDIRECT("'"&$B31&"'!$D$68")),"")) | BD31: =IFERROR(Z31+BB31-BC31,0) -> 0 | BE31: =IF($B31="","",IFERROR(IF(INDIRECT("'"&$B31&"'!$J$21")="","",INDIRECT("'"&$B31&"'!$J$21")),"")) | BF31: =IF($B31="","",IFERROR(IF(INDIRECT("'"&$B31&"'!$F$15")="","",INDIRECT("'"&$B31&"'!$F$15")),"")) | BG31: =IFERROR(N31-TODAY(),"") -> -46258 | BH31: =IF(N31="","",IF(AND(N31-TODAY()>=0,N31-TODAY()<=90),"Sim","Não")) | BI31: =IF(N31="","",IF(N31<TODAY(),"Sim","Não")) | BJ31: =IF(AF31=0,"",IF(IFERROR(AL31/AF31,0)<0.2,"Sim","Não")) | BK31: =IF(AF31=0,"",IF(IFERROR(AK31/AF31,0)>0.9,"Sim","Não")) | BL31: =IF(AY31="","",IF(TODAY()-AY31>60,"Sim","Não")) | BM31: =IF('2027'!$V$35="","",'2027'!$V$35) | BN31: =IF($B31="","",IFERROR(IF(INDIRECT("'"&$B31&"'!$B$24")="","",INDIRECT("'"&$B31&"'!$B$24")),"")) | BO31: =IF($B31="","",IFERROR(IF(INDIRECT("'"&$B31&"'!$B$25")="","",INDIRECT("'"&$B31&"'!$B$25")),"")) | BP31: =IF($B31="","",IFERROR(IF(INDIRECT("'"&$B31&"'!$B$26")="","",INDIRECT("'"&$B31&"'!$B$26")),"")) | BQ31: =IF($B31="","",IFERROR(IF(INDIRECT("'"&$B31&"'!$B$27")="","",INDIRECT("'"&$B31&"'!$B$27")),"")) | BR31: =IF($B31="","",IFERROR(IF(INDIRECT("'"&$B31&"'!$B$28")="","",INDIRECT("'"&$B31&"'!$B$28")),"")) | BS31: =IF($B31="","",IF(AK31="","",IF(ROUND(AK31-SUM(BN31:BR31),2)>0,"Verificar — pagamento sem fonte",IF(ROUND(AK31-SUM(BN31:BR31),2)<0,"Verificar — fonte > pago","OK"))))
A32: =IF('2027'!$E$36="","",'2027'!$E$36) | C32: =IF('2027'!$B$36="","",'2027'!$B$36) | D32: =IF('2027'!$C$36="","",'2027'!$C$36) | E32: =IF('2027'!$D$36="","",'2027'!$D$36) | F32: =IF('2027'!$E$36="","",'2027'!$E$36) | G32: =IF('2027'!$F$36="","",'2027'!$F$36) | H32: =IF('2027'!$H$36="","",'2027'!$H$36) | J32: =IF('2027'!$I$36="","",'2027'!$I$36) | K32: =IF($B32="","",IFERROR(IF(INDIRECT("'"&$B32&"'!$B$10")="","",INDIRECT("'"&$B32&"'!$B$10")),"")) | L32: =IF('2027'!$J$36="","",'2027'!$J$36) | M32: =IF('2027'!$K$36="","",'2027'!$K$36) | N32: =IF('2027'!$L$36="","",'2027'!$L$36) | O32: =IF($B32="","","SMD") | Q32: =IF($B32="","",IFERROR(IF(INDIRECT("'"&$B32&"'!$B$11")="","",INDIRECT("'"&$B32&"'!$B$11")),"")) | R32: =IF($B32="","",IFERROR(IF(INDIRECT("'"&$B32&"'!$F$11")="","",INDIRECT("'"&$B32&"'!$F$11")),"")) | S32: =IF($B32="","",IFERROR(IF(INDIRECT("'"&$B32&"'!$J$11")="","",INDIRECT("'"&$B32&"'!$J$11")),"")) | T32: =IF($B32="","",IFERROR(IF(INDIRECT("'"&$B32&"'!$J$10")="","",INDIRECT("'"&$B32&"'!$J$10")),"")) | U32: =IF($B32="","",IFERROR(IF(INDIRECT("'"&$B32&"'!$F$10")="","",INDIRECT("'"&$B32&"'!$F$10")),"")) | V32: =IF('2027'!$G$36="","",'2027'!$G$36) | X32: =IF($B32="","",IFERROR(IF(INDIRECT("'"&$B32&"'!$F$12")="","",INDIRECT("'"&$B32&"'!$F$12")),"")) | Y32: =IF($B32="","",IFERROR(IF(INDIRECT("'"&$B32&"'!$B$12")="","",INDIRECT("'"&$B32&"'!$B$12")),"")) | Z32: =IF($B32="","",IFERROR(IF(INDIRECT("'"&$B32&"'!$J$13")="","",INDIRECT("'"&$B32&"'!$J$13")),"")) | AB32: =IF($B32="","",IFERROR(IF(INDIRECT("'"&$B32&"'!$J$4")="","",INDIRECT("'"&$B32&"'!$J$4")),"")) | AC32: =IF($B32="","",2026) | AD32: =IF('2027'!$M$36="","",'2027'!$M$36) | AE32: =IF('2027'!$N$36="","",'2027'!$N$36) | AF32: =IF('2027'!$O$36="","",'2027'!$O$36) -> 0 | AI32: =IF('2027'!$Q$36="","",'2027'!$Q$36) | AJ32: =IF($B32="","",IFERROR(IF(INDIRECT("'"&$B32&"'!$D$21")="","",INDIRECT("'"&$B32&"'!$D$21")),"")) | AK32: =IF($B32="","",IFERROR(IF(INDIRECT("'"&$B32&"'!$E$21")="","",INDIRECT("'"&$B32&"'!$E$21")),"")) | AL32: =IF('2027'!$R$36="","",'2027'!$R$36) -> 0 | AM32: =IFERROR(AI32-AJ32,0) -> 0 | AN32: =IFERROR(AJ32-AK32,0) -> 0 | AO32: =IF('2027'!$S$36="","",'2027'!$S$36) -> 0 | AP32: =IFERROR(AK32/AF32,0) -> 0 | AQ32: =IF($B32="","",IFERROR(IF(INDIRECT("'"&$B32&"'!$K$21")="","",INDIRECT("'"&$B32&"'!$K$21")),"")) | AR32: =IF('2027'!$T$36="","",'2027'!$T$36) | AS32: =IF('2027'!$U$36="","",'2027'!$U$36) -> 0 | AT32: =IF($B32="","",IFERROR(IF(INDIRECT("'"&$B32&"'!$B$15")="","",INDIRECT("'"&$B32&"'!$B$15")),"")) | AV32: =IF($B32="","",IFERROR(IF(INDIRECT("'"&$B32&"'!$B$14")="","",INDIRECT("'"&$B32&"'!$B$14")),"")) | AW32: =IF($B32="","",AY32) | AX32: =IF($B32="","",IFERROR(IF(INDIRECT("'"&$B32&"'!$F$14")="","",INDIRECT("'"&$B32&"'!$F$14")),"")) | AY32: =IF($B32="","",IFERROR(IF(INDIRECT("'"&$B32&"'!$D$35")="","",INDIRECT("'"&$B32&"'!$D$35")),"")) | AZ32: =IF($B32="","",IFERROR(IF(INDIRECT("'"&$B32&"'!$J$14")="","",INDIRECT("'"&$B32&"'!$J$14")),"")) | BA32: =IF($B32="","",IFERROR(IF(INDIRECT("'"&$B32&"'!$I$21")="","",INDIRECT("'"&$B32&"'!$I$21")),"")) | BB32: =IF($B32="","",IFERROR(IF(INDIRECT("'"&$B32&"'!$C$67")="","",INDIRECT("'"&$B32&"'!$C$67")),"")) | BC32: =IF($B32="","",IFERROR(IF(INDIRECT("'"&$B32&"'!$D$68")="","",INDIRECT("'"&$B32&"'!$D$68")),"")) | BD32: =IFERROR(Z32+BB32-BC32,0) -> 0 | BE32: =IF($B32="","",IFERROR(IF(INDIRECT("'"&$B32&"'!$J$21")="","",INDIRECT("'"&$B32&"'!$J$21")),"")) | BF32: =IF($B32="","",IFERROR(IF(INDIRECT("'"&$B32&"'!$F$15")="","",INDIRECT("'"&$B32&"'!$F$15")),"")) | BG32: =IFERROR(N32-TODAY(),"") -> -46258 | BH32: =IF(N32="","",IF(AND(N32-TODAY()>=0,N32-TODAY()<=90),"Sim","Não")) | BI32: =IF(N32="","",IF(N32<TODAY(),"Sim","Não")) | BJ32: =IF(AF32=0,"",IF(IFERROR(AL32/AF32,0)<0.2,"Sim","Não")) | BK32: =IF(AF32=0,"",IF(IFERROR(AK32/AF32,0)>0.9,"Sim","Não")) | BL32: =IF(AY32="","",IF(TODAY()-AY32>60,"Sim","Não")) | BM32: =IF('2027'!$V$36="","",'2027'!$V$36) | BN32: =IF($B32="","",IFERROR(IF(INDIRECT("'"&$B32&"'!$B$24")="","",INDIRECT("'"&$B32&"'!$B$24")),"")) | BO32: =IF($B32="","",IFERROR(IF(INDIRECT("'"&$B32&"'!$B$25")="","",INDIRECT("'"&$B32&"'!$B$25")),"")) | BP32: =IF($B32="","",IFERROR(IF(INDIRECT("'"&$B32&"'!$B$26")="","",INDIRECT("'"&$B32&"'!$B$26")),"")) | BQ32: =IF($B32="","",IFERROR(IF(INDIRECT("'"&$B32&"'!$B$27")="","",INDIRECT("'"&$B32&"'!$B$27")),"")) | BR32: =IF($B32="","",IFERROR(IF(INDIRECT("'"&$B32&"'!$B$28")="","",INDIRECT("'"&$B32&"'!$B$28")),"")) | BS32: =IF($B32="","",IF(AK32="","",IF(ROUND(AK32-SUM(BN32:BR32),2)>0,"Verificar — pagamento sem fonte",IF(ROUND(AK32-SUM(BN32:BR32),2)<0,"Verificar — fonte > pago","OK"))))
A33: =IF('2027'!$E$37="","",'2027'!$E$37) | C33: =IF('2027'!$B$37="","",'2027'!$B$37) | D33: =IF('2027'!$C$37="","",'2027'!$C$37) | E33: =IF('2027'!$D$37="","",'2027'!$D$37) | F33: =IF('2027'!$E$37="","",'2027'!$E$37) | G33: =IF('2027'!$F$37="","",'2027'!$F$37) | H33: =IF('2027'!$H$37="","",'2027'!$H$37) | J33: =IF('2027'!$I$37="","",'2027'!$I$37) | K33: =IF($B33="","",IFERROR(IF(INDIRECT("'"&$B33&"'!$B$10")="","",INDIRECT("'"&$B33&"'!$B$10")),"")) | L33: =IF('2027'!$J$37="","",'2027'!$J$37) | M33: =IF('2027'!$K$37="","",'2027'!$K$37) | N33: =IF('2027'!$L$37="","",'2027'!$L$37) | O33: =IF($B33="","","SMD") | Q33: =IF($B33="","",IFERROR(IF(INDIRECT("'"&$B33&"'!$B$11")="","",INDIRECT("'"&$B33&"'!$B$11")),"")) | R33: =IF($B33="","",IFERROR(IF(INDIRECT("'"&$B33&"'!$F$11")="","",INDIRECT("'"&$B33&"'!$F$11")),"")) | S33: =IF($B33="","",IFERROR(IF(INDIRECT("'"&$B33&"'!$J$11")="","",INDIRECT("'"&$B33&"'!$J$11")),"")) | T33: =IF($B33="","",IFERROR(IF(INDIRECT("'"&$B33&"'!$J$10")="","",INDIRECT("'"&$B33&"'!$J$10")),"")) | U33: =IF($B33="","",IFERROR(IF(INDIRECT("'"&$B33&"'!$F$10")="","",INDIRECT("'"&$B33&"'!$F$10")),"")) | V33: =IF('2027'!$G$37="","",'2027'!$G$37) | X33: =IF($B33="","",IFERROR(IF(INDIRECT("'"&$B33&"'!$F$12")="","",INDIRECT("'"&$B33&"'!$F$12")),"")) | Y33: =IF($B33="","",IFERROR(IF(INDIRECT("'"&$B33&"'!$B$12")="","",INDIRECT("'"&$B33&"'!$B$12")),"")) | Z33: =IF($B33="","",IFERROR(IF(INDIRECT("'"&$B33&"'!$J$13")="","",INDIRECT("'"&$B33&"'!$J$13")),"")) | AB33: =IF($B33="","",IFERROR(IF(INDIRECT("'"&$B33&"'!$J$4")="","",INDIRECT("'"&$B33&"'!$J$4")),"")) | AC33: =IF($B33="","",2026) | AD33: =IF('2027'!$M$37="","",'2027'!$M$37) | AE33: =IF('2027'!$N$37="","",'2027'!$N$37) | AF33: =IF('2027'!$O$37="","",'2027'!$O$37) -> 0 | AI33: =IF('2027'!$Q$37="","",'2027'!$Q$37) | AJ33: =IF($B33="","",IFERROR(IF(INDIRECT("'"&$B33&"'!$D$21")="","",INDIRECT("'"&$B33&"'!$D$21")),"")) | AK33: =IF($B33="","",IFERROR(IF(INDIRECT("'"&$B33&"'!$E$21")="","",INDIRECT("'"&$B33&"'!$E$21")),"")) | AL33: =IF('2027'!$R$37="","",'2027'!$R$37) -> 0 | AM33: =IFERROR(AI33-AJ33,0) -> 0 | AN33: =IFERROR(AJ33-AK33,0) -> 0 | AO33: =IF('2027'!$S$37="","",'2027'!$S$37) -> 0 | AP33: =IFERROR(AK33/AF33,0) -> 0 | AQ33: =IF($B33="","",IFERROR(IF(INDIRECT("'"&$B33&"'!$K$21")="","",INDIRECT("'"&$B33&"'!$K$21")),"")) | AR33: =IF('2027'!$T$37="","",'2027'!$T$37) | AS33: =IF('2027'!$U$37="","",'2027'!$U$37) -> 0 | AT33: =IF($B33="","",IFERROR(IF(INDIRECT("'"&$B33&"'!$B$15")="","",INDIRECT("'"&$B33&"'!$B$15")),"")) | AV33: =IF($B33="","",IFERROR(IF(INDIRECT("'"&$B33&"'!$B$14")="","",INDIRECT("'"&$B33&"'!$B$14")),"")) | AW33: =IF($B33="","",AY33) | AX33: =IF($B33="","",IFERROR(IF(INDIRECT("'"&$B33&"'!$F$14")="","",INDIRECT("'"&$B33&"'!$F$14")),"")) | AY33: =IF($B33="","",IFERROR(IF(INDIRECT("'"&$B33&"'!$D$35")="","",INDIRECT("'"&$B33&"'!$D$35")),"")) | AZ33: =IF($B33="","",IFERROR(IF(INDIRECT("'"&$B33&"'!$J$14")="","",INDIRECT("'"&$B33&"'!$J$14")),"")) | BA33: =IF($B33="","",IFERROR(IF(INDIRECT("'"&$B33&"'!$I$21")="","",INDIRECT("'"&$B33&"'!$I$21")),"")) | BB33: =IF($B33="","",IFERROR(IF(INDIRECT("'"&$B33&"'!$C$67")="","",INDIRECT("'"&$B33&"'!$C$67")),"")) | BC33: =IF($B33="","",IFERROR(IF(INDIRECT("'"&$B33&"'!$D$68")="","",INDIRECT("'"&$B33&"'!$D$68")),"")) | BD33: =IFERROR(Z33+BB33-BC33,0) -> 0 | BE33: =IF($B33="","",IFERROR(IF(INDIRECT("'"&$B33&"'!$J$21")="","",INDIRECT("'"&$B33&"'!$J$21")),"")) | BF33: =IF($B33="","",IFERROR(IF(INDIRECT("'"&$B33&"'!$F$15")="","",INDIRECT("'"&$B33&"'!$F$15")),"")) | BG33: =IFERROR(N33-TODAY(),"") -> -46258 | BH33: =IF(N33="","",IF(AND(N33-TODAY()>=0,N33-TODAY()<=90),"Sim","Não")) | BI33: =IF(N33="","",IF(N33<TODAY(),"Sim","Não")) | BJ33: =IF(AF33=0,"",IF(IFERROR(AL33/AF33,0)<0.2,"Sim","Não")) | BK33: =IF(AF33=0,"",IF(IFERROR(AK33/AF33,0)>0.9,"Sim","Não")) | BL33: =IF(AY33="","",IF(TODAY()-AY33>60,"Sim","Não")) | BM33: =IF('2027'!$V$37="","",'2027'!$V$37) | BN33: =IF($B33="","",IFERROR(IF(INDIRECT("'"&$B33&"'!$B$24")="","",INDIRECT("'"&$B33&"'!$B$24")),"")) | BO33: =IF($B33="","",IFERROR(IF(INDIRECT("'"&$B33&"'!$B$25")="","",INDIRECT("'"&$B33&"'!$B$25")),"")) | BP33: =IF($B33="","",IFERROR(IF(INDIRECT("'"&$B33&"'!$B$26")="","",INDIRECT("'"&$B33&"'!$B$26")),"")) | BQ33: =IF($B33="","",IFERROR(IF(INDIRECT("'"&$B33&"'!$B$27")="","",INDIRECT("'"&$B33&"'!$B$27")),"")) | BR33: =IF($B33="","",IFERROR(IF(INDIRECT("'"&$B33&"'!$B$28")="","",INDIRECT("'"&$B33&"'!$B$28")),"")) | BS33: =IF($B33="","",IF(AK33="","",IF(ROUND(AK33-SUM(BN33:BR33),2)>0,"Verificar — pagamento sem fonte",IF(ROUND(AK33-SUM(BN33:BR33),2)<0,"Verificar — fonte > pago","OK"))))
A34: =IF('2027'!$E$38="","",'2027'!$E$38) | C34: =IF('2027'!$B$38="","",'2027'!$B$38) | D34: =IF('2027'!$C$38="","",'2027'!$C$38) | E34: =IF('2027'!$D$38="","",'2027'!$D$38) | F34: =IF('2027'!$E$38="","",'2027'!$E$38) | G34: =IF('2027'!$F$38="","",'2027'!$F$38) | H34: =IF('2027'!$H$38="","",'2027'!$H$38) | J34: =IF('2027'!$I$38="","",'2027'!$I$38) | K34: =IF($B34="","",IFERROR(IF(INDIRECT("'"&$B34&"'!$B$10")="","",INDIRECT("'"&$B34&"'!$B$10")),"")) | L34: =IF('2027'!$J$38="","",'2027'!$J$38) | M34: =IF('2027'!$K$38="","",'2027'!$K$38) | N34: =IF('2027'!$L$38="","",'2027'!$L$38) | O34: =IF($B34="","","SMD") | Q34: =IF($B34="","",IFERROR(IF(INDIRECT("'"&$B34&"'!$B$11")="","",INDIRECT("'"&$B34&"'!$B$11")),"")) | R34: =IF($B34="","",IFERROR(IF(INDIRECT("'"&$B34&"'!$F$11")="","",INDIRECT("'"&$B34&"'!$F$11")),"")) | S34: =IF($B34="","",IFERROR(IF(INDIRECT("'"&$B34&"'!$J$11")="","",INDIRECT("'"&$B34&"'!$J$11")),"")) | T34: =IF($B34="","",IFERROR(IF(INDIRECT("'"&$B34&"'!$J$10")="","",INDIRECT("'"&$B34&"'!$J$10")),"")) | U34: =IF($B34="","",IFERROR(IF(INDIRECT("'"&$B34&"'!$F$10")="","",INDIRECT("'"&$B34&"'!$F$10")),"")) | V34: =IF('2027'!$G$38="","",'2027'!$G$38) | X34: =IF($B34="","",IFERROR(IF(INDIRECT("'"&$B34&"'!$F$12")="","",INDIRECT("'"&$B34&"'!$F$12")),"")) | Y34: =IF($B34="","",IFERROR(IF(INDIRECT("'"&$B34&"'!$B$12")="","",INDIRECT("'"&$B34&"'!$B$12")),"")) | Z34: =IF($B34="","",IFERROR(IF(INDIRECT("'"&$B34&"'!$J$13")="","",INDIRECT("'"&$B34&"'!$J$13")),"")) | AB34: =IF($B34="","",IFERROR(IF(INDIRECT("'"&$B34&"'!$J$4")="","",INDIRECT("'"&$B34&"'!$J$4")),"")) | AC34: =IF($B34="","",2026) | AD34: =IF('2027'!$M$38="","",'2027'!$M$38) | AE34: =IF('2027'!$N$38="","",'2027'!$N$38) | AF34: =IF('2027'!$O$38="","",'2027'!$O$38) -> 0 | AI34: =IF('2027'!$Q$38="","",'2027'!$Q$38) | AJ34: =IF($B34="","",IFERROR(IF(INDIRECT("'"&$B34&"'!$D$21")="","",INDIRECT("'"&$B34&"'!$D$21")),"")) | AK34: =IF($B34="","",IFERROR(IF(INDIRECT("'"&$B34&"'!$E$21")="","",INDIRECT("'"&$B34&"'!$E$21")),"")) | AL34: =IF('2027'!$R$38="","",'2027'!$R$38) -> 0 | AM34: =IFERROR(AI34-AJ34,0) -> 0 | AN34: =IFERROR(AJ34-AK34,0) -> 0 | AO34: =IF('2027'!$S$38="","",'2027'!$S$38) -> 0 | AP34: =IFERROR(AK34/AF34,0) -> 0 | AQ34: =IF($B34="","",IFERROR(IF(INDIRECT("'"&$B34&"'!$K$21")="","",INDIRECT("'"&$B34&"'!$K$21")),"")) | AR34: =IF('2027'!$T$38="","",'2027'!$T$38) | AS34: =IF('2027'!$U$38="","",'2027'!$U$38) -> 0 | AT34: =IF($B34="","",IFERROR(IF(INDIRECT("'"&$B34&"'!$B$15")="","",INDIRECT("'"&$B34&"'!$B$15")),"")) | AV34: =IF($B34="","",IFERROR(IF(INDIRECT("'"&$B34&"'!$B$14")="","",INDIRECT("'"&$B34&"'!$B$14")),"")) | AW34: =IF($B34="","",AY34) | AX34: =IF($B34="","",IFERROR(IF(INDIRECT("'"&$B34&"'!$F$14")="","",INDIRECT("'"&$B34&"'!$F$14")),"")) | AY34: =IF($B34="","",IFERROR(IF(INDIRECT("'"&$B34&"'!$D$35")="","",INDIRECT("'"&$B34&"'!$D$35")),"")) | AZ34: =IF($B34="","",IFERROR(IF(INDIRECT("'"&$B34&"'!$J$14")="","",INDIRECT("'"&$B34&"'!$J$14")),"")) | BA34: =IF($B34="","",IFERROR(IF(INDIRECT("'"&$B34&"'!$I$21")="","",INDIRECT("'"&$B34&"'!$I$21")),"")) | BB34: =IF($B34="","",IFERROR(IF(INDIRECT("'"&$B34&"'!$C$67")="","",INDIRECT("'"&$B34&"'!$C$67")),"")) | BC34: =IF($B34="","",IFERROR(IF(INDIRECT("'"&$B34&"'!$D$68")="","",INDIRECT("'"&$B34&"'!$D$68")),"")) | BD34: =IFERROR(Z34+BB34-BC34,0) -> 0 | BE34: =IF($B34="","",IFERROR(IF(INDIRECT("'"&$B34&"'!$J$21")="","",INDIRECT("'"&$B34&"'!$J$21")),"")) | BF34: =IF($B34="","",IFERROR(IF(INDIRECT("'"&$B34&"'!$F$15")="","",INDIRECT("'"&$B34&"'!$F$15")),"")) | BG34: =IFERROR(N34-TODAY(),"") -> -46258 | BH34: =IF(N34="","",IF(AND(N34-TODAY()>=0,N34-TODAY()<=90),"Sim","Não")) | BI34: =IF(N34="","",IF(N34<TODAY(),"Sim","Não")) | BJ34: =IF(AF34=0,"",IF(IFERROR(AL34/AF34,0)<0.2,"Sim","Não")) | BK34: =IF(AF34=0,"",IF(IFERROR(AK34/AF34,0)>0.9,"Sim","Não")) | BL34: =IF(AY34="","",IF(TODAY()-AY34>60,"Sim","Não")) | BM34: =IF('2027'!$V$38="","",'2027'!$V$38) | BN34: =IF($B34="","",IFERROR(IF(INDIRECT("'"&$B34&"'!$B$24")="","",INDIRECT("'"&$B34&"'!$B$24")),"")) | BO34: =IF($B34="","",IFERROR(IF(INDIRECT("'"&$B34&"'!$B$25")="","",INDIRECT("'"&$B34&"'!$B$25")),"")) | BP34: =IF($B34="","",IFERROR(IF(INDIRECT("'"&$B34&"'!$B$26")="","",INDIRECT("'"&$B34&"'!$B$26")),"")) | BQ34: =IF($B34="","",IFERROR(IF(INDIRECT("'"&$B34&"'!$B$27")="","",INDIRECT("'"&$B34&"'!$B$27")),"")) | BR34: =IF($B34="","",IFERROR(IF(INDIRECT("'"&$B34&"'!$B$28")="","",INDIRECT("'"&$B34&"'!$B$28")),"")) | BS34: =IF($B34="","",IF(AK34="","",IF(ROUND(AK34-SUM(BN34:BR34),2)>0,"Verificar — pagamento sem fonte",IF(ROUND(AK34-SUM(BN34:BR34),2)<0,"Verificar — fonte > pago","OK"))))
A35: =IF('2027'!$E$39="","",'2027'!$E$39) | C35: =IF('2027'!$B$39="","",'2027'!$B$39) | D35: =IF('2027'!$C$39="","",'2027'!$C$39) | E35: =IF('2027'!$D$39="","",'2027'!$D$39) | F35: =IF('2027'!$E$39="","",'2027'!$E$39) | G35: =IF('2027'!$F$39="","",'2027'!$F$39) | H35: =IF('2027'!$H$39="","",'2027'!$H$39) | J35: =IF('2027'!$I$39="","",'2027'!$I$39) | K35: =IF($B35="","",IFERROR(IF(INDIRECT("'"&$B35&"'!$B$10")="","",INDIRECT("'"&$B35&"'!$B$10")),"")) | L35: =IF('2027'!$J$39="","",'2027'!$J$39) | M35: =IF('2027'!$K$39="","",'2027'!$K$39) | N35: =IF('2027'!$L$39="","",'2027'!$L$39) | O35: =IF($B35="","","SMD") | Q35: =IF($B35="","",IFERROR(IF(INDIRECT("'"&$B35&"'!$B$11")="","",INDIRECT("'"&$B35&"'!$B$11")),"")) | R35: =IF($B35="","",IFERROR(IF(INDIRECT("'"&$B35&"'!$F$11")="","",INDIRECT("'"&$B35&"'!$F$11")),"")) | S35: =IF($B35="","",IFERROR(IF(INDIRECT("'"&$B35&"'!$J$11")="","",INDIRECT("'"&$B35&"'!$J$11")),"")) | T35: =IF($B35="","",IFERROR(IF(INDIRECT("'"&$B35&"'!$J$10")="","",INDIRECT("'"&$B35&"'!$J$10")),"")) | U35: =IF($B35="","",IFERROR(IF(INDIRECT("'"&$B35&"'!$F$10")="","",INDIRECT("'"&$B35&"'!$F$10")),"")) | V35: =IF('2027'!$G$39="","",'2027'!$G$39) | X35: =IF($B35="","",IFERROR(IF(INDIRECT("'"&$B35&"'!$F$12")="","",INDIRECT("'"&$B35&"'!$F$12")),"")) | Y35: =IF($B35="","",IFERROR(IF(INDIRECT("'"&$B35&"'!$B$12")="","",INDIRECT("'"&$B35&"'!$B$12")),"")) | Z35: =IF($B35="","",IFERROR(IF(INDIRECT("'"&$B35&"'!$J$13")="","",INDIRECT("'"&$B35&"'!$J$13")),"")) | AB35: =IF($B35="","",IFERROR(IF(INDIRECT("'"&$B35&"'!$J$4")="","",INDIRECT("'"&$B35&"'!$J$4")),"")) | AC35: =IF($B35="","",2026) | AD35: =IF('2027'!$M$39="","",'2027'!$M$39) | AE35: =IF('2027'!$N$39="","",'2027'!$N$39) | AF35: =IF('2027'!$O$39="","",'2027'!$O$39) -> 0 | AI35: =IF('2027'!$Q$39="","",'2027'!$Q$39) | AJ35: =IF($B35="","",IFERROR(IF(INDIRECT("'"&$B35&"'!$D$21")="","",INDIRECT("'"&$B35&"'!$D$21")),"")) | AK35: =IF($B35="","",IFERROR(IF(INDIRECT("'"&$B35&"'!$E$21")="","",INDIRECT("'"&$B35&"'!$E$21")),"")) | AL35: =IF('2027'!$R$39="","",'2027'!$R$39) -> 0 | AM35: =IFERROR(AI35-AJ35,0) -> 0 | AN35: =IFERROR(AJ35-AK35,0) -> 0 | AO35: =IF('2027'!$S$39="","",'2027'!$S$39) -> 0 | AP35: =IFERROR(AK35/AF35,0) -> 0 | AQ35: =IF($B35="","",IFERROR(IF(INDIRECT("'"&$B35&"'!$K$21")="","",INDIRECT("'"&$B35&"'!$K$21")),"")) | AR35: =IF('2027'!$T$39="","",'2027'!$T$39) | AS35: =IF('2027'!$U$39="","",'2027'!$U$39) -> 0 | AT35: =IF($B35="","",IFERROR(IF(INDIRECT("'"&$B35&"'!$B$15")="","",INDIRECT("'"&$B35&"'!$B$15")),"")) | AV35: =IF($B35="","",IFERROR(IF(INDIRECT("'"&$B35&"'!$B$14")="","",INDIRECT("'"&$B35&"'!$B$14")),"")) | AW35: =IF($B35="","",AY35) | AX35: =IF($B35="","",IFERROR(IF(INDIRECT("'"&$B35&"'!$F$14")="","",INDIRECT("'"&$B35&"'!$F$14")),"")) | AY35: =IF($B35="","",IFERROR(IF(INDIRECT("'"&$B35&"'!$D$35")="","",INDIRECT("'"&$B35&"'!$D$35")),"")) | AZ35: =IF($B35="","",IFERROR(IF(INDIRECT("'"&$B35&"'!$J$14")="","",INDIRECT("'"&$B35&"'!$J$14")),"")) | BA35: =IF($B35="","",IFERROR(IF(INDIRECT("'"&$B35&"'!$I$21")="","",INDIRECT("'"&$B35&"'!$I$21")),"")) | BB35: =IF($B35="","",IFERROR(IF(INDIRECT("'"&$B35&"'!$C$67")="","",INDIRECT("'"&$B35&"'!$C$67")),"")) | BC35: =IF($B35="","",IFERROR(IF(INDIRECT("'"&$B35&"'!$D$68")="","",INDIRECT("'"&$B35&"'!$D$68")),"")) | BD35: =IFERROR(Z35+BB35-BC35,0) -> 0 | BE35: =IF($B35="","",IFERROR(IF(INDIRECT("'"&$B35&"'!$J$21")="","",INDIRECT("'"&$B35&"'!$J$21")),"")) | BF35: =IF($B35="","",IFERROR(IF(INDIRECT("'"&$B35&"'!$F$15")="","",INDIRECT("'"&$B35&"'!$F$15")),"")) | BG35: =IFERROR(N35-TODAY(),"") -> -46258 | BH35: =IF(N35="","",IF(AND(N35-TODAY()>=0,N35-TODAY()<=90),"Sim","Não")) | BI35: =IF(N35="","",IF(N35<TODAY(),"Sim","Não")) | BJ35: =IF(AF35=0,"",IF(IFERROR(AL35/AF35,0)<0.2,"Sim","Não")) | BK35: =IF(AF35=0,"",IF(IFERROR(AK35/AF35,0)>0.9,"Sim","Não")) | BL35: =IF(AY35="","",IF(TODAY()-AY35>60,"Sim","Não")) | BM35: =IF('2027'!$V$39="","",'2027'!$V$39) | BN35: =IF($B35="","",IFERROR(IF(INDIRECT("'"&$B35&"'!$B$24")="","",INDIRECT("'"&$B35&"'!$B$24")),"")) | BO35: =IF($B35="","",IFERROR(IF(INDIRECT("'"&$B35&"'!$B$25")="","",INDIRECT("'"&$B35&"'!$B$25")),"")) | BP35: =IF($B35="","",IFERROR(IF(INDIRECT("'"&$B35&"'!$B$26")="","",INDIRECT("'"&$B35&"'!$B$26")),"")) | BQ35: =IF($B35="","",IFERROR(IF(INDIRECT("'"&$B35&"'!$B$27")="","",INDIRECT("'"&$B35&"'!$B$27")),"")) | BR35: =IF($B35="","",IFERROR(IF(INDIRECT("'"&$B35&"'!$B$28")="","",INDIRECT("'"&$B35&"'!$B$28")),"")) | BS35: =IF($B35="","",IF(AK35="","",IF(ROUND(AK35-SUM(BN35:BR35),2)>0,"Verificar — pagamento sem fonte",IF(ROUND(AK35-SUM(BN35:BR35),2)<0,"Verificar — fonte > pago","OK"))))
A36: =IF('2027'!$E$40="","",'2027'!$E$40) | C36: =IF('2027'!$B$40="","",'2027'!$B$40) | D36: =IF('2027'!$C$40="","",'2027'!$C$40) | E36: =IF('2027'!$D$40="","",'2027'!$D$40) | F36: =IF('2027'!$E$40="","",'2027'!$E$40) | G36: =IF('2027'!$F$40="","",'2027'!$F$40) | H36: =IF('2027'!$H$40="","",'2027'!$H$40) | J36: =IF('2027'!$I$40="","",'2027'!$I$40) | K36: =IF($B36="","",IFERROR(IF(INDIRECT("'"&$B36&"'!$B$10")="","",INDIRECT("'"&$B36&"'!$B$10")),"")) | L36: =IF('2027'!$J$40="","",'2027'!$J$40) | M36: =IF('2027'!$K$40="","",'2027'!$K$40) | N36: =IF('2027'!$L$40="","",'2027'!$L$40) | O36: =IF($B36="","","SMD") | Q36: =IF($B36="","",IFERROR(IF(INDIRECT("'"&$B36&"'!$B$11")="","",INDIRECT("'"&$B36&"'!$B$11")),"")) | R36: =IF($B36="","",IFERROR(IF(INDIRECT("'"&$B36&"'!$F$11")="","",INDIRECT("'"&$B36&"'!$F$11")),"")) | S36: =IF($B36="","",IFERROR(IF(INDIRECT("'"&$B36&"'!$J$11")="","",INDIRECT("'"&$B36&"'!$J$11")),"")) | T36: =IF($B36="","",IFERROR(IF(INDIRECT("'"&$B36&"'!$J$10")="","",INDIRECT("'"&$B36&"'!$J$10")),"")) | U36: =IF($B36="","",IFERROR(IF(INDIRECT("'"&$B36&"'!$F$10")="","",INDIRECT("'"&$B36&"'!$F$10")),"")) | V36: =IF('2027'!$G$40="","",'2027'!$G$40) | X36: =IF($B36="","",IFERROR(IF(INDIRECT("'"&$B36&"'!$F$12")="","",INDIRECT("'"&$B36&"'!$F$12")),"")) | Y36: =IF($B36="","",IFERROR(IF(INDIRECT("'"&$B36&"'!$B$12")="","",INDIRECT("'"&$B36&"'!$B$12")),"")) | Z36: =IF($B36="","",IFERROR(IF(INDIRECT("'"&$B36&"'!$J$13")="","",INDIRECT("'"&$B36&"'!$J$13")),"")) | AB36: =IF($B36="","",IFERROR(IF(INDIRECT("'"&$B36&"'!$J$4")="","",INDIRECT("'"&$B36&"'!$J$4")),"")) | AC36: =IF($B36="","",2026) | AD36: =IF('2027'!$M$40="","",'2027'!$M$40) | AE36: =IF('2027'!$N$40="","",'2027'!$N$40) | AF36: =IF('2027'!$O$40="","",'2027'!$O$40) -> 0 | AI36: =IF('2027'!$Q$40="","",'2027'!$Q$40) | AJ36: =IF($B36="","",IFERROR(IF(INDIRECT("'"&$B36&"'!$D$21")="","",INDIRECT("'"&$B36&"'!$D$21")),"")) | AK36: =IF($B36="","",IFERROR(IF(INDIRECT("'"&$B36&"'!$E$21")="","",INDIRECT("'"&$B36&"'!$E$21")),"")) | AL36: =IF('2027'!$R$40="","",'2027'!$R$40) -> 0 | AM36: =IFERROR(AI36-AJ36,0) -> 0 | AN36: =IFERROR(AJ36-AK36,0) -> 0 | AO36: =IF('2027'!$S$40="","",'2027'!$S$40) -> 0 | AP36: =IFERROR(AK36/AF36,0) -> 0 | AQ36: =IF($B36="","",IFERROR(IF(INDIRECT("'"&$B36&"'!$K$21")="","",INDIRECT("'"&$B36&"'!$K$21")),"")) | AR36: =IF('2027'!$T$40="","",'2027'!$T$40) | AS36: =IF('2027'!$U$40="","",'2027'!$U$40) -> 0 | AT36: =IF($B36="","",IFERROR(IF(INDIRECT("'"&$B36&"'!$B$15")="","",INDIRECT("'"&$B36&"'!$B$15")),"")) | AV36: =IF($B36="","",IFERROR(IF(INDIRECT("'"&$B36&"'!$B$14")="","",INDIRECT("'"&$B36&"'!$B$14")),"")) | AW36: =IF($B36="","",AY36) | AX36: =IF($B36="","",IFERROR(IF(INDIRECT("'"&$B36&"'!$F$14")="","",INDIRECT("'"&$B36&"'!$F$14")),"")) | AY36: =IF($B36="","",IFERROR(IF(INDIRECT("'"&$B36&"'!$D$35")="","",INDIRECT("'"&$B36&"'!$D$35")),"")) | AZ36: =IF($B36="","",IFERROR(IF(INDIRECT("'"&$B36&"'!$J$14")="","",INDIRECT("'"&$B36&"'!$J$14")),"")) | BA36: =IF($B36="","",IFERROR(IF(INDIRECT("'"&$B36&"'!$I$21")="","",INDIRECT("'"&$B36&"'!$I$21")),"")) | BB36: =IF($B36="","",IFERROR(IF(INDIRECT("'"&$B36&"'!$C$67")="","",INDIRECT("'"&$B36&"'!$C$67")),"")) | BC36: =IF($B36="","",IFERROR(IF(INDIRECT("'"&$B36&"'!$D$68")="","",INDIRECT("'"&$B36&"'!$D$68")),"")) | BD36: =IFERROR(Z36+BB36-BC36,0) -> 0 | BE36: =IF($B36="","",IFERROR(IF(INDIRECT("'"&$B36&"'!$J$21")="","",INDIRECT("'"&$B36&"'!$J$21")),"")) | BF36: =IF($B36="","",IFERROR(IF(INDIRECT("'"&$B36&"'!$F$15")="","",INDIRECT("'"&$B36&"'!$F$15")),"")) | BG36: =IFERROR(N36-TODAY(),"") -> -46258 | BH36: =IF(N36="","",IF(AND(N36-TODAY()>=0,N36-TODAY()<=90),"Sim","Não")) | BI36: =IF(N36="","",IF(N36<TODAY(),"Sim","Não")) | BJ36: =IF(AF36=0,"",IF(IFERROR(AL36/AF36,0)<0.2,"Sim","Não")) | BK36: =IF(AF36=0,"",IF(IFERROR(AK36/AF36,0)>0.9,"Sim","Não")) | BL36: =IF(AY36="","",IF(TODAY()-AY36>60,"Sim","Não")) | BM36: =IF('2027'!$V$40="","",'2027'!$V$40) | BN36: =IF($B36="","",IFERROR(IF(INDIRECT("'"&$B36&"'!$B$24")="","",INDIRECT("'"&$B36&"'!$B$24")),"")) | BO36: =IF($B36="","",IFERROR(IF(INDIRECT("'"&$B36&"'!$B$25")="","",INDIRECT("'"&$B36&"'!$B$25")),"")) | BP36: =IF($B36="","",IFERROR(IF(INDIRECT("'"&$B36&"'!$B$26")="","",INDIRECT("'"&$B36&"'!$B$26")),"")) | BQ36: =IF($B36="","",IFERROR(IF(INDIRECT("'"&$B36&"'!$B$27")="","",INDIRECT("'"&$B36&"'!$B$27")),"")) | BR36: =IF($B36="","",IFERROR(IF(INDIRECT("'"&$B36&"'!$B$28")="","",INDIRECT("'"&$B36&"'!$B$28")),"")) | BS36: =IF($B36="","",IF(AK36="","",IF(ROUND(AK36-SUM(BN36:BR36),2)>0,"Verificar — pagamento sem fonte",IF(ROUND(AK36-SUM(BN36:BR36),2)<0,"Verificar — fonte > pago","OK"))))
A37: =IF('2027'!$E$41="","",'2027'!$E$41) | C37: =IF('2027'!$B$41="","",'2027'!$B$41) | D37: =IF('2027'!$C$41="","",'2027'!$C$41) | E37: =IF('2027'!$D$41="","",'2027'!$D$41) | F37: =IF('2027'!$E$41="","",'2027'!$E$41) | G37: =IF('2027'!$F$41="","",'2027'!$F$41) | H37: =IF('2027'!$H$41="","",'2027'!$H$41) | J37: =IF('2027'!$I$41="","",'2027'!$I$41) | K37: =IF($B37="","",IFERROR(IF(INDIRECT("'"&$B37&"'!$B$10")="","",INDIRECT("'"&$B37&"'!$B$10")),"")) | L37: =IF('2027'!$J$41="","",'2027'!$J$41) | M37: =IF('2027'!$K$41="","",'2027'!$K$41) | N37: =IF('2027'!$L$41="","",'2027'!$L$41) | O37: =IF($B37="","","SMD") | Q37: =IF($B37="","",IFERROR(IF(INDIRECT("'"&$B37&"'!$B$11")="","",INDIRECT("'"&$B37&"'!$B$11")),"")) | R37: =IF($B37="","",IFERROR(IF(INDIRECT("'"&$B37&"'!$F$11")="","",INDIRECT("'"&$B37&"'!$F$11")),"")) | S37: =IF($B37="","",IFERROR(IF(INDIRECT("'"&$B37&"'!$J$11")="","",INDIRECT("'"&$B37&"'!$J$11")),"")) | T37: =IF($B37="","",IFERROR(IF(INDIRECT("'"&$B37&"'!$J$10")="","",INDIRECT("'"&$B37&"'!$J$10")),"")) | U37: =IF($B37="","",IFERROR(IF(INDIRECT("'"&$B37&"'!$F$10")="","",INDIRECT("'"&$B37&"'!$F$10")),"")) | V37: =IF('2027'!$G$41="","",'2027'!$G$41) | X37: =IF($B37="","",IFERROR(IF(INDIRECT("'"&$B37&"'!$F$12")="","",INDIRECT("'"&$B37&"'!$F$12")),"")) | Y37: =IF($B37="","",IFERROR(IF(INDIRECT("'"&$B37&"'!$B$12")="","",INDIRECT("'"&$B37&"'!$B$12")),"")) | Z37: =IF($B37="","",IFERROR(IF(INDIRECT("'"&$B37&"'!$J$13")="","",INDIRECT("'"&$B37&"'!$J$13")),"")) | AB37: =IF($B37="","",IFERROR(IF(INDIRECT("'"&$B37&"'!$J$4")="","",INDIRECT("'"&$B37&"'!$J$4")),"")) | AC37: =IF($B37="","",2026) | AD37: =IF('2027'!$M$41="","",'2027'!$M$41) | AE37: =IF('2027'!$N$41="","",'2027'!$N$41) | AF37: =IF('2027'!$O$41="","",'2027'!$O$41) -> 0 | AI37: =IF('2027'!$Q$41="","",'2027'!$Q$41) | AJ37: =IF($B37="","",IFERROR(IF(INDIRECT("'"&$B37&"'!$D$21")="","",INDIRECT("'"&$B37&"'!$D$21")),"")) | AK37: =IF($B37="","",IFERROR(IF(INDIRECT("'"&$B37&"'!$E$21")="","",INDIRECT("'"&$B37&"'!$E$21")),"")) | AL37: =IF('2027'!$R$41="","",'2027'!$R$41) -> 0 | AM37: =IFERROR(AI37-AJ37,0) -> 0 | AN37: =IFERROR(AJ37-AK37,0) -> 0 | AO37: =IF('2027'!$S$41="","",'2027'!$S$41) -> 0 | AP37: =IFERROR(AK37/AF37,0) -> 0 | AQ37: =IF($B37="","",IFERROR(IF(INDIRECT("'"&$B37&"'!$K$21")="","",INDIRECT("'"&$B37&"'!$K$21")),"")) | AR37: =IF('2027'!$T$41="","",'2027'!$T$41) | AS37: =IF('2027'!$U$41="","",'2027'!$U$41) -> 0 | AT37: =IF($B37="","",IFERROR(IF(INDIRECT("'"&$B37&"'!$B$15")="","",INDIRECT("'"&$B37&"'!$B$15")),"")) | AV37: =IF($B37="","",IFERROR(IF(INDIRECT("'"&$B37&"'!$B$14")="","",INDIRECT("'"&$B37&"'!$B$14")),"")) | AW37: =IF($B37="","",AY37) | AX37: =IF($B37="","",IFERROR(IF(INDIRECT("'"&$B37&"'!$F$14")="","",INDIRECT("'"&$B37&"'!$F$14")),"")) | AY37: =IF($B37="","",IFERROR(IF(INDIRECT("'"&$B37&"'!$D$35")="","",INDIRECT("'"&$B37&"'!$D$35")),"")) | AZ37: =IF($B37="","",IFERROR(IF(INDIRECT("'"&$B37&"'!$J$14")="","",INDIRECT("'"&$B37&"'!$J$14")),"")) | BA37: =IF($B37="","",IFERROR(IF(INDIRECT("'"&$B37&"'!$I$21")="","",INDIRECT("'"&$B37&"'!$I$21")),"")) | BB37: =IF($B37="","",IFERROR(IF(INDIRECT("'"&$B37&"'!$C$67")="","",INDIRECT("'"&$B37&"'!$C$67")),"")) | BC37: =IF($B37="","",IFERROR(IF(INDIRECT("'"&$B37&"'!$D$68")="","",INDIRECT("'"&$B37&"'!$D$68")),"")) | BD37: =IFERROR(Z37+BB37-BC37,0) -> 0 | BE37: =IF($B37="","",IFERROR(IF(INDIRECT("'"&$B37&"'!$J$21")="","",INDIRECT("'"&$B37&"'!$J$21")),"")) | BF37: =IF($B37="","",IFERROR(IF(INDIRECT("'"&$B37&"'!$F$15")="","",INDIRECT("'"&$B37&"'!$F$15")),"")) | BG37: =IFERROR(N37-TODAY(),"") -> -46258 | BH37: =IF(N37="","",IF(AND(N37-TODAY()>=0,N37-TODAY()<=90),"Sim","Não")) | BI37: =IF(N37="","",IF(N37<TODAY(),"Sim","Não")) | BJ37: =IF(AF37=0,"",IF(IFERROR(AL37/AF37,0)<0.2,"Sim","Não")) | BK37: =IF(AF37=0,"",IF(IFERROR(AK37/AF37,0)>0.9,"Sim","Não")) | BL37: =IF(AY37="","",IF(TODAY()-AY37>60,"Sim","Não")) | BM37: =IF('2027'!$V$41="","",'2027'!$V$41) | BN37: =IF($B37="","",IFERROR(IF(INDIRECT("'"&$B37&"'!$B$24")="","",INDIRECT("'"&$B37&"'!$B$24")),"")) | BO37: =IF($B37="","",IFERROR(IF(INDIRECT("'"&$B37&"'!$B$25")="","",INDIRECT("'"&$B37&"'!$B$25")),"")) | BP37: =IF($B37="","",IFERROR(IF(INDIRECT("'"&$B37&"'!$B$26")="","",INDIRECT("'"&$B37&"'!$B$26")),"")) | BQ37: =IF($B37="","",IFERROR(IF(INDIRECT("'"&$B37&"'!$B$27")="","",INDIRECT("'"&$B37&"'!$B$27")),"")) | BR37: =IF($B37="","",IFERROR(IF(INDIRECT("'"&$B37&"'!$B$28")="","",INDIRECT("'"&$B37&"'!$B$28")),"")) | BS37: =IF($B37="","",IF(AK37="","",IF(ROUND(AK37-SUM(BN37:BR37),2)>0,"Verificar — pagamento sem fonte",IF(ROUND(AK37-SUM(BN37:BR37),2)<0,"Verificar — fonte > pago","OK"))))
